package o;

import android.content.Context;
import android.os.Build.VERSION;
import android.util.Pair;
import dalvik.system.DexClassLoader;
import java.io.File;
import java.io.FileInputStream;
import java.io.FileOutputStream;
import java.io.IOException;
import java.lang.reflect.Method;
import java.security.NoSuchAlgorithmException;
import java.util.Arrays;
import java.util.Collection;
import java.util.Collections;
import java.util.HashMap;
import java.util.List;
import java.util.Map;
import java.util.Set;
import java.util.concurrent.ExecutionException;
import java.util.concurrent.ExecutorService;
import java.util.concurrent.Executors;
import java.util.concurrent.Future;
import java.util.concurrent.TimeUnit;
import java.util.concurrent.TimeoutException;

public final class kb
{
  private static Object atm = new Object();
  private static hd ato = null;
  Context Nt;
  private volatile boolean asJ = false;
  ExecutorService atb;
  DexClassLoader atc;
  jz atd;
  byte[] ate;
  private volatile ᑈ atf = null;
  private Future atg = null;
  volatile is.if ath = null;
  Future ati = null;
  je atj;
  acv atk = null;
  boolean atl = false;
  private boolean atn = false;
  boolean atp = false;
  private Map<Pair<String, String>, ku> atq;
  
  private kb(Context paramContext)
  {
    Nt = paramContext;
    atq = new HashMap();
  }
  
  public static kb ˊ(Context paramContext, String paramString1, String paramString2, boolean paramBoolean)
  {
    paramContext = new kb(paramContext);
    try
    {
      paramContext.ˊ(paramString1, paramString2, paramBoolean);
      return paramContext;
    }
    catch (ka paramContext)
    {
      for (;;) {}
    }
    return null;
  }
  
  /* Error */
  private void ˊ(File paramFile, String paramString)
  {
    // Byte code:
    //   0: new 91	java/io/File
    //   3: dup
    //   4: ldc 93
    //   6: iconst_2
    //   7: anewarray 4	java/lang/Object
    //   10: dup
    //   11: iconst_0
    //   12: aload_1
    //   13: aastore
    //   14: dup
    //   15: iconst_1
    //   16: aload_2
    //   17: aastore
    //   18: invokestatic 99	java/lang/String:format	(Ljava/lang/String;[Ljava/lang/Object;)Ljava/lang/String;
    //   21: invokespecial 102	java/io/File:<init>	(Ljava/lang/String;)V
    //   24: astore 10
    //   26: aload 10
    //   28: invokevirtual 106	java/io/File:exists	()Z
    //   31: ifeq +4 -> 35
    //   34: return
    //   35: new 91	java/io/File
    //   38: dup
    //   39: ldc 108
    //   41: iconst_2
    //   42: anewarray 4	java/lang/Object
    //   45: dup
    //   46: iconst_0
    //   47: aload_1
    //   48: aastore
    //   49: dup
    //   50: iconst_1
    //   51: aload_2
    //   52: aastore
    //   53: invokestatic 99	java/lang/String:format	(Ljava/lang/String;[Ljava/lang/Object;)Ljava/lang/String;
    //   56: invokespecial 102	java/io/File:<init>	(Ljava/lang/String;)V
    //   59: astore 9
    //   61: aload 9
    //   63: invokevirtual 106	java/io/File:exists	()Z
    //   66: ifne +4 -> 70
    //   69: return
    //   70: aconst_null
    //   71: astore 7
    //   73: aconst_null
    //   74: astore 6
    //   76: aload 9
    //   78: invokevirtual 112	java/io/File:length	()J
    //   81: lstore 4
    //   83: lload 4
    //   85: lconst_0
    //   86: lcmp
    //   87: ifgt +4 -> 91
    //   90: return
    //   91: lload 4
    //   93: l2i
    //   94: newarray <illegal type>
    //   96: astore 11
    //   98: new 114	java/io/FileInputStream
    //   101: dup
    //   102: aload 9
    //   104: invokespecial 117	java/io/FileInputStream:<init>	(Ljava/io/File;)V
    //   107: astore 8
    //   109: aload 8
    //   111: astore_1
    //   112: aload_1
    //   113: astore 6
    //   115: aload_1
    //   116: astore 7
    //   118: aload 8
    //   120: aload 11
    //   122: invokevirtual 121	java/io/FileInputStream:read	([B)I
    //   125: istore_3
    //   126: iload_3
    //   127: ifgt +29 -> 156
    //   130: aload_1
    //   131: invokevirtual 124	java/io/FileInputStream:close	()V
    //   134: aload 9
    //   136: invokevirtual 106	java/io/File:exists	()Z
    //   139: ifne +10 -> 149
    //   142: aload 9
    //   144: invokevirtual 128	java/io/File:getAbsolutePath	()Ljava/lang/String;
    //   147: pop
    //   148: return
    //   149: aload 9
    //   151: invokevirtual 131	java/io/File:delete	()Z
    //   154: pop
    //   155: return
    //   156: aload_1
    //   157: astore 6
    //   159: aload_1
    //   160: astore 7
    //   162: new 133	o/is$ˎ
    //   165: dup
    //   166: invokespecial 134	o/is$ˎ:<init>	()V
    //   169: astore 8
    //   171: aload_1
    //   172: astore 6
    //   174: aload_1
    //   175: astore 7
    //   177: aload 8
    //   179: getstatic 140	android/os/Build$VERSION:SDK	Ljava/lang/String;
    //   182: invokevirtual 144	java/lang/String:getBytes	()[B
    //   185: putfield 147	o/is$ˎ:ahJ	[B
    //   188: aload_1
    //   189: astore 6
    //   191: aload_1
    //   192: astore 7
    //   194: aload 8
    //   196: aload_2
    //   197: invokevirtual 144	java/lang/String:getBytes	()[B
    //   200: putfield 150	o/is$ˎ:ahI	[B
    //   203: aload_1
    //   204: astore 6
    //   206: aload_1
    //   207: astore 7
    //   209: aload_0
    //   210: getfield 152	o/kb:atd	Lo/jz;
    //   213: aload_0
    //   214: getfield 154	o/kb:ate	[B
    //   217: aload 11
    //   219: invokevirtual 160	o/jz:ˎ	([B[B)Ljava/lang/String;
    //   222: invokevirtual 144	java/lang/String:getBytes	()[B
    //   225: astore_2
    //   226: aload_1
    //   227: astore 6
    //   229: aload_1
    //   230: astore 7
    //   232: aload 8
    //   234: aload_2
    //   235: putfield 163	o/is$ˎ:ahG	[B
    //   238: aload_1
    //   239: astore 6
    //   241: aload_1
    //   242: astore 7
    //   244: aload 8
    //   246: aload_2
    //   247: invokestatic 169	o/iy:ᐝ	([B)[B
    //   250: putfield 172	o/is$ˎ:ahH	[B
    //   253: aload_1
    //   254: astore 6
    //   256: aload_1
    //   257: astore 7
    //   259: aload 10
    //   261: invokevirtual 175	java/io/File:createNewFile	()Z
    //   264: pop
    //   265: aload_1
    //   266: astore 6
    //   268: aload_1
    //   269: astore 7
    //   271: new 177	java/io/FileOutputStream
    //   274: dup
    //   275: aload 10
    //   277: invokespecial 178	java/io/FileOutputStream:<init>	(Ljava/io/File;)V
    //   280: astore_2
    //   281: aload_1
    //   282: astore 6
    //   284: aload_1
    //   285: astore 7
    //   287: aload 8
    //   289: invokestatic 183	o/jq:ˊ	(Lo/jj;)[B
    //   292: astore 8
    //   294: aload_1
    //   295: astore 6
    //   297: aload_1
    //   298: astore 7
    //   300: aload_2
    //   301: aload 8
    //   303: iconst_0
    //   304: aload 8
    //   306: arraylength
    //   307: invokevirtual 187	java/io/FileOutputStream:write	([BII)V
    //   310: aload_1
    //   311: astore 6
    //   313: aload_1
    //   314: astore 7
    //   316: aload_2
    //   317: invokevirtual 188	java/io/FileOutputStream:close	()V
    //   320: aload_1
    //   321: invokevirtual 124	java/io/FileInputStream:close	()V
    //   324: aload 9
    //   326: invokevirtual 106	java/io/File:exists	()Z
    //   329: ifne +10 -> 339
    //   332: aload 9
    //   334: invokevirtual 128	java/io/File:getAbsolutePath	()Ljava/lang/String;
    //   337: pop
    //   338: return
    //   339: aload 9
    //   341: invokevirtual 131	java/io/File:delete	()Z
    //   344: pop
    //   345: return
    //   346: aload 7
    //   348: ifnull +8 -> 356
    //   351: aload 7
    //   353: invokevirtual 124	java/io/FileInputStream:close	()V
    //   356: aload 9
    //   358: invokevirtual 106	java/io/File:exists	()Z
    //   361: ifne +10 -> 371
    //   364: aload 9
    //   366: invokevirtual 128	java/io/File:getAbsolutePath	()Ljava/lang/String;
    //   369: pop
    //   370: return
    //   371: aload 9
    //   373: invokevirtual 131	java/io/File:delete	()Z
    //   376: pop
    //   377: return
    //   378: astore_1
    //   379: aload 6
    //   381: ifnull +8 -> 389
    //   384: aload 6
    //   386: invokevirtual 124	java/io/FileInputStream:close	()V
    //   389: aload 9
    //   391: invokevirtual 106	java/io/File:exists	()Z
    //   394: ifne +12 -> 406
    //   397: aload 9
    //   399: invokevirtual 128	java/io/File:getAbsolutePath	()Ljava/lang/String;
    //   402: pop
    //   403: goto +9 -> 412
    //   406: aload 9
    //   408: invokevirtual 131	java/io/File:delete	()Z
    //   411: pop
    //   412: aload_1
    //   413: athrow
    //   414: astore_1
    //   415: goto -69 -> 346
    //   418: astore_1
    //   419: goto -285 -> 134
    //   422: astore_1
    //   423: goto -99 -> 324
    //   426: astore_1
    //   427: goto -71 -> 356
    //   430: astore_2
    //   431: goto -42 -> 389
    // Local variable table:
    //   start	length	slot	name	signature
    //   0	434	0	this	kb
    //   0	434	1	paramFile	File
    //   0	434	2	paramString	String
    //   125	2	3	i	int
    //   81	11	4	l	long
    //   74	311	6	localFile1	File
    //   71	281	7	localFile2	File
    //   107	198	8	localObject	Object
    //   59	348	9	localFile3	File
    //   24	252	10	localFile4	File
    //   96	122	11	arrayOfByte	byte[]
    // Exception table:
    //   from	to	target	type
    //   98	109	378	finally
    //   118	126	378	finally
    //   162	171	378	finally
    //   177	188	378	finally
    //   194	203	378	finally
    //   209	226	378	finally
    //   232	238	378	finally
    //   244	253	378	finally
    //   259	265	378	finally
    //   271	281	378	finally
    //   287	294	378	finally
    //   300	310	378	finally
    //   316	320	378	finally
    //   98	109	414	java/io/IOException
    //   98	109	414	java/security/NoSuchAlgorithmException
    //   98	109	414	o/jz$if
    //   118	126	414	java/io/IOException
    //   118	126	414	java/security/NoSuchAlgorithmException
    //   118	126	414	o/jz$if
    //   162	171	414	java/io/IOException
    //   162	171	414	java/security/NoSuchAlgorithmException
    //   162	171	414	o/jz$if
    //   177	188	414	java/io/IOException
    //   177	188	414	java/security/NoSuchAlgorithmException
    //   177	188	414	o/jz$if
    //   194	203	414	java/io/IOException
    //   194	203	414	java/security/NoSuchAlgorithmException
    //   194	203	414	o/jz$if
    //   209	226	414	java/io/IOException
    //   209	226	414	java/security/NoSuchAlgorithmException
    //   209	226	414	o/jz$if
    //   232	238	414	java/io/IOException
    //   232	238	414	java/security/NoSuchAlgorithmException
    //   232	238	414	o/jz$if
    //   244	253	414	java/io/IOException
    //   244	253	414	java/security/NoSuchAlgorithmException
    //   244	253	414	o/jz$if
    //   259	265	414	java/io/IOException
    //   259	265	414	java/security/NoSuchAlgorithmException
    //   259	265	414	o/jz$if
    //   271	281	414	java/io/IOException
    //   271	281	414	java/security/NoSuchAlgorithmException
    //   271	281	414	o/jz$if
    //   287	294	414	java/io/IOException
    //   287	294	414	java/security/NoSuchAlgorithmException
    //   287	294	414	o/jz$if
    //   300	310	414	java/io/IOException
    //   300	310	414	java/security/NoSuchAlgorithmException
    //   300	310	414	o/jz$if
    //   316	320	414	java/io/IOException
    //   316	320	414	java/security/NoSuchAlgorithmException
    //   316	320	414	o/jz$if
    //   130	134	418	java/io/IOException
    //   320	324	422	java/io/IOException
    //   351	356	426	java/io/IOException
    //   384	389	430	java/io/IOException
  }
  
  private boolean ˊ(String paramString1, String paramString2, boolean paramBoolean)
  {
    atb = Executors.newCachedThreadPool();
    asJ = paramBoolean;
    if (paramBoolean) {
      atg = atb.submit(new kc(this));
    }
    ato = hd.ɢ();
    if (ato.zzbn(Nt) > 0) {
      paramBoolean = true;
    } else {
      paramBoolean = false;
    }
    atl = paramBoolean;
    if (ato.isGooglePlayServicesAvailable(Nt) == 0) {
      paramBoolean = true;
    } else {
      paramBoolean = false;
    }
    atn = paramBoolean;
    if (Nt.getApplicationContext() != null)
    {
      localObject1 = new ee.if(Nt);
      Object localObject2 = dr.aaE;
      abv.put(localObject2, null);
      localObject2 = Collections.emptyList();
      abr.addAll((Collection)localObject2);
      abq.addAll((Collection)localObject2);
      atk = ((ee.if)localObject1).ἷ();
    }
    ms.ו(Nt);
    Object localObject1 = ms.awT;
    if (((Boolean)v.כֿ().ˊ((mk)localObject1)).booleanValue()) {
      ati = atb.submit(new kd(this));
    }
    atd = new jz();
    try
    {
      ate = atd.ˢ(paramString1);
    }
    catch (jz.if paramString1)
    {
      throw new ka(paramString1);
    }
    ˤ(paramString2);
    atj = new je(this);
    return true;
  }
  
  private boolean ˋ(File paramFile, String paramString)
  {
    File localFile = new File(String.format("%s/%s.tmp", new Object[] { paramFile, paramString }));
    if (!localFile.exists()) {
      return false;
    }
    paramFile = new File(String.format("%s/%s.dex", new Object[] { paramFile, paramString }));
    if (paramFile.exists()) {
      return false;
    }
    try
    {
      long l = localFile.length();
      if (l <= 0L)
      {
        if (!localFile.exists()) {
          localFile.getAbsolutePath();
        } else {
          localFile.delete();
        }
        return false;
      }
      int i = (int)l;
      Object localObject = new byte[i];
      if (new FileInputStream(localFile).read((byte[])localObject) <= 0)
      {
        if (!localFile.exists()) {
          localFile.getAbsolutePath();
        } else {
          localFile.delete();
        }
        return false;
      }
      localObject = (is.ˎ)jq.ˊ(new is.ˎ(), (byte[])localObject, localObject.length);
      if ((!paramString.equals(new String(ahI))) || (!Arrays.equals(ahH, iy.ᐝ(ahG))) || (!Arrays.equals(ahJ, Build.VERSION.SDK.getBytes())))
      {
        if (!localFile.exists()) {
          localFile.getAbsolutePath();
        } else {
          localFile.delete();
        }
        return false;
      }
      paramString = atd.ˊ(ate, new String(ahG));
      paramFile.createNewFile();
      paramFile = new FileOutputStream(paramFile);
      paramFile.write(paramString, 0, paramString.length);
      paramFile.close();
    }
    catch (IOException|NoSuchAlgorithmException|jz.if paramFile)
    {
      for (;;) {}
    }
    return false;
    return true;
  }
  
  /* Error */
  private boolean ˤ(String paramString)
  {
    // Byte code:
    //   0: aload_0
    //   1: getfield 68	o/kb:Nt	Landroid/content/Context;
    //   4: invokevirtual 387	android/content/Context:getCacheDir	()Ljava/io/File;
    //   7: astore_3
    //   8: aload_3
    //   9: astore_2
    //   10: aload_3
    //   11: ifnonnull +29 -> 40
    //   14: aload_0
    //   15: getfield 68	o/kb:Nt	Landroid/content/Context;
    //   18: ldc_w 389
    //   21: iconst_0
    //   22: invokevirtual 393	android/content/Context:getDir	(Ljava/lang/String;I)Ljava/io/File;
    //   25: astore_3
    //   26: aload_3
    //   27: astore_2
    //   28: aload_3
    //   29: ifnonnull +11 -> 40
    //   32: new 77	o/ka
    //   35: dup
    //   36: invokespecial 394	o/ka:<init>	()V
    //   39: athrow
    //   40: new 91	java/io/File
    //   43: dup
    //   44: ldc_w 396
    //   47: iconst_2
    //   48: anewarray 4	java/lang/Object
    //   51: dup
    //   52: iconst_0
    //   53: aload_2
    //   54: aastore
    //   55: dup
    //   56: iconst_1
    //   57: ldc_w 398
    //   60: aastore
    //   61: invokestatic 99	java/lang/String:format	(Ljava/lang/String;[Ljava/lang/Object;)Ljava/lang/String;
    //   64: invokespecial 102	java/io/File:<init>	(Ljava/lang/String;)V
    //   67: astore_3
    //   68: aload_3
    //   69: invokevirtual 106	java/io/File:exists	()Z
    //   72: ifne +45 -> 117
    //   75: aload_0
    //   76: getfield 152	o/kb:atd	Lo/jz;
    //   79: aload_0
    //   80: getfield 154	o/kb:ate	[B
    //   83: aload_1
    //   84: invokevirtual 379	o/jz:ˊ	([BLjava/lang/String;)[B
    //   87: astore_1
    //   88: aload_3
    //   89: invokevirtual 175	java/io/File:createNewFile	()Z
    //   92: pop
    //   93: new 177	java/io/FileOutputStream
    //   96: dup
    //   97: aload_3
    //   98: invokespecial 178	java/io/FileOutputStream:<init>	(Ljava/io/File;)V
    //   101: astore 4
    //   103: aload 4
    //   105: aload_1
    //   106: iconst_0
    //   107: aload_1
    //   108: arraylength
    //   109: invokevirtual 187	java/io/FileOutputStream:write	([BII)V
    //   112: aload 4
    //   114: invokevirtual 188	java/io/FileOutputStream:close	()V
    //   117: aload_0
    //   118: aload_2
    //   119: ldc_w 398
    //   122: invokespecial 400	o/kb:ˋ	(Ljava/io/File;Ljava/lang/String;)Z
    //   125: pop
    //   126: aload_0
    //   127: new 402	dalvik/system/DexClassLoader
    //   130: dup
    //   131: aload_3
    //   132: invokevirtual 128	java/io/File:getAbsolutePath	()Ljava/lang/String;
    //   135: aload_2
    //   136: invokevirtual 128	java/io/File:getAbsolutePath	()Ljava/lang/String;
    //   139: aconst_null
    //   140: aload_0
    //   141: getfield 68	o/kb:Nt	Landroid/content/Context;
    //   144: invokevirtual 406	android/content/Context:getClassLoader	()Ljava/lang/ClassLoader;
    //   147: invokespecial 409	dalvik/system/DexClassLoader:<init>	(Ljava/lang/String;Ljava/lang/String;Ljava/lang/String;Ljava/lang/ClassLoader;)V
    //   150: putfield 411	o/kb:atc	Ldalvik/system/DexClassLoader;
    //   153: aload_3
    //   154: invokevirtual 106	java/io/File:exists	()Z
    //   157: ifne +11 -> 168
    //   160: aload_3
    //   161: invokevirtual 128	java/io/File:getAbsolutePath	()Ljava/lang/String;
    //   164: pop
    //   165: goto +8 -> 173
    //   168: aload_3
    //   169: invokevirtual 131	java/io/File:delete	()Z
    //   172: pop
    //   173: aload_0
    //   174: aload_2
    //   175: ldc_w 398
    //   178: invokespecial 413	o/kb:ˊ	(Ljava/io/File;Ljava/lang/String;)V
    //   181: new 91	java/io/File
    //   184: dup
    //   185: ldc 108
    //   187: iconst_2
    //   188: anewarray 4	java/lang/Object
    //   191: dup
    //   192: iconst_0
    //   193: aload_2
    //   194: aastore
    //   195: dup
    //   196: iconst_1
    //   197: ldc_w 398
    //   200: aastore
    //   201: invokestatic 99	java/lang/String:format	(Ljava/lang/String;[Ljava/lang/Object;)Ljava/lang/String;
    //   204: invokespecial 102	java/io/File:<init>	(Ljava/lang/String;)V
    //   207: astore_1
    //   208: aload_1
    //   209: invokevirtual 106	java/io/File:exists	()Z
    //   212: ifne +11 -> 223
    //   215: aload_1
    //   216: invokevirtual 128	java/io/File:getAbsolutePath	()Ljava/lang/String;
    //   219: pop
    //   220: goto +129 -> 349
    //   223: aload_1
    //   224: invokevirtual 131	java/io/File:delete	()Z
    //   227: pop
    //   228: goto +121 -> 349
    //   231: astore_1
    //   232: aload_3
    //   233: invokevirtual 106	java/io/File:exists	()Z
    //   236: ifne +11 -> 247
    //   239: aload_3
    //   240: invokevirtual 128	java/io/File:getAbsolutePath	()Ljava/lang/String;
    //   243: pop
    //   244: goto +8 -> 252
    //   247: aload_3
    //   248: invokevirtual 131	java/io/File:delete	()Z
    //   251: pop
    //   252: aload_0
    //   253: aload_2
    //   254: ldc_w 398
    //   257: invokespecial 413	o/kb:ˊ	(Ljava/io/File;Ljava/lang/String;)V
    //   260: new 91	java/io/File
    //   263: dup
    //   264: ldc 108
    //   266: iconst_2
    //   267: anewarray 4	java/lang/Object
    //   270: dup
    //   271: iconst_0
    //   272: aload_2
    //   273: aastore
    //   274: dup
    //   275: iconst_1
    //   276: ldc_w 398
    //   279: aastore
    //   280: invokestatic 99	java/lang/String:format	(Ljava/lang/String;[Ljava/lang/Object;)Ljava/lang/String;
    //   283: invokespecial 102	java/io/File:<init>	(Ljava/lang/String;)V
    //   286: astore_2
    //   287: aload_2
    //   288: invokevirtual 106	java/io/File:exists	()Z
    //   291: ifne +11 -> 302
    //   294: aload_2
    //   295: invokevirtual 128	java/io/File:getAbsolutePath	()Ljava/lang/String;
    //   298: pop
    //   299: goto +8 -> 307
    //   302: aload_2
    //   303: invokevirtual 131	java/io/File:delete	()Z
    //   306: pop
    //   307: aload_1
    //   308: athrow
    //   309: astore_1
    //   310: new 77	o/ka
    //   313: dup
    //   314: aload_1
    //   315: invokespecial 314	o/ka:<init>	(Ljava/lang/Exception;)V
    //   318: athrow
    //   319: astore_1
    //   320: new 77	o/ka
    //   323: dup
    //   324: aload_1
    //   325: invokespecial 314	o/ka:<init>	(Ljava/lang/Exception;)V
    //   328: athrow
    //   329: astore_1
    //   330: new 77	o/ka
    //   333: dup
    //   334: aload_1
    //   335: invokespecial 314	o/ka:<init>	(Ljava/lang/Exception;)V
    //   338: athrow
    //   339: astore_1
    //   340: new 77	o/ka
    //   343: dup
    //   344: aload_1
    //   345: invokespecial 314	o/ka:<init>	(Ljava/lang/Exception;)V
    //   348: athrow
    //   349: iconst_1
    //   350: ireturn
    // Local variable table:
    //   start	length	slot	name	signature
    //   0	351	0	this	kb
    //   0	351	1	paramString	String
    //   9	294	2	localFile1	File
    //   7	241	3	localFile2	File
    //   101	12	4	localFileOutputStream	FileOutputStream
    // Exception table:
    //   from	to	target	type
    //   126	153	231	finally
    //   0	8	309	java/io/FileNotFoundException
    //   14	26	309	java/io/FileNotFoundException
    //   32	40	309	java/io/FileNotFoundException
    //   40	117	309	java/io/FileNotFoundException
    //   117	126	309	java/io/FileNotFoundException
    //   153	165	309	java/io/FileNotFoundException
    //   168	173	309	java/io/FileNotFoundException
    //   173	220	309	java/io/FileNotFoundException
    //   223	228	309	java/io/FileNotFoundException
    //   232	244	309	java/io/FileNotFoundException
    //   247	252	309	java/io/FileNotFoundException
    //   252	299	309	java/io/FileNotFoundException
    //   302	307	309	java/io/FileNotFoundException
    //   307	309	309	java/io/FileNotFoundException
    //   0	8	319	java/io/IOException
    //   14	26	319	java/io/IOException
    //   32	40	319	java/io/IOException
    //   40	117	319	java/io/IOException
    //   117	126	319	java/io/IOException
    //   153	165	319	java/io/IOException
    //   168	173	319	java/io/IOException
    //   173	220	319	java/io/IOException
    //   223	228	319	java/io/IOException
    //   232	244	319	java/io/IOException
    //   247	252	319	java/io/IOException
    //   252	299	319	java/io/IOException
    //   302	307	319	java/io/IOException
    //   307	309	319	java/io/IOException
    //   0	8	329	o/jz$if
    //   14	26	329	o/jz$if
    //   32	40	329	o/jz$if
    //   40	117	329	o/jz$if
    //   117	126	329	o/jz$if
    //   153	165	329	o/jz$if
    //   168	173	329	o/jz$if
    //   173	220	329	o/jz$if
    //   223	228	329	o/jz$if
    //   232	244	329	o/jz$if
    //   247	252	329	o/jz$if
    //   252	299	329	o/jz$if
    //   302	307	329	o/jz$if
    //   307	309	329	o/jz$if
    //   0	8	339	java/lang/NullPointerException
    //   14	26	339	java/lang/NullPointerException
    //   32	40	339	java/lang/NullPointerException
    //   40	117	339	java/lang/NullPointerException
    //   117	126	339	java/lang/NullPointerException
    //   153	165	339	java/lang/NullPointerException
    //   168	173	339	java/lang/NullPointerException
    //   173	220	339	java/lang/NullPointerException
    //   223	228	339	java/lang/NullPointerException
    //   232	244	339	java/lang/NullPointerException
    //   247	252	339	java/lang/NullPointerException
    //   252	299	339	java/lang/NullPointerException
    //   302	307	339	java/lang/NullPointerException
    //   307	309	339	java/lang/NullPointerException
  }
  
  public final boolean ˊ(String paramString1, String paramString2, List<Class> paramList)
  {
    if (!atq.containsKey(new Pair(paramString1, paramString2)))
    {
      atq.put(new Pair(paramString1, paramString2), new ku(this, paramString1, paramString2, paramList));
      return true;
    }
    return false;
  }
  
  public final ᑈ ৰ()
  {
    if (!asJ) {
      return null;
    }
    if (atf != null) {
      return atf;
    }
    if (atg != null) {}
    try
    {
      atg.get(2000L, TimeUnit.MILLISECONDS);
      atg = null;
    }
    catch (InterruptedException localInterruptedException)
    {
      for (;;) {}
    }
    catch (ExecutionException localExecutionException)
    {
      for (;;) {}
    }
    catch (TimeoutException localTimeoutException)
    {
      label69:
      for (;;) {}
    }
    break label69;
    break label69;
    atg.cancel(true);
    return atf;
  }
  
  public final void ค()
  {
    synchronized (atm)
    {
      boolean bool = atp;
      if (bool) {
        return;
      }
      if ((atn) && (atk != null))
      {
        atk.connect();
        atp = true;
      }
      else
      {
        atp = false;
      }
      return;
    }
  }
  
  public final void ฅ()
  {
    synchronized (atm)
    {
      if ((atp) && (atk != null))
      {
        atk.disconnect();
        atp = false;
      }
      return;
    }
  }
  
  public final Method ﾞ(String paramString1, String paramString2)
  {
    paramString1 = (ku)atq.get(new Pair(paramString1, paramString2));
    if (paramString1 == null) {
      return null;
    }
    return paramString1.ป();
  }
}

/* Location:
 * Qualified Name:     o.kb
 * Java Class Version: 6 (50.0)
 * JD-Core Version:    0.7.1
 */