package o;

final class kv
  implements Runnable
{
  kv(ku paramku) {}
  
  /* Error */
  public final void run()
  {
    // Byte code:
    //   0: aload_0
    //   1: getfield 12	o/kv:atK	Lo/ku;
    //   4: astore_1
    //   5: aload_1
    //   6: getfield 33	o/ku:arc	Lo/kb;
    //   9: getfield 39	o/kb:atc	Ldalvik/system/DexClassLoader;
    //   12: astore_2
    //   13: aload_1
    //   14: getfield 33	o/ku:arc	Lo/kb;
    //   17: getfield 43	o/kb:ate	[B
    //   20: astore_3
    //   21: aload_1
    //   22: getfield 47	o/ku:className	Ljava/lang/String;
    //   25: astore 4
    //   27: aload_2
    //   28: new 49	java/lang/String
    //   31: dup
    //   32: aload_1
    //   33: getfield 33	o/ku:arc	Lo/kb;
    //   36: getfield 53	o/kb:atd	Lo/jz;
    //   39: aload_3
    //   40: aload 4
    //   42: invokevirtual 59	o/jz:ˊ	([BLjava/lang/String;)[B
    //   45: ldc 61
    //   47: invokespecial 64	java/lang/String:<init>	([BLjava/lang/String;)V
    //   50: invokevirtual 70	dalvik/system/DexClassLoader:loadClass	(Ljava/lang/String;)Ljava/lang/Class;
    //   53: astore_2
    //   54: aload_2
    //   55: ifnonnull +11 -> 66
    //   58: aload_1
    //   59: getfield 74	o/ku:atJ	Ljava/util/concurrent/CountDownLatch;
    //   62: invokevirtual 79	java/util/concurrent/CountDownLatch:countDown	()V
    //   65: return
    //   66: aload_1
    //   67: getfield 33	o/ku:arc	Lo/kb;
    //   70: getfield 43	o/kb:ate	[B
    //   73: astore_3
    //   74: aload_1
    //   75: getfield 82	o/ku:atF	Ljava/lang/String;
    //   78: astore 4
    //   80: aload_1
    //   81: aload_2
    //   82: new 49	java/lang/String
    //   85: dup
    //   86: aload_1
    //   87: getfield 33	o/ku:arc	Lo/kb;
    //   90: getfield 53	o/kb:atd	Lo/jz;
    //   93: aload_3
    //   94: aload 4
    //   96: invokevirtual 59	o/jz:ˊ	([BLjava/lang/String;)[B
    //   99: ldc 61
    //   101: invokespecial 64	java/lang/String:<init>	([BLjava/lang/String;)V
    //   104: aload_1
    //   105: getfield 86	o/ku:atI	Ljava/util/ArrayList;
    //   108: aload_1
    //   109: getfield 86	o/ku:atI	Ljava/util/ArrayList;
    //   112: invokeinterface 92 1 0
    //   117: anewarray 94	java/lang/Class
    //   120: invokeinterface 98 2 0
    //   125: checkcast 100	[Ljava/lang/Class;
    //   128: invokevirtual 104	java/lang/Class:getMethod	(Ljava/lang/String;[Ljava/lang/Class;)Ljava/lang/reflect/Method;
    //   131: putfield 108	o/ku:atH	Ljava/lang/reflect/Method;
    //   134: aload_1
    //   135: getfield 108	o/ku:atH	Ljava/lang/reflect/Method;
    //   138: astore_2
    //   139: aload_2
    //   140: ifnonnull +11 -> 151
    //   143: aload_1
    //   144: getfield 74	o/ku:atJ	Ljava/util/concurrent/CountDownLatch;
    //   147: invokevirtual 79	java/util/concurrent/CountDownLatch:countDown	()V
    //   150: return
    //   151: aload_1
    //   152: getfield 74	o/ku:atJ	Ljava/util/concurrent/CountDownLatch;
    //   155: invokevirtual 79	java/util/concurrent/CountDownLatch:countDown	()V
    //   158: return
    //   159: aload_1
    //   160: getfield 74	o/ku:atJ	Ljava/util/concurrent/CountDownLatch;
    //   163: invokevirtual 79	java/util/concurrent/CountDownLatch:countDown	()V
    //   166: return
    //   167: aload_1
    //   168: getfield 74	o/ku:atJ	Ljava/util/concurrent/CountDownLatch;
    //   171: invokevirtual 79	java/util/concurrent/CountDownLatch:countDown	()V
    //   174: return
    //   175: aload_1
    //   176: getfield 74	o/ku:atJ	Ljava/util/concurrent/CountDownLatch;
    //   179: invokevirtual 79	java/util/concurrent/CountDownLatch:countDown	()V
    //   182: return
    //   183: aload_1
    //   184: getfield 74	o/ku:atJ	Ljava/util/concurrent/CountDownLatch;
    //   187: invokevirtual 79	java/util/concurrent/CountDownLatch:countDown	()V
    //   190: return
    //   191: aload_1
    //   192: getfield 74	o/ku:atJ	Ljava/util/concurrent/CountDownLatch;
    //   195: invokevirtual 79	java/util/concurrent/CountDownLatch:countDown	()V
    //   198: return
    //   199: astore_2
    //   200: aload_1
    //   201: getfield 74	o/ku:atJ	Ljava/util/concurrent/CountDownLatch;
    //   204: invokevirtual 79	java/util/concurrent/CountDownLatch:countDown	()V
    //   207: aload_2
    //   208: athrow
    //   209: astore_2
    //   210: goto -51 -> 159
    //   213: astore_2
    //   214: goto -47 -> 167
    //   217: astore_2
    //   218: goto -43 -> 175
    //   221: astore_2
    //   222: goto -39 -> 183
    //   225: astore_2
    //   226: goto -35 -> 191
    // Local variable table:
    //   start	length	slot	name	signature
    //   0	229	0	this	kv
    //   4	197	1	localku	ku
    //   12	128	2	localObject1	Object
    //   199	9	2	localObject2	Object
    //   209	1	2	localif	jz.if
    //   213	1	2	localUnsupportedEncodingException	java.io.UnsupportedEncodingException
    //   217	1	2	localClassNotFoundException	ClassNotFoundException
    //   221	1	2	localNoSuchMethodException	NoSuchMethodException
    //   225	1	2	localNullPointerException	NullPointerException
    //   20	74	3	arrayOfByte	byte[]
    //   25	70	4	str	String
    // Exception table:
    //   from	to	target	type
    //   5	54	199	finally
    //   66	139	199	finally
    //   5	54	209	o/jz$if
    //   66	139	209	o/jz$if
    //   5	54	213	java/io/UnsupportedEncodingException
    //   66	139	213	java/io/UnsupportedEncodingException
    //   5	54	217	java/lang/ClassNotFoundException
    //   66	139	217	java/lang/ClassNotFoundException
    //   5	54	221	java/lang/NoSuchMethodException
    //   66	139	221	java/lang/NoSuchMethodException
    //   5	54	225	java/lang/NullPointerException
    //   66	139	225	java/lang/NullPointerException
  }
}

/* Location:
 * Qualified Name:     o.kv
 * Java Class Version: 6 (50.0)
 * JD-Core Version:    0.7.1
 */