package o;

import org.json.JSONObject;

@vq
public final class lp
  extends lg
{
  private qy.ˋ auB;
  private boolean auC;
  
  /* Error */
  public lp(android.content.Context paramContext, com.google.android.gms.ads.internal.client.AdSizeParcel paramAdSizeParcel, xg paramxg, com.google.android.gms.ads.internal.util.client.VersionInfoParcel paramVersionInfoParcel, lw paramlw, qy paramqy)
  {
    // Byte code:
    //   0: aload_0
    //   1: aload_1
    //   2: aload_2
    //   3: aload_3
    //   4: aload 4
    //   6: aload 5
    //   8: invokespecial 18	o/lg:<init>	(Landroid/content/Context;Lcom/google/android/gms/ads/internal/client/AdSizeParcel;Lo/xg;Lcom/google/android/gms/ads/internal/util/client/VersionInfoParcel;Lo/lw;)V
    //   11: aload_0
    //   12: aload 6
    //   14: aconst_null
    //   15: invokevirtual 24	o/qy:ˋ	(Lo/jx;)Lo/qy$ˋ;
    //   18: putfield 26	o/lp:auB	Lo/qy$ˋ;
    //   21: aload_0
    //   22: aload 5
    //   24: invokeinterface 32 1 0
    //   29: invokeinterface 36 1 0
    //   34: invokevirtual 40	o/lp:ﻧ	(Landroid/view/View;)Lorg/json/JSONObject;
    //   37: astore_1
    //   38: aload_0
    //   39: getfield 26	o/lp:auB	Lo/qy$ˋ;
    //   42: new 42	o/lq
    //   45: dup
    //   46: aload_0
    //   47: aload_1
    //   48: invokespecial 45	o/lq:<init>	(Lo/lp;Lorg/json/JSONObject;)V
    //   51: new 47	o/lr
    //   54: dup
    //   55: aload_0
    //   56: invokespecial 50	o/lr:<init>	(Lo/lp;)V
    //   59: invokevirtual 56	o/qy$ˋ:ˊ	(Lo/zs$ˋ;Lo/zs$if;)V
    //   62: goto +16 -> 78
    //   65: goto +13 -> 78
    //   68: astore_1
    //   69: ldc 58
    //   71: ldc 60
    //   73: aload_1
    //   74: invokestatic 66	android/util/Log:e	(Ljava/lang/String;Ljava/lang/String;Ljava/lang/Throwable;)I
    //   77: pop
    //   78: aload_0
    //   79: getfield 26	o/lp:auB	Lo/qy$ˋ;
    //   82: new 68	o/ls
    //   85: dup
    //   86: aload_0
    //   87: invokespecial 69	o/ls:<init>	(Lo/lp;)V
    //   90: new 71	o/lt
    //   93: dup
    //   94: aload_0
    //   95: invokespecial 72	o/lt:<init>	(Lo/lp;)V
    //   98: invokevirtual 56	o/qy$ˋ:ˊ	(Lo/zs$ˋ;Lo/zs$if;)V
    //   101: aload_0
    //   102: getfield 76	o/lp:auc	Lo/Դ;
    //   105: getfield 82	o/Դ:GK	Ljava/lang/String;
    //   108: invokestatic 88	java/lang/String:valueOf	(Ljava/lang/Object;)Ljava/lang/String;
    //   111: invokevirtual 92	java/lang/String:length	()I
    //   114: ifeq +4 -> 118
    //   117: return
    //   118: new 84	java/lang/String
    //   121: dup
    //   122: ldc 94
    //   124: invokespecial 97	java/lang/String:<init>	(Ljava/lang/String;)V
    //   127: pop
    //   128: return
    //   129: astore_1
    //   130: goto -65 -> 65
    // Local variable table:
    //   start	length	slot	name	signature
    //   0	133	0	this	lp
    //   0	133	1	paramContext	android.content.Context
    //   0	133	2	paramAdSizeParcel	com.google.android.gms.ads.internal.client.AdSizeParcel
    //   0	133	3	paramxg	xg
    //   0	133	4	paramVersionInfoParcel	com.google.android.gms.ads.internal.util.client.VersionInfoParcel
    //   0	133	5	paramlw	lw
    //   0	133	6	paramqy	qy
    // Exception table:
    //   from	to	target	type
    //   21	62	68	java/lang/RuntimeException
    //   21	62	129	org/json/JSONException
  }
  
  protected final void destroy()
  {
    synchronized (Im)
    {
      super.destroy();
      auB.ˊ(new lv(this), new zs.ˊ());
      auB.release();
      return;
    }
  }
  
  protected final void ˎ(JSONObject paramJSONObject)
  {
    auB.ˊ(new lu(this, paramJSONObject), new zs.ˊ());
  }
  
  protected final boolean ᐵ()
  {
    return auC;
  }
}

/* Location:
 * Qualified Name:     o.lp
 * Java Class Version: 6 (50.0)
 * JD-Core Version:    0.7.1
 */