package o;

import android.app.Activity;

public final class ʡ
  implements ᓕ.if
{
  private static int $$5;
  private static final short[] $5 = { 42, -119, -32, 22, -2676, 2676, -2676, -2009 };
  private static int yP = 0;
  private static int yQ = 1;
  private static final byte[] yR;
  
  private static String $5(short paramShort1, byte paramByte, short paramShort2)
  {
    paramShort2 = 5 - paramShort2 * 2;
    paramShort1 = 111 - paramShort1 * 2;
    short s1 = 0;
    short s4 = 0;
    short[] arrayOfShort = $5;
    paramByte = 3 - paramByte * 4;
    char[] arrayOfChar = new char[paramByte];
    short s3 = paramByte - 1;
    paramByte = paramShort1;
    short s2 = paramShort2;
    if (arrayOfShort == null)
    {
      s1 = s3;
      s2 = paramShort1;
      paramByte = paramShort2;
      paramShort1 = s4;
      paramShort2 = s2;
    }
    for (;;)
    {
      paramShort2 = s1 + paramShort2 + 2611;
      s2 = paramByte;
      paramByte = paramShort2;
      s1 = paramShort1;
      s2 += 1;
      arrayOfChar[s1] = ((char)paramByte);
      if (s1 == s3) {
        return new String(arrayOfChar);
      }
      paramShort2 = arrayOfShort[s2];
      paramShort1 = s1 + 1;
      s1 = paramByte;
      paramByte = s2;
    }
  }
  
  static
  {
    $$5 = 32;
    yR = new byte[] { 24, 59, -58, 54, 16, 2, -59, 59, 2, 13, 1, 11, 7, -6, 8, -59, 61, 13, 7, 5, -1, 4, 1, -6, 17, 13, -70, 70, 6, 1 };
  }
  
  public ʡ(Activity paramActivity) {}
  
  private static String ˊ(short paramShort1, short paramShort2, byte paramByte)
  {
    short s1;
    short s2;
    byte[] arrayOfByte2;
    try
    {
      for (;;)
      {
        s1 = yQ + 103;
        try
        {
          yP = s1 % 128;
          if (s1 % 2 != 0) {
            break;
          }
        }
        catch (Exception localException1)
        {
          byte[] arrayOfByte1;
          throw localException1;
        }
        paramShort2 = s1 + paramShort2 - 4;
      }
      paramShort2 = 3 - paramShort2 * 2;
      s2 = paramShort1 * 3 + 27;
      s1 = paramByte * 4 + 99;
      paramShort1 = 0;
      arrayOfByte1 = yR;
      arrayOfByte2 = new byte[s2];
      paramByte = paramShort2;
      paramShort2 = s1;
    }
    catch (Exception localException2)
    {
      label80:
      throw localException2;
    }
    return new String(arrayOfByte2, 0);
    for (;;)
    {
      s1 = localException1[paramByte];
      break;
      s1 = paramShort1;
      paramByte += 1;
      paramShort1 = s1 + 1;
      arrayOfByte2[s1] = ((byte)paramShort2);
      if (paramShort1 == s2) {
        break label80;
      }
    }
  }
  
  /* Error */
  public final void ˊ(String paramString, com.anjlab.android.iab.v3.TransactionDetails paramTransactionDetails)
  {
    // Byte code:
    //   0: goto +322 -> 322
    //   3: iload 5
    //   5: tableswitch	default:+19->24, 0:+459->464
    //   24: goto +17 -> 41
    //   27: bipush 39
    //   29: istore 5
    //   31: goto +141 -> 172
    //   34: bipush 23
    //   36: istore 5
    //   38: goto +257 -> 295
    //   41: getstatic 64	o/ʡ:yQ	I
    //   44: bipush 65
    //   46: iadd
    //   47: istore 5
    //   49: iload 5
    //   51: sipush 128
    //   54: irem
    //   55: putstatic 62	o/ʡ:yP	I
    //   58: iload 5
    //   60: iconst_2
    //   61: irem
    //   62: ifne +257 -> 319
    //   65: goto +131 -> 196
    //   68: goto +9 -> 77
    //   71: astore_1
    //   72: aload_1
    //   73: invokevirtual 85	java/lang/Throwable:getCause	()Ljava/lang/Throwable;
    //   76: athrow
    //   77: iconst_0
    //   78: iconst_0
    //   79: iconst_0
    //   80: invokestatic 87	o/ʡ:$5	(SBS)Ljava/lang/String;
    //   83: invokestatic 93	o/ʢ:ˎ	(Ljava/lang/String;)Ljava/lang/Class;
    //   86: ldc 95
    //   88: aconst_null
    //   89: invokevirtual 101	java/lang/Class:getMethod	(Ljava/lang/String;[Ljava/lang/Class;)Ljava/lang/reflect/Method;
    //   92: aconst_null
    //   93: aconst_null
    //   94: invokevirtual 107	java/lang/reflect/Method:invoke	(Ljava/lang/Object;[Ljava/lang/Object;)Ljava/lang/Object;
    //   97: astore_1
    //   98: goto +9 -> 107
    //   101: astore_1
    //   102: aload_1
    //   103: invokevirtual 85	java/lang/Throwable:getCause	()Ljava/lang/Throwable;
    //   106: athrow
    //   107: iconst_0
    //   108: iconst_0
    //   109: iconst_1
    //   110: invokestatic 87	o/ʡ:$5	(SBS)Ljava/lang/String;
    //   113: invokestatic 93	o/ʢ:ˎ	(Ljava/lang/String;)Ljava/lang/Class;
    //   116: ldc 109
    //   118: iconst_1
    //   119: anewarray 97	java/lang/Class
    //   122: dup
    //   123: iconst_0
    //   124: ldc 111
    //   126: aastore
    //   127: invokevirtual 101	java/lang/Class:getMethod	(Ljava/lang/String;[Ljava/lang/Class;)Ljava/lang/reflect/Method;
    //   130: aload_1
    //   131: iconst_1
    //   132: anewarray 4	java/lang/Object
    //   135: dup
    //   136: iconst_0
    //   137: aload_2
    //   138: aastore
    //   139: invokevirtual 107	java/lang/reflect/Method:invoke	(Ljava/lang/Object;[Ljava/lang/Object;)Ljava/lang/Object;
    //   142: checkcast 113	java/lang/Boolean
    //   145: invokevirtual 117	java/lang/Boolean:booleanValue	()Z
    //   148: istore 6
    //   150: iload 6
    //   152: ifne +306 -> 458
    //   155: goto +343 -> 498
    //   158: bipush 88
    //   160: istore 5
    //   162: goto +10 -> 172
    //   165: bipush 29
    //   167: istore 5
    //   169: goto +126 -> 295
    //   172: iload 5
    //   174: lookupswitch	default:+18->192, 88:+217->391
    //   192: goto +169 -> 361
    //   195: return
    //   196: ldc2_w 118
    //   199: putstatic 125	o/ﾚ:z	J
    //   202: goto +9 -> 211
    //   205: astore_1
    //   206: aload_1
    //   207: invokevirtual 85	java/lang/Throwable:getCause	()Ljava/lang/Throwable;
    //   210: athrow
    //   211: iconst_0
    //   212: iconst_0
    //   213: iconst_0
    //   214: invokestatic 87	o/ʡ:$5	(SBS)Ljava/lang/String;
    //   217: invokestatic 93	o/ʢ:ˎ	(Ljava/lang/String;)Ljava/lang/Class;
    //   220: ldc 127
    //   222: aconst_null
    //   223: invokevirtual 130	java/lang/Class:getDeclaredMethod	(Ljava/lang/String;[Ljava/lang/Class;)Ljava/lang/reflect/Method;
    //   226: aconst_null
    //   227: aconst_null
    //   228: invokevirtual 107	java/lang/reflect/Method:invoke	(Ljava/lang/Object;[Ljava/lang/Object;)Ljava/lang/Object;
    //   231: checkcast 132	android/content/Context
    //   234: astore_1
    //   235: aload_1
    //   236: invokestatic 136	o/ﾚ:י	(Landroid/content/Context;)V
    //   239: aload_0
    //   240: getfield 67	o/ʡ:ʋ	Landroid/app/Activity;
    //   243: ldc -119
    //   245: iconst_1
    //   246: invokestatic 143	android/widget/Toast:makeText	(Landroid/content/Context;II)Landroid/widget/Toast;
    //   249: invokevirtual 146	android/widget/Toast:show	()V
    //   252: goto +9 -> 261
    //   255: astore_1
    //   256: aload_1
    //   257: invokevirtual 85	java/lang/Throwable:getCause	()Ljava/lang/Throwable;
    //   260: athrow
    //   261: iconst_0
    //   262: iconst_0
    //   263: iconst_0
    //   264: invokestatic 87	o/ʡ:$5	(SBS)Ljava/lang/String;
    //   267: invokestatic 93	o/ʢ:ˎ	(Ljava/lang/String;)Ljava/lang/Class;
    //   270: ldc -108
    //   272: aconst_null
    //   273: invokevirtual 101	java/lang/Class:getMethod	(Ljava/lang/String;[Ljava/lang/Class;)Ljava/lang/reflect/Method;
    //   276: aconst_null
    //   277: aconst_null
    //   278: invokevirtual 107	java/lang/reflect/Method:invoke	(Ljava/lang/Object;[Ljava/lang/Object;)Ljava/lang/Object;
    //   281: astore_1
    //   282: aload_1
    //   283: ifnonnull -256 -> 27
    //   286: goto -128 -> 158
    //   289: astore_1
    //   290: aload_1
    //   291: athrow
    //   292: goto +107 -> 399
    //   295: iload 5
    //   297: lookupswitch	default:+19->316, 23:+-102->195
    //   316: goto -248 -> 68
    //   319: goto -123 -> 196
    //   322: getstatic 60	o/ʡ:yR	[B
    //   325: bipush 10
    //   327: baload
    //   328: iconst_1
    //   329: isub
    //   330: i2b
    //   331: istore_3
    //   332: iload_3
    //   333: i2b
    //   334: istore 4
    //   336: aload_1
    //   337: iload_3
    //   338: iload 4
    //   340: iload 4
    //   342: i2b
    //   343: invokestatic 150	o/ʡ:ˊ	(SSB)Ljava/lang/String;
    //   346: invokevirtual 154	java/lang/String:intern	()Ljava/lang/String;
    //   349: invokevirtual 158	java/lang/String:equals	(Ljava/lang/Object;)Z
    //   352: ifne -187 -> 165
    //   355: goto -321 -> 34
    //   358: astore_1
    //   359: aload_1
    //   360: athrow
    //   361: getstatic 64	o/ʡ:yQ	I
    //   364: istore 5
    //   366: iload 5
    //   368: iconst_1
    //   369: iadd
    //   370: istore 5
    //   372: iload 5
    //   374: sipush 128
    //   377: irem
    //   378: putstatic 62	o/ʡ:yP	I
    //   381: iload 5
    //   383: iconst_2
    //   384: irem
    //   385: ifne -93 -> 292
    //   388: goto +11 -> 399
    //   391: aload_0
    //   392: getfield 67	o/ʡ:ʋ	Landroid/app/Activity;
    //   395: invokevirtual 163	android/app/Activity:recreate	()V
    //   398: return
    //   399: goto +9 -> 408
    //   402: astore_1
    //   403: aload_1
    //   404: invokevirtual 85	java/lang/Throwable:getCause	()Ljava/lang/Throwable;
    //   407: athrow
    //   408: iconst_0
    //   409: iconst_0
    //   410: iconst_0
    //   411: invokestatic 87	o/ʡ:$5	(SBS)Ljava/lang/String;
    //   414: invokestatic 93	o/ʢ:ˎ	(Ljava/lang/String;)Ljava/lang/Class;
    //   417: ldc -108
    //   419: aconst_null
    //   420: invokevirtual 101	java/lang/Class:getMethod	(Ljava/lang/String;[Ljava/lang/Class;)Ljava/lang/reflect/Method;
    //   423: aconst_null
    //   424: aconst_null
    //   425: invokevirtual 107	java/lang/reflect/Method:invoke	(Ljava/lang/Object;[Ljava/lang/Object;)Ljava/lang/Object;
    //   428: checkcast 165	o/ｧ$ˎ
    //   431: astore_1
    //   432: aload_1
    //   433: getfield 169	o/ｧ$ˎ:gv	Lo/uc;
    //   436: iconst_1
    //   437: invokeinterface 175 2 0
    //   442: goto -51 -> 391
    //   445: astore_1
    //   446: ldc -79
    //   448: ldc -77
    //   450: aload_1
    //   451: invokestatic 185	android/util/Log:w	(Ljava/lang/String;Ljava/lang/String;Ljava/lang/Throwable;)I
    //   454: pop
    //   455: goto -64 -> 391
    //   458: iconst_1
    //   459: istore 5
    //   461: goto -458 -> 3
    //   464: aload_0
    //   465: getfield 67	o/ʡ:ʋ	Landroid/app/Activity;
    //   468: aload_0
    //   469: getfield 67	o/ʡ:ʋ	Landroid/app/Activity;
    //   472: ldc -70
    //   474: iconst_1
    //   475: anewarray 4	java/lang/Object
    //   478: dup
    //   479: iconst_0
    //   480: sipush 200
    //   483: invokestatic 192	java/lang/Integer:valueOf	(I)Ljava/lang/Integer;
    //   486: aastore
    //   487: invokevirtual 196	android/app/Activity:getString	(I[Ljava/lang/Object;)Ljava/lang/String;
    //   490: iconst_1
    //   491: invokestatic 199	android/widget/Toast:makeText	(Landroid/content/Context;Ljava/lang/CharSequence;I)Landroid/widget/Toast;
    //   494: invokevirtual 146	android/widget/Toast:show	()V
    //   497: return
    //   498: iconst_0
    //   499: istore 5
    //   501: goto -498 -> 3
    // Local variable table:
    //   start	length	slot	name	signature
    //   0	504	0	this	ʡ
    //   0	504	1	paramString	String
    //   0	504	2	paramTransactionDetails	com.anjlab.android.iab.v3.TransactionDetails
    //   331	7	3	s1	short
    //   334	7	4	s2	short
    //   3	497	5	i	int
    //   148	3	6	bool	boolean
    // Exception table:
    //   from	to	target	type
    //   77	98	71	finally
    //   107	150	101	finally
    //   211	235	205	finally
    //   261	282	255	finally
    //   372	381	289	java/lang/Exception
    //   361	366	358	java/lang/Exception
    //   408	432	402	finally
    //   432	442	445	android/os/RemoteException
  }
  
  /* Error */
  public final void ї(int paramInt)
  {
    // Byte code:
    //   0: ldc -54
    //   2: ldc -52
    //   4: new 206	java/lang/StringBuilder
    //   7: dup
    //   8: ldc -48
    //   10: invokespecial 211	java/lang/StringBuilder:<init>	(Ljava/lang/String;)V
    //   13: iload_1
    //   14: invokevirtual 215	java/lang/StringBuilder:append	(I)Ljava/lang/StringBuilder;
    //   17: invokevirtual 218	java/lang/StringBuilder:toString	()Ljava/lang/String;
    //   20: iconst_0
    //   21: invokestatic 223	o/л:ˊ	(Ljava/lang/String;Ljava/lang/String;Ljava/lang/String;I)V
    //   24: iload_1
    //   25: iconst_1
    //   26: if_icmpne +107 -> 133
    //   29: goto +9 -> 38
    //   32: astore_2
    //   33: aload_2
    //   34: invokevirtual 85	java/lang/Throwable:getCause	()Ljava/lang/Throwable;
    //   37: athrow
    //   38: iconst_0
    //   39: iconst_0
    //   40: iconst_0
    //   41: invokestatic 87	o/ʡ:$5	(SBS)Ljava/lang/String;
    //   44: invokestatic 93	o/ʢ:ˎ	(Ljava/lang/String;)Ljava/lang/Class;
    //   47: ldc -108
    //   49: aconst_null
    //   50: invokevirtual 130	java/lang/Class:getDeclaredMethod	(Ljava/lang/String;[Ljava/lang/Class;)Ljava/lang/reflect/Method;
    //   53: aconst_null
    //   54: aconst_null
    //   55: invokevirtual 107	java/lang/reflect/Method:invoke	(Ljava/lang/Object;[Ljava/lang/Object;)Ljava/lang/Object;
    //   58: astore_2
    //   59: aload_2
    //   60: ifnull +59 -> 119
    //   63: goto +9 -> 72
    //   66: astore_2
    //   67: aload_2
    //   68: invokevirtual 85	java/lang/Throwable:getCause	()Ljava/lang/Throwable;
    //   71: athrow
    //   72: iconst_0
    //   73: iconst_0
    //   74: iconst_0
    //   75: invokestatic 87	o/ʡ:$5	(SBS)Ljava/lang/String;
    //   78: invokestatic 93	o/ʢ:ˎ	(Ljava/lang/String;)Ljava/lang/Class;
    //   81: ldc -108
    //   83: aconst_null
    //   84: invokevirtual 101	java/lang/Class:getMethod	(Ljava/lang/String;[Ljava/lang/Class;)Ljava/lang/reflect/Method;
    //   87: aconst_null
    //   88: aconst_null
    //   89: invokevirtual 107	java/lang/reflect/Method:invoke	(Ljava/lang/Object;[Ljava/lang/Object;)Ljava/lang/Object;
    //   92: checkcast 165	o/ｧ$ˎ
    //   95: astore_2
    //   96: aload_2
    //   97: getfield 169	o/ｧ$ˎ:gv	Lo/uc;
    //   100: iconst_2
    //   101: invokeinterface 175 2 0
    //   106: goto +13 -> 119
    //   109: astore_2
    //   110: ldc -79
    //   112: ldc -77
    //   114: aload_2
    //   115: invokestatic 185	android/util/Log:w	(Ljava/lang/String;Ljava/lang/String;Ljava/lang/Throwable;)I
    //   118: pop
    //   119: aload_0
    //   120: getfield 67	o/ʡ:ʋ	Landroid/app/Activity;
    //   123: ldc -32
    //   125: iconst_1
    //   126: invokestatic 143	android/widget/Toast:makeText	(Landroid/content/Context;II)Landroid/widget/Toast;
    //   129: invokevirtual 146	android/widget/Toast:show	()V
    //   132: return
    //   133: goto +9 -> 142
    //   136: astore_2
    //   137: aload_2
    //   138: invokevirtual 85	java/lang/Throwable:getCause	()Ljava/lang/Throwable;
    //   141: athrow
    //   142: iconst_0
    //   143: iconst_0
    //   144: iconst_0
    //   145: invokestatic 87	o/ʡ:$5	(SBS)Ljava/lang/String;
    //   148: invokestatic 93	o/ʢ:ˎ	(Ljava/lang/String;)Ljava/lang/Class;
    //   151: ldc -108
    //   153: aconst_null
    //   154: invokevirtual 101	java/lang/Class:getMethod	(Ljava/lang/String;[Ljava/lang/Class;)Ljava/lang/reflect/Method;
    //   157: aconst_null
    //   158: aconst_null
    //   159: invokevirtual 107	java/lang/reflect/Method:invoke	(Ljava/lang/Object;[Ljava/lang/Object;)Ljava/lang/Object;
    //   162: astore_2
    //   163: aload_2
    //   164: ifnull +59 -> 223
    //   167: goto +9 -> 176
    //   170: astore_2
    //   171: aload_2
    //   172: invokevirtual 85	java/lang/Throwable:getCause	()Ljava/lang/Throwable;
    //   175: athrow
    //   176: iconst_0
    //   177: iconst_0
    //   178: iconst_0
    //   179: invokestatic 87	o/ʡ:$5	(SBS)Ljava/lang/String;
    //   182: invokestatic 93	o/ʢ:ˎ	(Ljava/lang/String;)Ljava/lang/Class;
    //   185: ldc -108
    //   187: aconst_null
    //   188: invokevirtual 101	java/lang/Class:getMethod	(Ljava/lang/String;[Ljava/lang/Class;)Ljava/lang/reflect/Method;
    //   191: aconst_null
    //   192: aconst_null
    //   193: invokevirtual 107	java/lang/reflect/Method:invoke	(Ljava/lang/Object;[Ljava/lang/Object;)Ljava/lang/Object;
    //   196: checkcast 165	o/ｧ$ˎ
    //   199: astore_2
    //   200: aload_2
    //   201: getfield 169	o/ｧ$ˎ:gv	Lo/uc;
    //   204: iconst_0
    //   205: invokeinterface 175 2 0
    //   210: goto +13 -> 223
    //   213: astore_2
    //   214: ldc -79
    //   216: ldc -77
    //   218: aload_2
    //   219: invokestatic 185	android/util/Log:w	(Ljava/lang/String;Ljava/lang/String;Ljava/lang/Throwable;)I
    //   222: pop
    //   223: aload_0
    //   224: getfield 67	o/ʡ:ʋ	Landroid/app/Activity;
    //   227: aload_0
    //   228: getfield 67	o/ʡ:ʋ	Landroid/app/Activity;
    //   231: ldc -70
    //   233: iconst_1
    //   234: anewarray 4	java/lang/Object
    //   237: dup
    //   238: iconst_0
    //   239: iload_1
    //   240: invokestatic 192	java/lang/Integer:valueOf	(I)Ljava/lang/Integer;
    //   243: aastore
    //   244: invokevirtual 196	android/app/Activity:getString	(I[Ljava/lang/Object;)Ljava/lang/String;
    //   247: iconst_1
    //   248: invokestatic 199	android/widget/Toast:makeText	(Landroid/content/Context;Ljava/lang/CharSequence;I)Landroid/widget/Toast;
    //   251: invokevirtual 146	android/widget/Toast:show	()V
    //   254: return
    // Local variable table:
    //   start	length	slot	name	signature
    //   0	255	0	this	ʡ
    //   0	255	1	paramInt	int
    //   32	2	2	localObject1	Object
    //   58	2	2	localObject2	Object
    //   66	2	2	localObject3	Object
    //   95	2	2	localˎ1	ｧ.ˎ
    //   109	6	2	localRemoteException1	android.os.RemoteException
    //   136	2	2	localObject4	Object
    //   162	2	2	localObject5	Object
    //   170	2	2	localObject6	Object
    //   199	2	2	localˎ2	ｧ.ˎ
    //   213	6	2	localRemoteException2	android.os.RemoteException
    // Exception table:
    //   from	to	target	type
    //   38	59	32	finally
    //   72	96	66	finally
    //   96	106	109	android/os/RemoteException
    //   142	163	136	finally
    //   176	200	170	finally
    //   200	210	213	android/os/RemoteException
  }
  
  /* Error */
  public final void ῒ()
  {
    // Byte code:
    //   0: goto +730 -> 730
    //   3: aload 6
    //   5: invokeinterface 230 1 0
    //   10: ifeq +6 -> 16
    //   13: goto +109 -> 122
    //   16: goto +326 -> 342
    //   19: aload 6
    //   21: invokeinterface 234 1 0
    //   26: checkcast 21	java/lang/String
    //   29: astore 7
    //   31: getstatic 60	o/ʡ:yR	[B
    //   34: bipush 10
    //   36: baload
    //   37: iconst_1
    //   38: isub
    //   39: i2b
    //   40: istore_2
    //   41: iload_2
    //   42: i2b
    //   43: istore_3
    //   44: aload 7
    //   46: iload_2
    //   47: iload_3
    //   48: iload_3
    //   49: i2b
    //   50: invokestatic 150	o/ʡ:ˊ	(SSB)Ljava/lang/String;
    //   53: invokevirtual 154	java/lang/String:intern	()Ljava/lang/String;
    //   56: invokevirtual 158	java/lang/String:equals	(Ljava/lang/Object;)Z
    //   59: ifeq +6 -> 65
    //   62: goto +370 -> 432
    //   65: goto +784 -> 849
    //   68: iload 4
    //   70: lookupswitch	default:+18->88, 10:+442->512
    //   88: goto +40 -> 128
    //   91: iload 4
    //   93: lookupswitch	default:+19->112, 26:+375->468
    //   112: goto +364 -> 476
    //   115: bipush 47
    //   117: istore 4
    //   119: goto +271 -> 390
    //   122: iconst_1
    //   123: istore 4
    //   125: goto +693 -> 818
    //   128: goto +11 -> 139
    //   131: astore 6
    //   133: aload 6
    //   135: invokevirtual 85	java/lang/Throwable:getCause	()Ljava/lang/Throwable;
    //   138: athrow
    //   139: iconst_0
    //   140: iconst_0
    //   141: iconst_0
    //   142: invokestatic 87	o/ʡ:$5	(SBS)Ljava/lang/String;
    //   145: invokestatic 93	o/ʢ:ˎ	(Ljava/lang/String;)Ljava/lang/Class;
    //   148: ldc 95
    //   150: aconst_null
    //   151: invokevirtual 101	java/lang/Class:getMethod	(Ljava/lang/String;[Ljava/lang/Class;)Ljava/lang/reflect/Method;
    //   154: aconst_null
    //   155: aconst_null
    //   156: invokevirtual 107	java/lang/reflect/Method:invoke	(Ljava/lang/Object;[Ljava/lang/Object;)Ljava/lang/Object;
    //   159: astore 7
    //   161: goto +11 -> 172
    //   164: astore 6
    //   166: aload 6
    //   168: invokevirtual 85	java/lang/Throwable:getCause	()Ljava/lang/Throwable;
    //   171: athrow
    //   172: iconst_0
    //   173: iconst_0
    //   174: iconst_0
    //   175: invokestatic 87	o/ʡ:$5	(SBS)Ljava/lang/String;
    //   178: invokestatic 93	o/ʢ:ˎ	(Ljava/lang/String;)Ljava/lang/Class;
    //   181: ldc 95
    //   183: aconst_null
    //   184: invokevirtual 101	java/lang/Class:getMethod	(Ljava/lang/String;[Ljava/lang/Class;)Ljava/lang/reflect/Method;
    //   187: aconst_null
    //   188: aconst_null
    //   189: invokevirtual 107	java/lang/reflect/Method:invoke	(Ljava/lang/Object;[Ljava/lang/Object;)Ljava/lang/Object;
    //   192: astore 8
    //   194: getstatic 60	o/ʡ:yR	[B
    //   197: bipush 10
    //   199: baload
    //   200: iconst_1
    //   201: isub
    //   202: i2b
    //   203: istore_2
    //   204: iload_2
    //   205: i2b
    //   206: istore_3
    //   207: iload_2
    //   208: iload_3
    //   209: iload_3
    //   210: i2b
    //   211: invokestatic 150	o/ʡ:ˊ	(SSB)Ljava/lang/String;
    //   214: invokevirtual 154	java/lang/String:intern	()Ljava/lang/String;
    //   217: astore 9
    //   219: goto +11 -> 230
    //   222: astore 6
    //   224: aload 6
    //   226: invokevirtual 85	java/lang/Throwable:getCause	()Ljava/lang/Throwable;
    //   229: athrow
    //   230: iconst_0
    //   231: iconst_0
    //   232: iconst_1
    //   233: invokestatic 87	o/ʡ:$5	(SBS)Ljava/lang/String;
    //   236: invokestatic 93	o/ʢ:ˎ	(Ljava/lang/String;)Ljava/lang/Class;
    //   239: ldc -20
    //   241: iconst_1
    //   242: anewarray 97	java/lang/Class
    //   245: dup
    //   246: iconst_0
    //   247: ldc 21
    //   249: aastore
    //   250: invokevirtual 101	java/lang/Class:getMethod	(Ljava/lang/String;[Ljava/lang/Class;)Ljava/lang/reflect/Method;
    //   253: aload 8
    //   255: iconst_1
    //   256: anewarray 4	java/lang/Object
    //   259: dup
    //   260: iconst_0
    //   261: aload 9
    //   263: aastore
    //   264: invokevirtual 107	java/lang/reflect/Method:invoke	(Ljava/lang/Object;[Ljava/lang/Object;)Ljava/lang/Object;
    //   267: astore 8
    //   269: goto +11 -> 280
    //   272: astore 6
    //   274: aload 6
    //   276: invokevirtual 85	java/lang/Throwable:getCause	()Ljava/lang/Throwable;
    //   279: athrow
    //   280: iconst_0
    //   281: iconst_0
    //   282: iconst_1
    //   283: invokestatic 87	o/ʡ:$5	(SBS)Ljava/lang/String;
    //   286: invokestatic 93	o/ʢ:ˎ	(Ljava/lang/String;)Ljava/lang/Class;
    //   289: ldc 109
    //   291: iconst_1
    //   292: anewarray 97	java/lang/Class
    //   295: dup
    //   296: iconst_0
    //   297: ldc 111
    //   299: aastore
    //   300: invokevirtual 101	java/lang/Class:getMethod	(Ljava/lang/String;[Ljava/lang/Class;)Ljava/lang/reflect/Method;
    //   303: aload 7
    //   305: iconst_1
    //   306: anewarray 4	java/lang/Object
    //   309: dup
    //   310: iconst_0
    //   311: aload 8
    //   313: aastore
    //   314: invokevirtual 107	java/lang/reflect/Method:invoke	(Ljava/lang/Object;[Ljava/lang/Object;)Ljava/lang/Object;
    //   317: checkcast 113	java/lang/Boolean
    //   320: invokevirtual 117	java/lang/Boolean:booleanValue	()Z
    //   323: istore 5
    //   325: iload 5
    //   327: ifeq +6 -> 333
    //   330: goto -215 -> 115
    //   333: goto +510 -> 843
    //   336: iconst_1
    //   337: istore 4
    //   339: goto +100 -> 439
    //   342: iconst_0
    //   343: istore 4
    //   345: goto +473 -> 818
    //   348: goto +11 -> 359
    //   351: astore 6
    //   353: aload 6
    //   355: invokevirtual 85	java/lang/Throwable:getCause	()Ljava/lang/Throwable;
    //   358: athrow
    //   359: iconst_0
    //   360: iconst_0
    //   361: iconst_0
    //   362: invokestatic 87	o/ʡ:$5	(SBS)Ljava/lang/String;
    //   365: invokestatic 93	o/ʢ:ˎ	(Ljava/lang/String;)Ljava/lang/Class;
    //   368: ldc 127
    //   370: aconst_null
    //   371: invokevirtual 101	java/lang/Class:getMethod	(Ljava/lang/String;[Ljava/lang/Class;)Ljava/lang/reflect/Method;
    //   374: aconst_null
    //   375: aconst_null
    //   376: invokevirtual 107	java/lang/reflect/Method:invoke	(Ljava/lang/Object;[Ljava/lang/Object;)Ljava/lang/Object;
    //   379: checkcast 132	android/content/Context
    //   382: astore 6
    //   384: aload 6
    //   386: invokestatic 136	o/ﾚ:י	(Landroid/content/Context;)V
    //   389: return
    //   390: iload 4
    //   392: lookupswitch	default:+20->412, 3:+76->468
    //   412: ldc2_w 118
    //   415: putstatic 125	o/ﾚ:z	J
    //   418: aload_0
    //   419: getfield 67	o/ʡ:ʋ	Landroid/app/Activity;
    //   422: astore 7
    //   424: aload 7
    //   426: invokevirtual 163	android/app/Activity:recreate	()V
    //   429: goto +39 -> 468
    //   432: bipush 40
    //   434: istore 4
    //   436: goto -345 -> 91
    //   439: iload 4
    //   441: tableswitch	default:+19->460, 0:+27->468
    //   460: goto -48 -> 412
    //   463: astore 6
    //   465: aload 6
    //   467: athrow
    //   468: goto -465 -> 3
    //   471: astore 6
    //   473: aload 6
    //   475: athrow
    //   476: getstatic 64	o/ʡ:yQ	I
    //   479: bipush 51
    //   481: iadd
    //   482: istore 4
    //   484: iload 4
    //   486: sipush 128
    //   489: irem
    //   490: putstatic 62	o/ʡ:yP	I
    //   493: iload 4
    //   495: iconst_2
    //   496: irem
    //   497: ifeq +6 -> 503
    //   500: goto +6 -> 506
    //   503: goto +353 -> 856
    //   506: iconst_0
    //   507: istore 4
    //   509: goto -441 -> 68
    //   512: goto +11 -> 523
    //   515: astore 6
    //   517: aload 6
    //   519: invokevirtual 85	java/lang/Throwable:getCause	()Ljava/lang/Throwable;
    //   522: athrow
    //   523: iconst_0
    //   524: iconst_0
    //   525: iconst_0
    //   526: invokestatic 87	o/ʡ:$5	(SBS)Ljava/lang/String;
    //   529: invokestatic 93	o/ʢ:ˎ	(Ljava/lang/String;)Ljava/lang/Class;
    //   532: ldc 95
    //   534: aconst_null
    //   535: invokevirtual 101	java/lang/Class:getMethod	(Ljava/lang/String;[Ljava/lang/Class;)Ljava/lang/reflect/Method;
    //   538: aconst_null
    //   539: aconst_null
    //   540: invokevirtual 107	java/lang/reflect/Method:invoke	(Ljava/lang/Object;[Ljava/lang/Object;)Ljava/lang/Object;
    //   543: astore 7
    //   545: goto +11 -> 556
    //   548: astore 6
    //   550: aload 6
    //   552: invokevirtual 85	java/lang/Throwable:getCause	()Ljava/lang/Throwable;
    //   555: athrow
    //   556: iconst_0
    //   557: iconst_0
    //   558: iconst_0
    //   559: invokestatic 87	o/ʡ:$5	(SBS)Ljava/lang/String;
    //   562: invokestatic 93	o/ʢ:ˎ	(Ljava/lang/String;)Ljava/lang/Class;
    //   565: ldc 95
    //   567: aconst_null
    //   568: invokevirtual 101	java/lang/Class:getMethod	(Ljava/lang/String;[Ljava/lang/Class;)Ljava/lang/reflect/Method;
    //   571: aconst_null
    //   572: aconst_null
    //   573: invokevirtual 107	java/lang/reflect/Method:invoke	(Ljava/lang/Object;[Ljava/lang/Object;)Ljava/lang/Object;
    //   576: astore 8
    //   578: getstatic 60	o/ʡ:yR	[B
    //   581: astore 9
    //   583: aload 9
    //   585: bipush 10
    //   587: baload
    //   588: iconst_1
    //   589: isub
    //   590: i2b
    //   591: istore_2
    //   592: iload_2
    //   593: i2b
    //   594: istore_3
    //   595: iload_3
    //   596: i2b
    //   597: istore_1
    //   598: iload_2
    //   599: iload_3
    //   600: iload_1
    //   601: invokestatic 150	o/ʡ:ˊ	(SSB)Ljava/lang/String;
    //   604: astore 9
    //   606: aload 9
    //   608: invokevirtual 154	java/lang/String:intern	()Ljava/lang/String;
    //   611: astore 9
    //   613: goto +11 -> 624
    //   616: astore 6
    //   618: aload 6
    //   620: invokevirtual 85	java/lang/Throwable:getCause	()Ljava/lang/Throwable;
    //   623: athrow
    //   624: iconst_0
    //   625: iconst_0
    //   626: iconst_1
    //   627: invokestatic 87	o/ʡ:$5	(SBS)Ljava/lang/String;
    //   630: invokestatic 93	o/ʢ:ˎ	(Ljava/lang/String;)Ljava/lang/Class;
    //   633: ldc -20
    //   635: iconst_1
    //   636: anewarray 97	java/lang/Class
    //   639: dup
    //   640: iconst_0
    //   641: ldc 21
    //   643: aastore
    //   644: invokevirtual 101	java/lang/Class:getMethod	(Ljava/lang/String;[Ljava/lang/Class;)Ljava/lang/reflect/Method;
    //   647: aload 8
    //   649: iconst_1
    //   650: anewarray 4	java/lang/Object
    //   653: dup
    //   654: iconst_0
    //   655: aload 9
    //   657: aastore
    //   658: invokevirtual 107	java/lang/reflect/Method:invoke	(Ljava/lang/Object;[Ljava/lang/Object;)Ljava/lang/Object;
    //   661: astore 8
    //   663: goto +11 -> 674
    //   666: astore 6
    //   668: aload 6
    //   670: invokevirtual 85	java/lang/Throwable:getCause	()Ljava/lang/Throwable;
    //   673: athrow
    //   674: iconst_0
    //   675: iconst_0
    //   676: iconst_1
    //   677: invokestatic 87	o/ʡ:$5	(SBS)Ljava/lang/String;
    //   680: invokestatic 93	o/ʢ:ˎ	(Ljava/lang/String;)Ljava/lang/Class;
    //   683: ldc 109
    //   685: iconst_1
    //   686: anewarray 97	java/lang/Class
    //   689: dup
    //   690: iconst_0
    //   691: ldc 111
    //   693: aastore
    //   694: invokevirtual 101	java/lang/Class:getMethod	(Ljava/lang/String;[Ljava/lang/Class;)Ljava/lang/reflect/Method;
    //   697: aload 7
    //   699: iconst_1
    //   700: anewarray 4	java/lang/Object
    //   703: dup
    //   704: iconst_0
    //   705: aload 8
    //   707: aastore
    //   708: invokevirtual 107	java/lang/reflect/Method:invoke	(Ljava/lang/Object;[Ljava/lang/Object;)Ljava/lang/Object;
    //   711: checkcast 113	java/lang/Boolean
    //   714: invokevirtual 117	java/lang/Boolean:booleanValue	()Z
    //   717: istore 5
    //   719: iload 5
    //   721: ifeq +6 -> 727
    //   724: goto -388 -> 336
    //   727: goto +136 -> 863
    //   730: ldc2_w 237
    //   733: putstatic 125	o/ﾚ:z	J
    //   736: goto +11 -> 747
    //   739: astore 6
    //   741: aload 6
    //   743: invokevirtual 85	java/lang/Throwable:getCause	()Ljava/lang/Throwable;
    //   746: athrow
    //   747: iconst_0
    //   748: iconst_0
    //   749: iconst_0
    //   750: invokestatic 87	o/ʡ:$5	(SBS)Ljava/lang/String;
    //   753: invokestatic 93	o/ʢ:ˎ	(Ljava/lang/String;)Ljava/lang/Class;
    //   756: ldc 95
    //   758: aconst_null
    //   759: invokevirtual 101	java/lang/Class:getMethod	(Ljava/lang/String;[Ljava/lang/Class;)Ljava/lang/reflect/Method;
    //   762: aconst_null
    //   763: aconst_null
    //   764: invokevirtual 107	java/lang/reflect/Method:invoke	(Ljava/lang/Object;[Ljava/lang/Object;)Ljava/lang/Object;
    //   767: astore 6
    //   769: goto +11 -> 780
    //   772: astore 6
    //   774: aload 6
    //   776: invokevirtual 85	java/lang/Throwable:getCause	()Ljava/lang/Throwable;
    //   779: athrow
    //   780: iconst_0
    //   781: iconst_0
    //   782: iconst_1
    //   783: invokestatic 87	o/ʡ:$5	(SBS)Ljava/lang/String;
    //   786: invokestatic 93	o/ʢ:ˎ	(Ljava/lang/String;)Ljava/lang/Class;
    //   789: ldc -16
    //   791: aconst_null
    //   792: invokevirtual 101	java/lang/Class:getMethod	(Ljava/lang/String;[Ljava/lang/Class;)Ljava/lang/reflect/Method;
    //   795: aload 6
    //   797: aconst_null
    //   798: invokevirtual 107	java/lang/reflect/Method:invoke	(Ljava/lang/Object;[Ljava/lang/Object;)Ljava/lang/Object;
    //   801: checkcast 242	java/util/List
    //   804: astore 6
    //   806: aload 6
    //   808: invokeinterface 246 1 0
    //   813: astore 6
    //   815: goto -812 -> 3
    //   818: iload 4
    //   820: tableswitch	default:+20->840, 0:+-472->348
    //   840: goto -821 -> 19
    //   843: iconst_3
    //   844: istore 4
    //   846: goto -456 -> 390
    //   849: bipush 26
    //   851: istore 4
    //   853: goto -762 -> 91
    //   856: bipush 10
    //   858: istore 4
    //   860: goto -792 -> 68
    //   863: iconst_0
    //   864: istore 4
    //   866: goto -427 -> 439
    // Local variable table:
    //   start	length	slot	name	signature
    //   0	869	0	this	ʡ
    //   597	4	1	b	byte
    //   40	559	2	s1	short
    //   43	557	3	s2	short
    //   68	797	4	i	int
    //   323	397	5	bool	boolean
    //   3	17	6	localObject1	Object
    //   131	3	6	localObject2	Object
    //   164	3	6	localObject3	Object
    //   222	3	6	localObject4	Object
    //   272	3	6	localObject5	Object
    //   351	3	6	localObject6	Object
    //   382	3	6	localContext	android.content.Context
    //   463	3	6	localException1	Exception
    //   471	3	6	localException2	Exception
    //   515	3	6	localObject7	Object
    //   548	3	6	localObject8	Object
    //   616	3	6	localObject9	Object
    //   666	3	6	localObject10	Object
    //   739	3	6	localObject11	Object
    //   767	1	6	localObject12	Object
    //   772	24	6	localObject13	Object
    //   804	10	6	localObject14	Object
    //   29	669	7	localObject15	Object
    //   192	514	8	localObject16	Object
    //   217	439	9	localObject17	Object
    // Exception table:
    //   from	to	target	type
    //   139	161	131	finally
    //   172	194	164	finally
    //   230	269	222	finally
    //   280	325	272	finally
    //   359	384	351	finally
    //   418	424	463	java/lang/Exception
    //   517	523	463	java/lang/Exception
    //   550	556	463	java/lang/Exception
    //   578	583	463	java/lang/Exception
    //   598	606	463	java/lang/Exception
    //   606	613	463	java/lang/Exception
    //   618	624	463	java/lang/Exception
    //   668	674	463	java/lang/Exception
    //   412	418	471	java/lang/Exception
    //   418	424	471	java/lang/Exception
    //   424	429	471	java/lang/Exception
    //   523	545	515	finally
    //   556	578	548	finally
    //   624	663	616	finally
    //   674	719	666	finally
    //   747	769	739	finally
    //   780	806	772	finally
  }
  
  /* Error */
  public final void ΐ()
  {
    // Byte code:
    //   0: goto +77 -> 77
    //   3: return
    //   4: goto +11 -> 15
    //   7: astore 4
    //   9: aload 4
    //   11: invokevirtual 85	java/lang/Throwable:getCause	()Ljava/lang/Throwable;
    //   14: athrow
    //   15: iconst_0
    //   16: iconst_0
    //   17: iconst_0
    //   18: invokestatic 87	o/ʡ:$5	(SBS)Ljava/lang/String;
    //   21: invokestatic 93	o/ʢ:ˎ	(Ljava/lang/String;)Ljava/lang/Class;
    //   24: ldc -7
    //   26: aconst_null
    //   27: invokevirtual 130	java/lang/Class:getDeclaredMethod	(Ljava/lang/String;[Ljava/lang/Class;)Ljava/lang/reflect/Method;
    //   30: aconst_null
    //   31: aconst_null
    //   32: invokevirtual 107	java/lang/reflect/Method:invoke	(Ljava/lang/Object;[Ljava/lang/Object;)Ljava/lang/Object;
    //   35: checkcast 251	com/anjlab/android/iab/v3/SkuDetails
    //   38: astore 4
    //   40: aload 4
    //   42: getfield 255	com/anjlab/android/iab/v3/SkuDetails:yt	Ljava/lang/String;
    //   45: astore 4
    //   47: iconst_0
    //   48: iconst_0
    //   49: iconst_0
    //   50: invokestatic 87	o/ʡ:$5	(SBS)Ljava/lang/String;
    //   53: invokestatic 93	o/ʢ:ˎ	(Ljava/lang/String;)Ljava/lang/Class;
    //   56: ldc_w 257
    //   59: invokevirtual 261	java/lang/Class:getField	(Ljava/lang/String;)Ljava/lang/reflect/Field;
    //   62: aconst_null
    //   63: aload 4
    //   65: invokevirtual 267	java/lang/reflect/Field:set	(Ljava/lang/Object;Ljava/lang/Object;)V
    //   68: return
    //   69: iconst_1
    //   70: istore_3
    //   71: goto +273 -> 344
    //   74: goto -70 -> 4
    //   77: goto +11 -> 88
    //   80: astore 4
    //   82: aload 4
    //   84: invokevirtual 85	java/lang/Throwable:getCause	()Ljava/lang/Throwable;
    //   87: athrow
    //   88: iconst_0
    //   89: iconst_0
    //   90: iconst_0
    //   91: invokestatic 87	o/ʡ:$5	(SBS)Ljava/lang/String;
    //   94: invokestatic 93	o/ʢ:ˎ	(Ljava/lang/String;)Ljava/lang/Class;
    //   97: ldc_w 269
    //   100: iconst_1
    //   101: anewarray 97	java/lang/Class
    //   104: dup
    //   105: iconst_0
    //   106: getstatic 273	java/lang/Boolean:TYPE	Ljava/lang/Class;
    //   109: aastore
    //   110: invokevirtual 130	java/lang/Class:getDeclaredMethod	(Ljava/lang/String;[Ljava/lang/Class;)Ljava/lang/reflect/Method;
    //   113: aconst_null
    //   114: iconst_1
    //   115: anewarray 4	java/lang/Object
    //   118: dup
    //   119: iconst_0
    //   120: iconst_1
    //   121: invokestatic 276	java/lang/Boolean:valueOf	(Z)Ljava/lang/Boolean;
    //   124: aastore
    //   125: invokevirtual 107	java/lang/reflect/Method:invoke	(Ljava/lang/Object;[Ljava/lang/Object;)Ljava/lang/Object;
    //   128: checkcast 113	java/lang/Boolean
    //   131: invokevirtual 117	java/lang/Boolean:booleanValue	()Z
    //   134: pop
    //   135: goto +11 -> 146
    //   138: astore 4
    //   140: aload 4
    //   142: invokevirtual 85	java/lang/Throwable:getCause	()Ljava/lang/Throwable;
    //   145: athrow
    //   146: iconst_0
    //   147: iconst_0
    //   148: iconst_0
    //   149: invokestatic 87	o/ʡ:$5	(SBS)Ljava/lang/String;
    //   152: invokestatic 93	o/ʢ:ˎ	(Ljava/lang/String;)Ljava/lang/Class;
    //   155: ldc 95
    //   157: aconst_null
    //   158: invokevirtual 130	java/lang/Class:getDeclaredMethod	(Ljava/lang/String;[Ljava/lang/Class;)Ljava/lang/reflect/Method;
    //   161: aconst_null
    //   162: aconst_null
    //   163: invokevirtual 107	java/lang/reflect/Method:invoke	(Ljava/lang/Object;[Ljava/lang/Object;)Ljava/lang/Object;
    //   166: astore 4
    //   168: getstatic 60	o/ʡ:yR	[B
    //   171: bipush 10
    //   173: baload
    //   174: iconst_1
    //   175: isub
    //   176: i2b
    //   177: istore_1
    //   178: iload_1
    //   179: i2b
    //   180: istore_2
    //   181: iload_1
    //   182: iload_2
    //   183: iload_2
    //   184: i2b
    //   185: invokestatic 150	o/ʡ:ˊ	(SSB)Ljava/lang/String;
    //   188: invokevirtual 154	java/lang/String:intern	()Ljava/lang/String;
    //   191: astore 5
    //   193: goto +11 -> 204
    //   196: astore 4
    //   198: aload 4
    //   200: invokevirtual 85	java/lang/Throwable:getCause	()Ljava/lang/Throwable;
    //   203: athrow
    //   204: iconst_0
    //   205: iconst_0
    //   206: iconst_1
    //   207: invokestatic 87	o/ʡ:$5	(SBS)Ljava/lang/String;
    //   210: invokestatic 93	o/ʢ:ˎ	(Ljava/lang/String;)Ljava/lang/Class;
    //   213: ldc_w 278
    //   216: iconst_1
    //   217: anewarray 97	java/lang/Class
    //   220: dup
    //   221: iconst_0
    //   222: ldc 21
    //   224: aastore
    //   225: invokevirtual 101	java/lang/Class:getMethod	(Ljava/lang/String;[Ljava/lang/Class;)Ljava/lang/reflect/Method;
    //   228: aload 4
    //   230: iconst_1
    //   231: anewarray 4	java/lang/Object
    //   234: dup
    //   235: iconst_0
    //   236: aload 5
    //   238: aastore
    //   239: invokevirtual 107	java/lang/reflect/Method:invoke	(Ljava/lang/Object;[Ljava/lang/Object;)Ljava/lang/Object;
    //   242: astore 4
    //   244: goto +11 -> 255
    //   247: astore 4
    //   249: aload 4
    //   251: invokevirtual 85	java/lang/Throwable:getCause	()Ljava/lang/Throwable;
    //   254: athrow
    //   255: iconst_0
    //   256: iconst_0
    //   257: iconst_0
    //   258: invokestatic 87	o/ʡ:$5	(SBS)Ljava/lang/String;
    //   261: invokestatic 93	o/ʢ:ˎ	(Ljava/lang/String;)Ljava/lang/Class;
    //   264: ldc_w 279
    //   267: iconst_1
    //   268: anewarray 97	java/lang/Class
    //   271: dup
    //   272: iconst_0
    //   273: ldc -5
    //   275: aastore
    //   276: invokevirtual 130	java/lang/Class:getDeclaredMethod	(Ljava/lang/String;[Ljava/lang/Class;)Ljava/lang/reflect/Method;
    //   279: aconst_null
    //   280: iconst_1
    //   281: anewarray 4	java/lang/Object
    //   284: dup
    //   285: iconst_0
    //   286: aload 4
    //   288: aastore
    //   289: invokevirtual 107	java/lang/reflect/Method:invoke	(Ljava/lang/Object;[Ljava/lang/Object;)Ljava/lang/Object;
    //   292: pop
    //   293: goto +11 -> 304
    //   296: astore 4
    //   298: aload 4
    //   300: invokevirtual 85	java/lang/Throwable:getCause	()Ljava/lang/Throwable;
    //   303: athrow
    //   304: iconst_0
    //   305: iconst_0
    //   306: iconst_0
    //   307: invokestatic 87	o/ʡ:$5	(SBS)Ljava/lang/String;
    //   310: invokestatic 93	o/ʢ:ˎ	(Ljava/lang/String;)Ljava/lang/Class;
    //   313: ldc -7
    //   315: aconst_null
    //   316: invokevirtual 101	java/lang/Class:getMethod	(Ljava/lang/String;[Ljava/lang/Class;)Ljava/lang/reflect/Method;
    //   319: aconst_null
    //   320: aconst_null
    //   321: invokevirtual 107	java/lang/reflect/Method:invoke	(Ljava/lang/Object;[Ljava/lang/Object;)Ljava/lang/Object;
    //   324: astore 4
    //   326: aload 4
    //   328: ifnull +6 -> 334
    //   331: goto -262 -> 69
    //   334: iconst_0
    //   335: istore_3
    //   336: goto +8 -> 344
    //   339: astore 4
    //   341: aload 4
    //   343: athrow
    //   344: iload_3
    //   345: tableswitch	default:+19->364, 0:+-342->3
    //   364: getstatic 62	o/ʡ:yP	I
    //   367: istore_3
    //   368: iload_3
    //   369: bipush 97
    //   371: iadd
    //   372: istore_3
    //   373: iload_3
    //   374: sipush 128
    //   377: irem
    //   378: putstatic 64	o/ʡ:yQ	I
    //   381: iload_3
    //   382: iconst_2
    //   383: irem
    //   384: ifne +6 -> 390
    //   387: goto -313 -> 74
    //   390: goto -386 -> 4
    // Local variable table:
    //   start	length	slot	name	signature
    //   0	393	0	this	ʡ
    //   177	5	1	s1	short
    //   180	4	2	s2	short
    //   70	314	3	i	int
    //   7	3	4	localObject1	Object
    //   38	26	4	localObject2	Object
    //   80	3	4	localObject3	Object
    //   138	3	4	localObject4	Object
    //   166	1	4	localObject5	Object
    //   196	33	4	localObject6	Object
    //   242	1	4	localObject7	Object
    //   247	40	4	localObject8	Object
    //   296	3	4	localObject9	Object
    //   324	3	4	localObject10	Object
    //   339	3	4	localException	Exception
    //   191	46	5	str	String
    // Exception table:
    //   from	to	target	type
    //   15	40	7	finally
    //   88	135	80	finally
    //   146	168	138	finally
    //   204	244	196	finally
    //   255	293	247	finally
    //   304	326	296	finally
    //   364	368	339	java/lang/Exception
    //   373	381	339	java/lang/Exception
  }
}

/* Location:
 * Qualified Name:     o.ʡ
 * Java Class Version: 6 (50.0)
 * JD-Core Version:    0.7.1
 */