package o;

import android.os.ParcelFileDescriptor.AutoCloseOutputStream;
import com.google.android.gms.ads.internal.request.LargeParcelTeleporter;

public final class น
  implements Runnable
{
  public น(LargeParcelTeleporter paramLargeParcelTeleporter, ParcelFileDescriptor.AutoCloseOutputStream paramAutoCloseOutputStream, byte[] paramArrayOfByte) {}
  
  /* Error */
  public final void run()
  {
    // Byte code:
    //   0: aconst_null
    //   1: astore_2
    //   2: aconst_null
    //   3: astore_1
    //   4: new 29	java/io/DataOutputStream
    //   7: dup
    //   8: aload_0
    //   9: getfield 18	o/น:QI	Ljava/io/OutputStream;
    //   12: invokespecial 32	java/io/DataOutputStream:<init>	(Ljava/io/OutputStream;)V
    //   15: astore 4
    //   17: aload 4
    //   19: astore_3
    //   20: aload_3
    //   21: astore_1
    //   22: aload_3
    //   23: astore_2
    //   24: aload 4
    //   26: aload_0
    //   27: getfield 20	o/น:QJ	[B
    //   30: arraylength
    //   31: invokevirtual 36	java/io/DataOutputStream:writeInt	(I)V
    //   34: aload_3
    //   35: astore_1
    //   36: aload_3
    //   37: astore_2
    //   38: aload_3
    //   39: aload_0
    //   40: getfield 20	o/น:QJ	[B
    //   43: invokevirtual 40	java/io/DataOutputStream:write	([B)V
    //   46: aload_3
    //   47: invokeinterface 45 1 0
    //   52: return
    //   53: astore_3
    //   54: aload_1
    //   55: astore_2
    //   56: ldc 47
    //   58: ldc 49
    //   60: aload_3
    //   61: invokestatic 55	android/util/Log:e	(Ljava/lang/String;Ljava/lang/String;Ljava/lang/Throwable;)I
    //   64: pop
    //   65: aload_1
    //   66: astore_2
    //   67: invokestatic 61	o/v:Ἳ	()Lo/xl;
    //   70: aload_3
    //   71: invokevirtual 67	o/xl:ˋ	(Ljava/lang/Throwable;)V
    //   74: aload_1
    //   75: ifnonnull +20 -> 95
    //   78: aload_0
    //   79: getfield 18	o/น:QI	Ljava/io/OutputStream;
    //   82: astore_1
    //   83: aload_1
    //   84: ifnull +10 -> 94
    //   87: aload_1
    //   88: invokeinterface 45 1 0
    //   93: return
    //   94: return
    //   95: aload_1
    //   96: ifnull +10 -> 106
    //   99: aload_1
    //   100: invokeinterface 45 1 0
    //   105: return
    //   106: return
    //   107: astore_1
    //   108: aload_2
    //   109: ifnonnull +24 -> 133
    //   112: aload_0
    //   113: getfield 18	o/น:QI	Ljava/io/OutputStream;
    //   116: astore_2
    //   117: aload_2
    //   118: ifnull +12 -> 130
    //   121: aload_2
    //   122: invokeinterface 45 1 0
    //   127: goto +16 -> 143
    //   130: goto +13 -> 143
    //   133: aload_2
    //   134: ifnull +9 -> 143
    //   137: aload_2
    //   138: invokeinterface 45 1 0
    //   143: aload_1
    //   144: athrow
    //   145: astore_1
    //   146: return
    //   147: astore_1
    //   148: return
    //   149: astore_1
    //   150: return
    //   151: astore_2
    //   152: goto -22 -> 130
    //   155: astore_2
    //   156: goto -13 -> 143
    // Local variable table:
    //   start	length	slot	name	signature
    //   0	159	0	this	น
    //   3	97	1	localObject1	Object
    //   107	37	1	localObject2	Object
    //   145	1	1	localIOException1	java.io.IOException
    //   147	1	1	localIOException2	java.io.IOException
    //   149	1	1	localIOException3	java.io.IOException
    //   1	137	2	localObject3	Object
    //   151	1	2	localIOException4	java.io.IOException
    //   155	1	2	localIOException5	java.io.IOException
    //   19	28	3	localDataOutputStream1	java.io.DataOutputStream
    //   53	18	3	localIOException6	java.io.IOException
    //   15	10	4	localDataOutputStream2	java.io.DataOutputStream
    // Exception table:
    //   from	to	target	type
    //   4	17	53	java/io/IOException
    //   24	34	53	java/io/IOException
    //   38	46	53	java/io/IOException
    //   4	17	107	finally
    //   24	34	107	finally
    //   38	46	107	finally
    //   56	65	107	finally
    //   67	74	107	finally
    //   46	52	145	java/io/IOException
    //   87	93	147	java/io/IOException
    //   99	105	149	java/io/IOException
    //   121	127	151	java/io/IOException
    //   137	143	155	java/io/IOException
  }
}

/* Location:
 * Qualified Name:     o.น
 * Java Class Version: 6 (50.0)
 * JD-Core Version:    0.7.1
 */