package o;

import android.os.Bundle;
import java.io.FileDescriptor;
import java.io.PrintWriter;
import java.lang.reflect.Modifier;

public final class ᒾ$if
  implements ᐥ.ˋ<Object>, ᐥ.ˊ<Object>
{
  public boolean є;
  final Bundle ۊ = null;
  ᑦ.if<Object> ܚ;
  public ᐥ<Object> ܪ;
  public boolean ܬ;
  boolean र;
  public Object ঌ;
  public boolean গ;
  public boolean ঢ;
  private boolean ব;
  final int ᗮ = 0;
  private boolean כֿ;
  public boolean ﾅ;
  
  public ᒾ$if(int paramInt)
  {
    ᑦ.if localif;
    ܚ = localif;
  }
  
  /* Error */
  final void destroy()
  {
    // Byte code:
    //   0: aload_0
    //   1: iconst_1
    //   2: putfield 54	o/ᒾ$if:כֿ	Z
    //   5: aload_0
    //   6: getfield 56	o/ᒾ$if:र	Z
    //   9: istore_1
    //   10: aload_0
    //   11: iconst_0
    //   12: putfield 56	o/ᒾ$if:र	Z
    //   15: aload_0
    //   16: getfield 48	o/ᒾ$if:ܚ	Lo/ᑦ$if;
    //   19: ifnull +125 -> 144
    //   22: aload_0
    //   23: getfield 58	o/ᒾ$if:ܪ	Lo/ʶ;
    //   26: ifnull +118 -> 144
    //   29: aload_0
    //   30: getfield 60	o/ᒾ$if:ܬ	Z
    //   33: ifeq +111 -> 144
    //   36: iload_1
    //   37: ifeq +107 -> 144
    //   40: aconst_null
    //   41: astore_2
    //   42: aload_0
    //   43: getfield 39	o/ᒾ$if:শ	Lo/ᒾ;
    //   46: getfield 64	o/ᒾ:ʿ	Lo/ᕑ;
    //   49: ifnull +32 -> 81
    //   52: aload_0
    //   53: getfield 39	o/ᒾ$if:শ	Lo/ᒾ;
    //   56: getfield 64	o/ᒾ:ʿ	Lo/ᕑ;
    //   59: getfield 70	o/ᕑ:ɤ	Lo/ᘁ;
    //   62: getfield 76	o/ᘁ:ﮈ	Ljava/lang/String;
    //   65: astore_2
    //   66: aload_0
    //   67: getfield 39	o/ᒾ$if:শ	Lo/ᒾ;
    //   70: getfield 64	o/ᒾ:ʿ	Lo/ᕑ;
    //   73: getfield 70	o/ᕑ:ɤ	Lo/ᘁ;
    //   76: ldc 78
    //   78: putfield 76	o/ᘁ:ﮈ	Ljava/lang/String;
    //   81: aload_0
    //   82: getfield 48	o/ᒾ$if:ܚ	Lo/ᑦ$if;
    //   85: invokeinterface 83 1 0
    //   90: aload_0
    //   91: getfield 39	o/ᒾ$if:শ	Lo/ᒾ;
    //   94: getfield 64	o/ᒾ:ʿ	Lo/ᕑ;
    //   97: ifnull +47 -> 144
    //   100: aload_0
    //   101: getfield 39	o/ᒾ$if:শ	Lo/ᒾ;
    //   104: getfield 64	o/ᒾ:ʿ	Lo/ᕑ;
    //   107: getfield 70	o/ᕑ:ɤ	Lo/ᘁ;
    //   110: aload_2
    //   111: putfield 76	o/ᘁ:ﮈ	Ljava/lang/String;
    //   114: goto +30 -> 144
    //   117: astore_3
    //   118: aload_0
    //   119: getfield 39	o/ᒾ$if:শ	Lo/ᒾ;
    //   122: getfield 64	o/ᒾ:ʿ	Lo/ᕑ;
    //   125: ifnull +17 -> 142
    //   128: aload_0
    //   129: getfield 39	o/ᒾ$if:শ	Lo/ᒾ;
    //   132: getfield 64	o/ᒾ:ʿ	Lo/ᕑ;
    //   135: getfield 70	o/ᕑ:ɤ	Lo/ᘁ;
    //   138: aload_2
    //   139: putfield 76	o/ᘁ:ﮈ	Ljava/lang/String;
    //   142: aload_3
    //   143: athrow
    //   144: aload_0
    //   145: aconst_null
    //   146: putfield 48	o/ᒾ$if:ܚ	Lo/ᑦ$if;
    //   149: aload_0
    //   150: aconst_null
    //   151: putfield 85	o/ᒾ$if:ঌ	Ljava/lang/Object;
    //   154: aload_0
    //   155: iconst_0
    //   156: putfield 60	o/ᒾ$if:ܬ	Z
    //   159: aload_0
    //   160: getfield 58	o/ᒾ$if:ܪ	Lo/ʶ;
    //   163: ifnull +38 -> 201
    //   166: aload_0
    //   167: getfield 87	o/ᒾ$if:ব	Z
    //   170: ifeq +24 -> 194
    //   173: aload_0
    //   174: iconst_0
    //   175: putfield 87	o/ᒾ$if:ব	Z
    //   178: aload_0
    //   179: getfield 58	o/ᒾ$if:ܪ	Lo/ʶ;
    //   182: aload_0
    //   183: invokevirtual 93	o/ᐥ:ˊ	(Lo/ᒾ$if;)V
    //   186: aload_0
    //   187: getfield 58	o/ᒾ$if:ܪ	Lo/ʶ;
    //   190: aload_0
    //   191: invokevirtual 96	o/ᐥ:ˋ	(Lo/ᒾ$if;)V
    //   194: aload_0
    //   195: getfield 58	o/ᒾ$if:ܪ	Lo/ʶ;
    //   198: invokevirtual 99	o/ᐥ:reset	()V
    //   201: return
    // Local variable table:
    //   start	length	slot	name	signature
    //   0	202	0	this	if
    //   9	28	1	bool	boolean
    //   41	98	2	str	String
    //   117	26	3	localObject	Object
    // Exception table:
    //   from	to	target	type
    //   81	90	117	finally
  }
  
  public final void dump(String paramString, FileDescriptor paramFileDescriptor, PrintWriter paramPrintWriter, String[] paramArrayOfString)
  {
    paramPrintWriter.print(paramString);
    paramPrintWriter.print("mId=");
    paramPrintWriter.print(ᗮ);
    paramPrintWriter.print(" mArgs=");
    paramPrintWriter.println(ۊ);
    paramPrintWriter.print(paramString);
    paramPrintWriter.print("mCallbacks=");
    paramPrintWriter.println(ܚ);
    paramPrintWriter.print(paramString);
    paramPrintWriter.print("mLoader=");
    paramPrintWriter.println(ܪ);
    if (ܪ != null) {
      ܪ.dump(paramString + "  ", paramFileDescriptor, paramPrintWriter, paramArrayOfString);
    }
    if ((ܬ) || (र))
    {
      paramPrintWriter.print(paramString);
      paramPrintWriter.print("mHaveData=");
      paramPrintWriter.print(ܬ);
      paramPrintWriter.print("  mDeliveredData=");
      paramPrintWriter.println(र);
      paramPrintWriter.print(paramString);
      paramPrintWriter.print("mData=");
      paramPrintWriter.println(ঌ);
    }
    paramPrintWriter.print(paramString);
    paramPrintWriter.print("mStarted=");
    paramPrintWriter.print(ﾅ);
    paramPrintWriter.print(" mReportNextStart=");
    paramPrintWriter.print(ঢ);
    paramPrintWriter.print(" mDestroyed=");
    paramPrintWriter.println(כֿ);
    paramPrintWriter.print(paramString);
    paramPrintWriter.print("mRetaining=");
    paramPrintWriter.print(є);
    paramPrintWriter.print(" mRetainingStarted=");
    paramPrintWriter.print(গ);
    paramPrintWriter.print(" mListenerRegistered=");
    paramPrintWriter.println(ব);
  }
  
  final void start()
  {
    if ((є) && (গ))
    {
      ﾅ = true;
      return;
    }
    if (ﾅ) {
      return;
    }
    ﾅ = true;
    if ((ܪ == null) && (ܚ != null)) {
      ܪ = ܚ.ᵞ();
    }
    if (ܪ != null)
    {
      if ((ܪ.getClass().isMemberClass()) && (!Modifier.isStatic(ܪ.getClass().getModifiers()))) {
        throw new IllegalArgumentException("Object returned from onCreateLoader must not be a non-static inner member class: " + ܪ);
      }
      if (!ব)
      {
        ʶ localʶ = ܪ;
        int i = ᗮ;
        if (ϒ != null) {
          throw new IllegalStateException("There is already a listener registered");
        }
        ϒ = this;
        ᗮ = i;
        localʶ = ܪ;
        if (Ϝ != null) {
          throw new IllegalStateException("There is already a listener registered");
        }
        Ϝ = this;
        ব = true;
      }
      ܪ.startLoading();
    }
  }
  
  public final void stop()
  {
    ﾅ = false;
    if ((!є) && (ܪ != null) && (ব))
    {
      ব = false;
      ܪ.ˊ(this);
      ܪ.ˋ(this);
      ܪ.stopLoading();
    }
  }
  
  public final String toString()
  {
    StringBuilder localStringBuilder = new StringBuilder(64);
    localStringBuilder.append("LoaderInfo{");
    localStringBuilder.append(Integer.toHexString(System.identityHashCode(this)));
    localStringBuilder.append(" #");
    localStringBuilder.append(ᗮ);
    localStringBuilder.append(" : ");
    ﹳ.ˊ(ܪ, localStringBuilder);
    localStringBuilder.append("}}");
    return localStringBuilder.toString();
  }
  
  public final void ˏ(Object paramObject)
  {
    if (כֿ) {
      return;
    }
    if (শ.ڕ.get(ᗮ) != this) {
      return;
    }
    if ((ঌ != paramObject) || (!ܬ))
    {
      ঌ = paramObject;
      ܬ = true;
      if (ﾅ) {
        ᐝ(paramObject);
      }
    }
    paramObject = (if)শ.ڹ.get(ᗮ);
    if ((paramObject != null) && (paramObject != this))
    {
      र = false;
      ((if)paramObject).destroy();
      শ.ڹ.remove(ᗮ);
    }
    if ((শ.ʿ != null) && (!শ.ᵄ())) {
      শ.ʿ.ɤ.ᔊ();
    }
  }
  
  /* Error */
  public final void ᐝ(Object paramObject)
  {
    // Byte code:
    //   0: aload_0
    //   1: getfield 48	o/ᒾ$if:ܚ	Lo/ᑦ$if;
    //   4: ifnull +114 -> 118
    //   7: aconst_null
    //   8: astore_2
    //   9: aload_0
    //   10: getfield 39	o/ᒾ$if:শ	Lo/ᒾ;
    //   13: getfield 64	o/ᒾ:ʿ	Lo/ᕑ;
    //   16: ifnull +33 -> 49
    //   19: aload_0
    //   20: getfield 39	o/ᒾ$if:শ	Lo/ᒾ;
    //   23: getfield 64	o/ᒾ:ʿ	Lo/ᕑ;
    //   26: getfield 70	o/ᕑ:ɤ	Lo/ᘁ;
    //   29: getfield 76	o/ᘁ:ﮈ	Ljava/lang/String;
    //   32: astore_2
    //   33: aload_0
    //   34: getfield 39	o/ᒾ$if:শ	Lo/ᒾ;
    //   37: getfield 64	o/ᒾ:ʿ	Lo/ᕑ;
    //   40: getfield 70	o/ᕑ:ɤ	Lo/ᘁ;
    //   43: ldc_w 282
    //   46: putfield 76	o/ᘁ:ﮈ	Ljava/lang/String;
    //   49: aload_0
    //   50: getfield 48	o/ᒾ$if:ܚ	Lo/ᑦ$if;
    //   53: aload_1
    //   54: invokeinterface 285 2 0
    //   59: aload_0
    //   60: getfield 39	o/ᒾ$if:শ	Lo/ᒾ;
    //   63: getfield 64	o/ᒾ:ʿ	Lo/ᕑ;
    //   66: ifnull +47 -> 113
    //   69: aload_0
    //   70: getfield 39	o/ᒾ$if:শ	Lo/ᒾ;
    //   73: getfield 64	o/ᒾ:ʿ	Lo/ᕑ;
    //   76: getfield 70	o/ᕑ:ɤ	Lo/ᘁ;
    //   79: aload_2
    //   80: putfield 76	o/ᘁ:ﮈ	Ljava/lang/String;
    //   83: goto +30 -> 113
    //   86: astore_1
    //   87: aload_0
    //   88: getfield 39	o/ᒾ$if:শ	Lo/ᒾ;
    //   91: getfield 64	o/ᒾ:ʿ	Lo/ᕑ;
    //   94: ifnull +17 -> 111
    //   97: aload_0
    //   98: getfield 39	o/ᒾ$if:শ	Lo/ᒾ;
    //   101: getfield 64	o/ᒾ:ʿ	Lo/ᕑ;
    //   104: getfield 70	o/ᕑ:ɤ	Lo/ᘁ;
    //   107: aload_2
    //   108: putfield 76	o/ᘁ:ﮈ	Ljava/lang/String;
    //   111: aload_1
    //   112: athrow
    //   113: aload_0
    //   114: iconst_1
    //   115: putfield 56	o/ᒾ$if:र	Z
    //   118: return
    // Local variable table:
    //   start	length	slot	name	signature
    //   0	119	0	this	if
    //   0	119	1	paramObject	Object
    //   8	100	2	str	String
    // Exception table:
    //   from	to	target	type
    //   49	59	86	finally
  }
  
  final void ﺑ()
  {
    if ((ﾅ) && (ঢ))
    {
      ঢ = false;
      if (ܬ) {
        ᐝ(ঌ);
      }
    }
  }
  
  public final void ﻧ()
  {
    if (כֿ) {
      return;
    }
    if (শ.ڕ.get(ᗮ) != this) {}
  }
}

/* Location:
 * Qualified Name:     o.ᒾ.if
 * Java Class Version: 6 (50.0)
 * JD-Core Version:    0.7.1
 */