package o;

import android.content.ServiceConnection;

public final class ᓗ
  implements ServiceConnection
{
  private static int $$5 = 206;
  private static final short[] $5 = { 23, 92, -53, -18, -2676, 2676 };
  
  private static String $5(byte paramByte, int paramInt, short paramShort)
  {
    short[] arrayOfShort = $5;
    short s = paramShort * 2 + 111;
    int k = 3 - paramByte * 2;
    int i = 0;
    int j = 0;
    paramInt = paramInt * 4 + 4;
    char[] arrayOfChar = new char[k];
    paramByte = paramInt;
    paramShort = s;
    if (arrayOfShort == null)
    {
      paramShort = s;
      s = paramInt;
      paramByte = paramInt;
      paramInt = j;
    }
    for (;;)
    {
      paramByte += 1;
      paramShort = paramShort + s + 2611;
      i = paramInt;
      arrayOfChar[i] = ((char)paramShort);
      paramInt = i + 1;
      if (paramInt == k) {
        return new String(arrayOfChar);
      }
      s = arrayOfShort[paramByte];
    }
  }
  
  public ᓗ(ᒐ paramᒐ) {}
  
  /* Error */
  public final void onServiceConnected(android.content.ComponentName paramComponentName, android.os.IBinder paramIBinder)
  {
    // Byte code:
    //   0: aload_0
    //   1: getfield 35	o/ᓗ:yk$464a5f2	Lo/ᒐ;
    //   4: astore_1
    //   5: aload_2
    //   6: invokestatic 45	o/ᒍ$if:ˋ	(Landroid/os/IBinder;)Lo/ᒍ;
    //   9: astore_2
    //   10: goto +9 -> 19
    //   13: astore_1
    //   14: aload_1
    //   15: invokevirtual 51	java/lang/Throwable:getCause	()Ljava/lang/Throwable;
    //   18: athrow
    //   19: iconst_0
    //   20: iconst_0
    //   21: iconst_0
    //   22: invokestatic 53	o/ᓗ:$5	(BIS)Ljava/lang/String;
    //   25: invokestatic 59	o/ʢ:ˎ	(Ljava/lang/String;)Ljava/lang/Class;
    //   28: ldc 61
    //   30: iconst_2
    //   31: anewarray 63	java/lang/Class
    //   34: dup
    //   35: iconst_0
    //   36: iconst_0
    //   37: iconst_0
    //   38: iconst_0
    //   39: invokestatic 53	o/ᓗ:$5	(BIS)Ljava/lang/String;
    //   42: invokestatic 59	o/ʢ:ˎ	(Ljava/lang/String;)Ljava/lang/Class;
    //   45: aastore
    //   46: dup
    //   47: iconst_1
    //   48: ldc 65
    //   50: aastore
    //   51: invokevirtual 69	java/lang/Class:getMethod	(Ljava/lang/String;[Ljava/lang/Class;)Ljava/lang/reflect/Method;
    //   54: aconst_null
    //   55: iconst_2
    //   56: anewarray 4	java/lang/Object
    //   59: dup
    //   60: iconst_0
    //   61: aload_1
    //   62: aastore
    //   63: dup
    //   64: iconst_1
    //   65: aload_2
    //   66: aastore
    //   67: invokevirtual 75	java/lang/reflect/Method:invoke	(Ljava/lang/Object;[Ljava/lang/Object;)Ljava/lang/Object;
    //   70: pop
    //   71: aload_0
    //   72: getfield 35	o/ᓗ:yk$464a5f2	Lo/ᒐ;
    //   75: astore_1
    //   76: goto +9 -> 85
    //   79: astore_1
    //   80: aload_1
    //   81: invokevirtual 51	java/lang/Throwable:getCause	()Ljava/lang/Throwable;
    //   84: athrow
    //   85: iconst_0
    //   86: iconst_0
    //   87: iconst_0
    //   88: invokestatic 53	o/ᓗ:$5	(BIS)Ljava/lang/String;
    //   91: invokestatic 59	o/ʢ:ˎ	(Ljava/lang/String;)Ljava/lang/Class;
    //   94: ldc 61
    //   96: iconst_1
    //   97: anewarray 63	java/lang/Class
    //   100: dup
    //   101: iconst_0
    //   102: iconst_0
    //   103: iconst_0
    //   104: iconst_0
    //   105: invokestatic 53	o/ᓗ:$5	(BIS)Ljava/lang/String;
    //   108: invokestatic 59	o/ʢ:ˎ	(Ljava/lang/String;)Ljava/lang/Class;
    //   111: aastore
    //   112: invokevirtual 78	java/lang/Class:getDeclaredMethod	(Ljava/lang/String;[Ljava/lang/Class;)Ljava/lang/reflect/Method;
    //   115: aconst_null
    //   116: iconst_1
    //   117: anewarray 4	java/lang/Object
    //   120: dup
    //   121: iconst_0
    //   122: aload_1
    //   123: aastore
    //   124: invokevirtual 75	java/lang/reflect/Method:invoke	(Ljava/lang/Object;[Ljava/lang/Object;)Ljava/lang/Object;
    //   127: checkcast 80	java/lang/Boolean
    //   130: invokevirtual 84	java/lang/Boolean:booleanValue	()Z
    //   133: istore_3
    //   134: iload_3
    //   135: ifne +210 -> 345
    //   138: aload_0
    //   139: getfield 35	o/ᓗ:yk$464a5f2	Lo/ᒐ;
    //   142: astore_1
    //   143: goto +9 -> 152
    //   146: astore_1
    //   147: aload_1
    //   148: invokevirtual 51	java/lang/Throwable:getCause	()Ljava/lang/Throwable;
    //   151: athrow
    //   152: iconst_0
    //   153: iconst_0
    //   154: iconst_0
    //   155: invokestatic 53	o/ᓗ:$5	(BIS)Ljava/lang/String;
    //   158: invokestatic 59	o/ʢ:ˎ	(Ljava/lang/String;)Ljava/lang/Class;
    //   161: ldc 86
    //   163: aconst_null
    //   164: invokevirtual 69	java/lang/Class:getMethod	(Ljava/lang/String;[Ljava/lang/Class;)Ljava/lang/reflect/Method;
    //   167: aload_1
    //   168: aconst_null
    //   169: invokevirtual 75	java/lang/reflect/Method:invoke	(Ljava/lang/Object;[Ljava/lang/Object;)Ljava/lang/Object;
    //   172: checkcast 80	java/lang/Boolean
    //   175: invokevirtual 84	java/lang/Boolean:booleanValue	()Z
    //   178: istore_3
    //   179: iload_3
    //   180: ifeq +165 -> 345
    //   183: aload_0
    //   184: getfield 35	o/ᓗ:yk$464a5f2	Lo/ᒐ;
    //   187: astore_1
    //   188: goto +9 -> 197
    //   191: astore_1
    //   192: aload_1
    //   193: invokevirtual 51	java/lang/Throwable:getCause	()Ljava/lang/Throwable;
    //   196: athrow
    //   197: iconst_0
    //   198: iconst_0
    //   199: iconst_0
    //   200: invokestatic 53	o/ᓗ:$5	(BIS)Ljava/lang/String;
    //   203: invokestatic 59	o/ʢ:ˎ	(Ljava/lang/String;)Ljava/lang/Class;
    //   206: ldc 88
    //   208: aconst_null
    //   209: invokevirtual 69	java/lang/Class:getMethod	(Ljava/lang/String;[Ljava/lang/Class;)Ljava/lang/reflect/Method;
    //   212: aload_1
    //   213: aconst_null
    //   214: invokevirtual 75	java/lang/reflect/Method:invoke	(Ljava/lang/Object;[Ljava/lang/Object;)Ljava/lang/Object;
    //   217: pop
    //   218: aload_0
    //   219: getfield 35	o/ᓗ:yk$464a5f2	Lo/ᒐ;
    //   222: astore_1
    //   223: goto +9 -> 232
    //   226: astore_1
    //   227: aload_1
    //   228: invokevirtual 51	java/lang/Throwable:getCause	()Ljava/lang/Throwable;
    //   231: athrow
    //   232: iconst_0
    //   233: iconst_0
    //   234: iconst_0
    //   235: invokestatic 53	o/ᓗ:$5	(BIS)Ljava/lang/String;
    //   238: invokestatic 59	o/ʢ:ˎ	(Ljava/lang/String;)Ljava/lang/Class;
    //   241: ldc 89
    //   243: iconst_1
    //   244: anewarray 63	java/lang/Class
    //   247: dup
    //   248: iconst_0
    //   249: iconst_0
    //   250: iconst_0
    //   251: iconst_0
    //   252: invokestatic 53	o/ᓗ:$5	(BIS)Ljava/lang/String;
    //   255: invokestatic 59	o/ʢ:ˎ	(Ljava/lang/String;)Ljava/lang/Class;
    //   258: aastore
    //   259: invokevirtual 78	java/lang/Class:getDeclaredMethod	(Ljava/lang/String;[Ljava/lang/Class;)Ljava/lang/reflect/Method;
    //   262: aconst_null
    //   263: iconst_1
    //   264: anewarray 4	java/lang/Object
    //   267: dup
    //   268: iconst_0
    //   269: aload_1
    //   270: aastore
    //   271: invokevirtual 75	java/lang/reflect/Method:invoke	(Ljava/lang/Object;[Ljava/lang/Object;)Ljava/lang/Object;
    //   274: astore_1
    //   275: aload_1
    //   276: ifnull +69 -> 345
    //   279: aload_0
    //   280: getfield 35	o/ᓗ:yk$464a5f2	Lo/ᒐ;
    //   283: astore_1
    //   284: goto +9 -> 293
    //   287: astore_1
    //   288: aload_1
    //   289: invokevirtual 51	java/lang/Throwable:getCause	()Ljava/lang/Throwable;
    //   292: athrow
    //   293: iconst_0
    //   294: iconst_0
    //   295: iconst_0
    //   296: invokestatic 53	o/ᓗ:$5	(BIS)Ljava/lang/String;
    //   299: invokestatic 59	o/ʢ:ˎ	(Ljava/lang/String;)Ljava/lang/Class;
    //   302: ldc 89
    //   304: iconst_1
    //   305: anewarray 63	java/lang/Class
    //   308: dup
    //   309: iconst_0
    //   310: iconst_0
    //   311: iconst_0
    //   312: iconst_0
    //   313: invokestatic 53	o/ᓗ:$5	(BIS)Ljava/lang/String;
    //   316: invokestatic 59	o/ʢ:ˎ	(Ljava/lang/String;)Ljava/lang/Class;
    //   319: aastore
    //   320: invokevirtual 69	java/lang/Class:getMethod	(Ljava/lang/String;[Ljava/lang/Class;)Ljava/lang/reflect/Method;
    //   323: aconst_null
    //   324: iconst_1
    //   325: anewarray 4	java/lang/Object
    //   328: dup
    //   329: iconst_0
    //   330: aload_1
    //   331: aastore
    //   332: invokevirtual 75	java/lang/reflect/Method:invoke	(Ljava/lang/Object;[Ljava/lang/Object;)Ljava/lang/Object;
    //   335: checkcast 91	o/ᓕ$if
    //   338: astore_1
    //   339: aload_1
    //   340: invokeinterface 94 1 0
    //   345: aload_0
    //   346: getfield 35	o/ᓗ:yk$464a5f2	Lo/ᒐ;
    //   349: astore_1
    //   350: goto +9 -> 359
    //   353: astore_1
    //   354: aload_1
    //   355: invokevirtual 51	java/lang/Throwable:getCause	()Ljava/lang/Throwable;
    //   358: athrow
    //   359: iconst_0
    //   360: iconst_0
    //   361: iconst_0
    //   362: invokestatic 53	o/ᓗ:$5	(BIS)Ljava/lang/String;
    //   365: invokestatic 59	o/ʢ:ˎ	(Ljava/lang/String;)Ljava/lang/Class;
    //   368: ldc 89
    //   370: iconst_1
    //   371: anewarray 63	java/lang/Class
    //   374: dup
    //   375: iconst_0
    //   376: iconst_0
    //   377: iconst_0
    //   378: iconst_0
    //   379: invokestatic 53	o/ᓗ:$5	(BIS)Ljava/lang/String;
    //   382: invokestatic 59	o/ʢ:ˎ	(Ljava/lang/String;)Ljava/lang/Class;
    //   385: aastore
    //   386: invokevirtual 69	java/lang/Class:getMethod	(Ljava/lang/String;[Ljava/lang/Class;)Ljava/lang/reflect/Method;
    //   389: aconst_null
    //   390: iconst_1
    //   391: anewarray 4	java/lang/Object
    //   394: dup
    //   395: iconst_0
    //   396: aload_1
    //   397: aastore
    //   398: invokevirtual 75	java/lang/reflect/Method:invoke	(Ljava/lang/Object;[Ljava/lang/Object;)Ljava/lang/Object;
    //   401: astore_1
    //   402: aload_1
    //   403: ifnull +69 -> 472
    //   406: aload_0
    //   407: getfield 35	o/ᓗ:yk$464a5f2	Lo/ᒐ;
    //   410: astore_1
    //   411: goto +9 -> 420
    //   414: astore_1
    //   415: aload_1
    //   416: invokevirtual 51	java/lang/Throwable:getCause	()Ljava/lang/Throwable;
    //   419: athrow
    //   420: iconst_0
    //   421: iconst_0
    //   422: iconst_0
    //   423: invokestatic 53	o/ᓗ:$5	(BIS)Ljava/lang/String;
    //   426: invokestatic 59	o/ʢ:ˎ	(Ljava/lang/String;)Ljava/lang/Class;
    //   429: ldc 89
    //   431: iconst_1
    //   432: anewarray 63	java/lang/Class
    //   435: dup
    //   436: iconst_0
    //   437: iconst_0
    //   438: iconst_0
    //   439: iconst_0
    //   440: invokestatic 53	o/ᓗ:$5	(BIS)Ljava/lang/String;
    //   443: invokestatic 59	o/ʢ:ˎ	(Ljava/lang/String;)Ljava/lang/Class;
    //   446: aastore
    //   447: invokevirtual 69	java/lang/Class:getMethod	(Ljava/lang/String;[Ljava/lang/Class;)Ljava/lang/reflect/Method;
    //   450: aconst_null
    //   451: iconst_1
    //   452: anewarray 4	java/lang/Object
    //   455: dup
    //   456: iconst_0
    //   457: aload_1
    //   458: aastore
    //   459: invokevirtual 75	java/lang/reflect/Method:invoke	(Ljava/lang/Object;[Ljava/lang/Object;)Ljava/lang/Object;
    //   462: checkcast 91	o/ᓕ$if
    //   465: astore_1
    //   466: aload_1
    //   467: invokeinterface 97 1 0
    //   472: return
    // Local variable table:
    //   start	length	slot	name	signature
    //   0	473	0	this	ᓗ
    //   0	473	1	paramComponentName	android.content.ComponentName
    //   0	473	2	paramIBinder	android.os.IBinder
    //   133	47	3	bool	boolean
    // Exception table:
    //   from	to	target	type
    //   19	71	13	finally
    //   85	134	79	finally
    //   152	179	146	finally
    //   197	218	191	finally
    //   232	275	226	finally
    //   293	339	287	finally
    //   359	402	353	finally
    //   420	466	414	finally
  }
  
  /* Error */
  public final void onServiceDisconnected(android.content.ComponentName paramComponentName)
  {
    // Byte code:
    //   0: aload_0
    //   1: getfield 35	o/ᓗ:yk$464a5f2	Lo/ᒐ;
    //   4: astore_1
    //   5: goto +9 -> 14
    //   8: astore_1
    //   9: aload_1
    //   10: invokevirtual 51	java/lang/Throwable:getCause	()Ljava/lang/Throwable;
    //   13: athrow
    //   14: iconst_0
    //   15: iconst_0
    //   16: iconst_0
    //   17: invokestatic 53	o/ᓗ:$5	(BIS)Ljava/lang/String;
    //   20: invokestatic 59	o/ʢ:ˎ	(Ljava/lang/String;)Ljava/lang/Class;
    //   23: ldc 61
    //   25: iconst_2
    //   26: anewarray 63	java/lang/Class
    //   29: dup
    //   30: iconst_0
    //   31: iconst_0
    //   32: iconst_0
    //   33: iconst_0
    //   34: invokestatic 53	o/ᓗ:$5	(BIS)Ljava/lang/String;
    //   37: invokestatic 59	o/ʢ:ˎ	(Ljava/lang/String;)Ljava/lang/Class;
    //   40: aastore
    //   41: dup
    //   42: iconst_1
    //   43: ldc 65
    //   45: aastore
    //   46: invokevirtual 78	java/lang/Class:getDeclaredMethod	(Ljava/lang/String;[Ljava/lang/Class;)Ljava/lang/reflect/Method;
    //   49: aconst_null
    //   50: iconst_2
    //   51: anewarray 4	java/lang/Object
    //   54: dup
    //   55: iconst_0
    //   56: aload_1
    //   57: aastore
    //   58: dup
    //   59: iconst_1
    //   60: aconst_null
    //   61: aastore
    //   62: invokevirtual 75	java/lang/reflect/Method:invoke	(Ljava/lang/Object;[Ljava/lang/Object;)Ljava/lang/Object;
    //   65: pop
    //   66: return
    // Local variable table:
    //   start	length	slot	name	signature
    //   0	67	0	this	ᓗ
    //   0	67	1	paramComponentName	android.content.ComponentName
    // Exception table:
    //   from	to	target	type
    //   14	66	8	finally
  }
}

/* Location:
 * Qualified Name:     o.ᓗ
 * Java Class Version: 6 (50.0)
 * JD-Core Version:    0.7.1
 */