package o;

import android.app.Activity;
import android.content.SharedPreferences;
import android.content.SharedPreferences.Editor;
import android.graphics.Point;
import android.preference.PreferenceManager;
import android.widget.FrameLayout;
import java.util.Map;

public abstract class ᓾ
  extends Ꮀ
{
  private static int $$5;
  private static final short[] $5;
  public static long w;
  public static long x;
  public static long y;
  public static long yD;
  private static int yP;
  private static int yQ;
  private static final byte[] yR;
  private static int yS;
  private static aln yz;
  public int mode = 1;
  protected ท yA;
  private ฅ yB;
  private if yC = new if((byte)0);
  protected boolean yE = false;
  protected boolean yF = true;
  public boolean yG = false;
  protected boolean yH = false;
  protected Point yI = new Point();
  private boolean yJ;
  protected boolean yK;
  protected boolean yL;
  protected FrameLayout yM;
  boolean yN;
  protected boolean yO;
  protected aks yy;
  
  private static String $5(int paramInt1, short paramShort, int paramInt2)
  {
    int k = 0;
    int m = 0;
    paramShort = 3 - paramShort * 2;
    int n = 3 - paramInt2 * 2;
    short[] arrayOfShort = $5;
    paramInt1 = paramInt1 * 3 + 111;
    char[] arrayOfChar = new char[n];
    paramInt2 = paramInt1;
    int j = paramShort;
    if (arrayOfShort == null)
    {
      paramInt2 = paramShort;
      j = paramInt1;
      paramInt1 = m;
    }
    for (;;)
    {
      paramInt2 = paramInt2 + -j + 268;
      j = paramShort;
      k = paramInt1;
      int i = (char)paramInt2;
      paramInt1 = k + 1;
      arrayOfChar[k] = i;
      paramShort = j + 1;
      if (paramInt1 == n) {
        return new String(arrayOfChar);
      }
      j = arrayOfShort[paramShort];
    }
  }
  
  /* Error */
  static
  {
    // Byte code:
    //   0: bipush 6
    //   2: newarray <illegal type>
    //   4: dup
    //   5: iconst_0
    //   6: ldc 61
    //   8: sastore
    //   9: dup
    //   10: iconst_1
    //   11: ldc 62
    //   13: sastore
    //   14: dup
    //   15: iconst_2
    //   16: ldc 63
    //   18: sastore
    //   19: dup
    //   20: iconst_3
    //   21: ldc 64
    //   23: sastore
    //   24: dup
    //   25: iconst_4
    //   26: ldc 65
    //   28: sastore
    //   29: dup
    //   30: iconst_5
    //   31: ldc 66
    //   33: sastore
    //   34: putstatic 49	o/ᓾ:$5	[S
    //   37: sipush 176
    //   40: putstatic 68	o/ᓾ:$$5	I
    //   43: goto +6 -> 49
    //   46: astore_0
    //   47: aload_0
    //   48: athrow
    //   49: sipush 142
    //   52: newarray <illegal type>
    //   54: dup
    //   55: iconst_0
    //   56: ldc 61
    //   58: bastore
    //   59: dup
    //   60: iconst_1
    //   61: ldc 62
    //   63: bastore
    //   64: dup
    //   65: iconst_2
    //   66: ldc 63
    //   68: bastore
    //   69: dup
    //   70: iconst_3
    //   71: ldc 64
    //   73: bastore
    //   74: dup
    //   75: iconst_4
    //   76: ldc 69
    //   78: bastore
    //   79: dup
    //   80: iconst_5
    //   81: ldc 70
    //   83: bastore
    //   84: dup
    //   85: bipush 6
    //   87: ldc 71
    //   89: bastore
    //   90: dup
    //   91: bipush 7
    //   93: ldc 72
    //   95: bastore
    //   96: dup
    //   97: bipush 8
    //   99: ldc 62
    //   101: bastore
    //   102: dup
    //   103: bipush 9
    //   105: ldc 71
    //   107: bastore
    //   108: dup
    //   109: bipush 10
    //   111: ldc 73
    //   113: bastore
    //   114: dup
    //   115: bipush 11
    //   117: ldc 74
    //   119: bastore
    //   120: dup
    //   121: bipush 12
    //   123: ldc 75
    //   125: bastore
    //   126: dup
    //   127: bipush 13
    //   129: ldc 69
    //   131: bastore
    //   132: dup
    //   133: bipush 14
    //   135: ldc 76
    //   137: bastore
    //   138: dup
    //   139: bipush 15
    //   141: ldc 77
    //   143: bastore
    //   144: dup
    //   145: bipush 16
    //   147: ldc 72
    //   149: bastore
    //   150: dup
    //   151: bipush 17
    //   153: ldc 78
    //   155: bastore
    //   156: dup
    //   157: bipush 18
    //   159: ldc 73
    //   161: bastore
    //   162: dup
    //   163: bipush 19
    //   165: ldc 69
    //   167: bastore
    //   168: dup
    //   169: bipush 20
    //   171: ldc 79
    //   173: bastore
    //   174: dup
    //   175: bipush 21
    //   177: ldc 80
    //   179: bastore
    //   180: dup
    //   181: bipush 22
    //   183: ldc 81
    //   185: bastore
    //   186: dup
    //   187: bipush 23
    //   189: ldc 74
    //   191: bastore
    //   192: dup
    //   193: bipush 24
    //   195: ldc 76
    //   197: bastore
    //   198: dup
    //   199: bipush 25
    //   201: ldc 82
    //   203: bastore
    //   204: dup
    //   205: bipush 26
    //   207: ldc 73
    //   209: bastore
    //   210: dup
    //   211: bipush 27
    //   213: ldc 83
    //   215: bastore
    //   216: dup
    //   217: bipush 28
    //   219: ldc 84
    //   221: bastore
    //   222: dup
    //   223: bipush 29
    //   225: ldc 85
    //   227: bastore
    //   228: dup
    //   229: bipush 30
    //   231: ldc 74
    //   233: bastore
    //   234: dup
    //   235: bipush 31
    //   237: ldc 71
    //   239: bastore
    //   240: dup
    //   241: bipush 32
    //   243: ldc 86
    //   245: bastore
    //   246: dup
    //   247: bipush 33
    //   249: ldc 87
    //   251: bastore
    //   252: dup
    //   253: bipush 34
    //   255: ldc 88
    //   257: bastore
    //   258: dup
    //   259: bipush 35
    //   261: ldc 81
    //   263: bastore
    //   264: dup
    //   265: bipush 36
    //   267: ldc 89
    //   269: bastore
    //   270: dup
    //   271: bipush 37
    //   273: ldc 90
    //   275: bastore
    //   276: dup
    //   277: bipush 38
    //   279: ldc 91
    //   281: bastore
    //   282: dup
    //   283: bipush 39
    //   285: ldc 92
    //   287: bastore
    //   288: dup
    //   289: bipush 40
    //   291: ldc 93
    //   293: bastore
    //   294: dup
    //   295: bipush 41
    //   297: ldc 70
    //   299: bastore
    //   300: dup
    //   301: bipush 42
    //   303: ldc 74
    //   305: bastore
    //   306: dup
    //   307: bipush 43
    //   309: ldc 74
    //   311: bastore
    //   312: dup
    //   313: bipush 44
    //   315: ldc 71
    //   317: bastore
    //   318: dup
    //   319: bipush 45
    //   321: ldc 75
    //   323: bastore
    //   324: dup
    //   325: bipush 46
    //   327: ldc 80
    //   329: bastore
    //   330: dup
    //   331: bipush 47
    //   333: ldc 71
    //   335: bastore
    //   336: dup
    //   337: bipush 48
    //   339: ldc 81
    //   341: bastore
    //   342: dup
    //   343: bipush 49
    //   345: ldc 94
    //   347: bastore
    //   348: dup
    //   349: bipush 50
    //   351: ldc 69
    //   353: bastore
    //   354: dup
    //   355: bipush 51
    //   357: ldc 94
    //   359: bastore
    //   360: dup
    //   361: bipush 52
    //   363: ldc 79
    //   365: bastore
    //   366: dup
    //   367: bipush 53
    //   369: ldc 71
    //   371: bastore
    //   372: dup
    //   373: bipush 54
    //   375: ldc 85
    //   377: bastore
    //   378: dup
    //   379: bipush 55
    //   381: ldc 91
    //   383: bastore
    //   384: dup
    //   385: bipush 56
    //   387: ldc 80
    //   389: bastore
    //   390: dup
    //   391: bipush 57
    //   393: ldc 95
    //   395: bastore
    //   396: dup
    //   397: bipush 58
    //   399: ldc 77
    //   401: bastore
    //   402: dup
    //   403: bipush 59
    //   405: ldc 81
    //   407: bastore
    //   408: dup
    //   409: bipush 60
    //   411: ldc 85
    //   413: bastore
    //   414: dup
    //   415: bipush 61
    //   417: ldc 74
    //   419: bastore
    //   420: dup
    //   421: bipush 62
    //   423: ldc 94
    //   425: bastore
    //   426: dup
    //   427: bipush 63
    //   429: ldc 75
    //   431: bastore
    //   432: dup
    //   433: bipush 64
    //   435: ldc 94
    //   437: bastore
    //   438: dup
    //   439: bipush 65
    //   441: ldc 80
    //   443: bastore
    //   444: dup
    //   445: bipush 66
    //   447: ldc 96
    //   449: bastore
    //   450: dup
    //   451: bipush 67
    //   453: ldc 71
    //   455: bastore
    //   456: dup
    //   457: bipush 68
    //   459: ldc 97
    //   461: bastore
    //   462: dup
    //   463: bipush 69
    //   465: ldc 71
    //   467: bastore
    //   468: dup
    //   469: bipush 70
    //   471: ldc 79
    //   473: bastore
    //   474: dup
    //   475: bipush 71
    //   477: ldc 80
    //   479: bastore
    //   480: dup
    //   481: bipush 72
    //   483: ldc 71
    //   485: bastore
    //   486: dup
    //   487: bipush 73
    //   489: ldc 85
    //   491: bastore
    //   492: dup
    //   493: bipush 74
    //   495: ldc 74
    //   497: bastore
    //   498: dup
    //   499: bipush 75
    //   501: ldc 98
    //   503: bastore
    //   504: dup
    //   505: bipush 76
    //   507: ldc 74
    //   509: bastore
    //   510: dup
    //   511: bipush 77
    //   513: ldc 69
    //   515: bastore
    //   516: dup
    //   517: bipush 78
    //   519: ldc 79
    //   521: bastore
    //   522: dup
    //   523: bipush 79
    //   525: ldc 99
    //   527: bastore
    //   528: dup
    //   529: bipush 80
    //   531: ldc 100
    //   533: bastore
    //   534: dup
    //   535: bipush 81
    //   537: ldc 69
    //   539: bastore
    //   540: dup
    //   541: bipush 82
    //   543: ldc 88
    //   545: bastore
    //   546: dup
    //   547: bipush 83
    //   549: ldc 73
    //   551: bastore
    //   552: dup
    //   553: bipush 84
    //   555: ldc 69
    //   557: bastore
    //   558: dup
    //   559: bipush 85
    //   561: ldc 101
    //   563: bastore
    //   564: dup
    //   565: bipush 86
    //   567: ldc 102
    //   569: bastore
    //   570: dup
    //   571: bipush 87
    //   573: ldc 103
    //   575: bastore
    //   576: dup
    //   577: bipush 88
    //   579: ldc 92
    //   581: bastore
    //   582: dup
    //   583: bipush 89
    //   585: ldc 104
    //   587: bastore
    //   588: dup
    //   589: bipush 90
    //   591: ldc 79
    //   593: bastore
    //   594: dup
    //   595: bipush 91
    //   597: ldc 71
    //   599: bastore
    //   600: dup
    //   601: bipush 92
    //   603: ldc 105
    //   605: bastore
    //   606: dup
    //   607: bipush 93
    //   609: ldc 106
    //   611: bastore
    //   612: dup
    //   613: bipush 94
    //   615: ldc 107
    //   617: bastore
    //   618: dup
    //   619: bipush 95
    //   621: ldc 74
    //   623: bastore
    //   624: dup
    //   625: bipush 96
    //   627: ldc 73
    //   629: bastore
    //   630: dup
    //   631: bipush 97
    //   633: ldc 69
    //   635: bastore
    //   636: dup
    //   637: bipush 98
    //   639: ldc 101
    //   641: bastore
    //   642: dup
    //   643: bipush 99
    //   645: ldc 102
    //   647: bastore
    //   648: dup
    //   649: bipush 100
    //   651: ldc 103
    //   653: bastore
    //   654: dup
    //   655: bipush 101
    //   657: ldc 92
    //   659: bastore
    //   660: dup
    //   661: bipush 102
    //   663: ldc 104
    //   665: bastore
    //   666: dup
    //   667: bipush 103
    //   669: ldc 79
    //   671: bastore
    //   672: dup
    //   673: bipush 104
    //   675: ldc 71
    //   677: bastore
    //   678: dup
    //   679: bipush 105
    //   681: ldc 69
    //   683: bastore
    //   684: dup
    //   685: bipush 106
    //   687: ldc 80
    //   689: bastore
    //   690: dup
    //   691: bipush 107
    //   693: ldc 75
    //   695: bastore
    //   696: dup
    //   697: bipush 108
    //   699: ldc 70
    //   701: bastore
    //   702: dup
    //   703: bipush 109
    //   705: ldc 108
    //   707: bastore
    //   708: dup
    //   709: bipush 110
    //   711: ldc 81
    //   713: bastore
    //   714: dup
    //   715: bipush 111
    //   717: ldc 109
    //   719: bastore
    //   720: dup
    //   721: bipush 112
    //   723: ldc 70
    //   725: bastore
    //   726: dup
    //   727: bipush 113
    //   729: ldc 109
    //   731: bastore
    //   732: dup
    //   733: bipush 114
    //   735: ldc 110
    //   737: bastore
    //   738: dup
    //   739: bipush 115
    //   741: ldc 111
    //   743: bastore
    //   744: dup
    //   745: bipush 116
    //   747: ldc 112
    //   749: bastore
    //   750: dup
    //   751: bipush 117
    //   753: ldc 85
    //   755: bastore
    //   756: dup
    //   757: bipush 118
    //   759: ldc 108
    //   761: bastore
    //   762: dup
    //   763: bipush 119
    //   765: ldc 79
    //   767: bastore
    //   768: dup
    //   769: bipush 120
    //   771: ldc 69
    //   773: bastore
    //   774: dup
    //   775: bipush 121
    //   777: ldc 85
    //   779: bastore
    //   780: dup
    //   781: bipush 122
    //   783: ldc 70
    //   785: bastore
    //   786: dup
    //   787: bipush 123
    //   789: ldc 108
    //   791: bastore
    //   792: dup
    //   793: bipush 124
    //   795: ldc 81
    //   797: bastore
    //   798: dup
    //   799: bipush 125
    //   801: ldc 95
    //   803: bastore
    //   804: dup
    //   805: bipush 126
    //   807: ldc 113
    //   809: bastore
    //   810: dup
    //   811: bipush 127
    //   813: ldc 114
    //   815: bastore
    //   816: dup
    //   817: sipush 128
    //   820: ldc 109
    //   822: bastore
    //   823: dup
    //   824: sipush 129
    //   827: ldc 79
    //   829: bastore
    //   830: dup
    //   831: sipush 130
    //   834: ldc 80
    //   836: bastore
    //   837: dup
    //   838: sipush 131
    //   841: ldc 69
    //   843: bastore
    //   844: dup
    //   845: sipush 132
    //   848: ldc 108
    //   850: bastore
    //   851: dup
    //   852: sipush 133
    //   855: ldc 70
    //   857: bastore
    //   858: dup
    //   859: sipush 134
    //   862: ldc 94
    //   864: bastore
    //   865: dup
    //   866: sipush 135
    //   869: ldc 99
    //   871: bastore
    //   872: dup
    //   873: sipush 136
    //   876: ldc 115
    //   878: bastore
    //   879: dup
    //   880: sipush 137
    //   883: ldc 82
    //   885: bastore
    //   886: dup
    //   887: sipush 138
    //   890: ldc 79
    //   892: bastore
    //   893: dup
    //   894: sipush 139
    //   897: ldc 76
    //   899: bastore
    //   900: dup
    //   901: sipush 140
    //   904: ldc 96
    //   906: bastore
    //   907: dup
    //   908: sipush 141
    //   911: ldc 94
    //   913: bastore
    //   914: putstatic 117	o/ᓾ:yR	[B
    //   917: bipush 23
    //   919: putstatic 119	o/ᓾ:yS	I
    //   922: iconst_0
    //   923: putstatic 121	o/ᓾ:yP	I
    //   926: iconst_1
    //   927: putstatic 123	o/ᓾ:yQ	I
    //   930: ldc2_w 124
    //   933: putstatic 127	o/ᓾ:x	J
    //   936: ldc2_w 124
    //   939: putstatic 129	o/ᓾ:y	J
    //   942: ldc2_w 124
    //   945: putstatic 131	o/ᓾ:yD	J
    //   948: ldc2_w 124
    //   951: putstatic 133	o/ᓾ:w	J
    //   954: return
    //   955: astore_0
    //   956: aload_0
    //   957: athrow
    // Local variable table:
    //   start	length	slot	name	signature
    //   46	2	0	localException1	Exception
    //   955	2	0	localException2	Exception
    // Exception table:
    //   from	to	target	type
    //   922	926	46	java/lang/Exception
    //   49	917	955	java/lang/Exception
    //   917	922	955	java/lang/Exception
    //   922	926	955	java/lang/Exception
    //   926	930	955	java/lang/Exception
    //   930	936	955	java/lang/Exception
    //   936	942	955	java/lang/Exception
    //   942	948	955	java/lang/Exception
    //   948	954	955	java/lang/Exception
  }
  
  public static boolean ʼ(Activity paramActivity)
  {
    for (;;)
    {
      i = 1;
      break label65;
      if (PreferenceManager.getDefaultSharedPreferences(paramActivity).getString(ˊ((short)yR[114], (byte)yR[66], (byte)yR[68]), "").hashCode() == 1662) {
        break;
      }
    }
    int i = 0;
    break label65;
    return false;
    label65:
    switch (i)
    {
    }
    return true;
  }
  
  private static String ˊ(int paramInt, byte paramByte, short paramShort)
  {
    break label102;
    byte[] arrayOfByte2;
    return new String(arrayOfByte2, 0).intern();
    for (;;)
    {
      byte b1 = paramInt;
      paramInt = b1 + 1;
      arrayOfByte2[b1] = ((byte)paramByte);
      paramShort += 1;
      if (paramInt == i) {
        break;
      }
      byte b2;
      try
      {
        for (;;)
        {
          b1 = yP + 47;
          try
          {
            yQ = b1 % 128;
            if (b1 % 2 == 0) {
              break;
            }
            paramByte = b2 + paramByte - 8;
          }
          catch (Exception localException1)
          {
            Object localObject;
            throw localException1;
          }
          b2 = localObject[paramShort];
        }
        b2 = 0;
      }
      catch (Exception localException2)
      {
        throw localException2;
      }
      label102:
      b1 = paramShort + 71;
      paramShort = 132 - paramInt;
      byte[] arrayOfByte1 = yR;
      int i = paramByte + 2;
      arrayOfByte2 = new byte[i];
      paramInt = b2;
      paramByte = b1;
    }
  }
  
  public static String י(String paramString)
  {
    if (yz == null) {
      yz = aln.bd();
    }
    paramString = yz.getString("ad_unit_id_" + paramString, "configns:firebase").split("\\s");
    if (paramString.length == 0) {
      return null;
    }
    if (paramString.length == 1) {
      return paramString[0];
    }
    return paramString[((int)(android.os.SystemClock.uptimeMillis() % paramString.length))];
  }
  
  private void Ⅼ()
  {
    break label555;
    label15:
    do
    {
      i = 89;
      break label586;
      i = 90;
      break;
      i = 60;
      break label361;
      if (w + 612133L + ﾚ.z == 0L) {
        i = 1;
      } else {
        i = 0;
      }
    } while (i != 0);
    break label503;
    switch (i)
    {
    default: 
      label51:
      break label746;
      label75:
      i = 0;
      break;
      label80:
      i = 17;
      break;
    }
    try
    {
      label86:
      i = mode;
      if (i == 3) {
        break label356;
      }
    }
    catch (Exception localException1)
    {
      label99:
      Object localObject1;
      throw localException1;
    }
    л.ˊ(ˊ((short)(yR[75] - 1), (byte)yR[22], (byte)yR[114]), "mode", ˊ((short)yR[17], (byte)yR[57], (byte)yR[114]), 0);
    return;
    label156:
    byte b;
    switch (i)
    {
    default: 
      break;
      localObject1 = yR;
      i = (short)(localObject1[75] - 1);
      localObject1 = yR;
      b = (byte)localObject1[22];
    }
    short s;
    Object localObject3;
    int j;
    try
    {
      localObject1 = yR;
      s = (byte)localObject1[114];
      localObject1 = ˊ(i, b, s);
      localObject3 = yR;
      i = (short)(localObject3[86] - 1);
      j = yR[11];
      b = (byte)j;
      j = yS;
      s = (byte)(j << 1);
      localObject3 = ˊ(i, b, s);
      л.ˊ((String)localObject1, "mode", (String)localObject3, 0);
      return;
    }
    catch (Exception localException2)
    {
      label281:
      label287:
      label311:
      label350:
      label356:
      label361:
      label383:
      label440:
      label503:
      throw localException2;
    }
    int i = 20;
    break label607;
    switch (i)
    {
    }
    for (;;)
    {
      ((SharedPreferences)localObject1).edit().putInt("app_old_mode_pref", mode).apply();
      if (mode == 1) {
        break label80;
      }
      break label15;
      i = 44;
      break label607;
      i = 0;
      break label156;
      switch (i)
      {
      }
      break label440;
      л.ˊ(ˊ((short)(yR[75] - 1), (byte)yR[22], (byte)yR[114]), "mode", ˊ((short)yR[38], (byte)yR[57], (byte)yR[68]), 0);
      return;
      л.ˊ(ˊ((short)(yR[75] - 1), (byte)yR[22], (byte)yR[114]), "mode", ˊ((short)(yR[2] + 1), (byte)yR[75], (byte)yR[68]), 0);
      break label86;
      label555:
      label586:
      label607:
      label631:
      label636:
      label746:
      do
      {
        break label311;
        i = 59;
        break label586;
        for (;;)
        {
          i = 12;
          break label51;
          if (mode == 2) {
            break label631;
          }
          break label75;
          i = yP + 63;
          yQ = i % 128;
          if (i % 2 != 0) {
            break label383;
          }
          break label383;
          localObject2 = PreferenceManager.getDefaultSharedPreferences(this);
          if (((SharedPreferences)localObject2).getInt("app_old_mode_pref", -1) != mode) {
            break;
          }
        }
        i = 1;
        break label156;
        switch (i)
        {
        }
        break label99;
        switch (i)
        {
        }
        break label636;
        i = 1;
        break label287;
        Object localObject2 = yR;
        i = (short)(localObject2[75] - 1);
        localObject2 = yR;
        b = (byte)localObject2[22];
        j = yR[114];
        s = (byte)j;
        localObject2 = ˊ(i, b, s);
        localObject3 = yR;
        i = (short)localObject3[22];
        j = yR[49];
        b = (byte)j;
        j = yR[87];
        s = (byte)j;
        localObject3 = ˊ(i, b, s);
        л.ˊ((String)localObject2, "mode", (String)localObject3, 0);
        return;
        if (ⅴ()) {
          break label281;
        }
        break label350;
        i = yP + 33;
        yQ = i % 128;
      } while (i % 2 == 0);
    }
  }
  
  private static boolean ⅴ()
  {
    return yD + w + x + y * (y + 714179L) == 242906121825L;
  }
  
  public static boolean ィ()
  {
    return w + 612133L + ﾚ.z == 0L;
  }
  
  public static boolean ךּ()
  {
    return w == 46422355215963731L - y * (ﾚ.z * 714179L + 136488177048L) - (yD + x + y * y) * (ﾚ.z + 191112L) + ﾚ.z * 242906542846L;
  }
  
  /* Error */
  public void onActivityResult(int paramInt1, int paramInt2, android.content.Intent paramIntent)
  {
    // Byte code:
    //   0: goto +9 -> 9
    //   3: astore_3
    //   4: aload_3
    //   5: invokevirtual 285	java/lang/Throwable:getCause	()Ljava/lang/Throwable;
    //   8: athrow
    //   9: iconst_0
    //   10: iconst_0
    //   11: iconst_0
    //   12: invokestatic 287	o/ᓾ:$5	(ISI)Ljava/lang/String;
    //   15: invokestatic 293	o/ʢ:ˎ	(Ljava/lang/String;)Ljava/lang/Class;
    //   18: ldc_w 295
    //   21: iconst_3
    //   22: anewarray 297	java/lang/Class
    //   25: dup
    //   26: iconst_0
    //   27: getstatic 303	java/lang/Integer:TYPE	Ljava/lang/Class;
    //   30: aastore
    //   31: dup
    //   32: iconst_1
    //   33: getstatic 303	java/lang/Integer:TYPE	Ljava/lang/Class;
    //   36: aastore
    //   37: dup
    //   38: iconst_2
    //   39: ldc_w 305
    //   42: aastore
    //   43: invokevirtual 309	java/lang/Class:getMethod	(Ljava/lang/String;[Ljava/lang/Class;)Ljava/lang/reflect/Method;
    //   46: aconst_null
    //   47: iconst_3
    //   48: anewarray 311	java/lang/Object
    //   51: dup
    //   52: iconst_0
    //   53: iload_1
    //   54: invokestatic 315	java/lang/Integer:valueOf	(I)Ljava/lang/Integer;
    //   57: aastore
    //   58: dup
    //   59: iconst_1
    //   60: iload_2
    //   61: invokestatic 315	java/lang/Integer:valueOf	(I)Ljava/lang/Integer;
    //   64: aastore
    //   65: dup
    //   66: iconst_2
    //   67: aload_3
    //   68: aastore
    //   69: invokevirtual 321	java/lang/reflect/Method:invoke	(Ljava/lang/Object;[Ljava/lang/Object;)Ljava/lang/Object;
    //   72: checkcast 323	java/lang/Boolean
    //   75: invokevirtual 326	java/lang/Boolean:booleanValue	()Z
    //   78: istore 4
    //   80: iload 4
    //   82: ifne +10 -> 92
    //   85: aload_0
    //   86: iload_1
    //   87: iload_2
    //   88: aload_3
    //   89: invokespecial 328	o/Ꮀ:onActivityResult	(IILandroid/content/Intent;)V
    //   92: return
    // Local variable table:
    //   start	length	slot	name	signature
    //   0	93	0	this	ᓾ
    //   0	93	1	paramInt1	int
    //   0	93	2	paramInt2	int
    //   0	93	3	paramIntent	android.content.Intent
    //   78	3	4	bool	boolean
    // Exception table:
    //   from	to	target	type
    //   9	80	3	finally
  }
  
  /* Error */
  public void onCreate(android.os.Bundle paramBundle)
  {
    // Byte code:
    //   0: goto +435 -> 435
    //   3: iload_3
    //   4: tableswitch	default:+24->28, 0:+492->496, 1:+298->302
    //   28: aload_1
    //   29: astore 6
    //   31: goto +457 -> 488
    //   34: iload 5
    //   36: istore 4
    //   38: aload_1
    //   39: astore 6
    //   41: iload_3
    //   42: tableswitch	default:+22->64, 0:+887->929, 1:+181->223
    //   64: goto +860 -> 924
    //   67: getstatic 117	o/ᓾ:yR	[B
    //   70: bipush 33
    //   72: baload
    //   73: i2s
    //   74: getstatic 117	o/ᓾ:yR	[B
    //   77: bipush 75
    //   79: baload
    //   80: i2b
    //   81: getstatic 117	o/ᓾ:yR	[B
    //   84: bipush 87
    //   86: baload
    //   87: i2b
    //   88: invokestatic 167	o/ᓾ:ˊ	(IBS)Ljava/lang/String;
    //   91: astore_1
    //   92: goto +222 -> 314
    //   95: getstatic 121	o/ᓾ:yP	I
    //   98: bipush 75
    //   100: iadd
    //   101: istore_3
    //   102: iload_3
    //   103: sipush 128
    //   106: irem
    //   107: putstatic 123	o/ᓾ:yQ	I
    //   110: iload_3
    //   111: iconst_2
    //   112: irem
    //   113: ifeq +808 -> 921
    //   116: goto +254 -> 370
    //   119: getstatic 121	o/ᓾ:yP	I
    //   122: bipush 119
    //   124: iadd
    //   125: istore_3
    //   126: iload_3
    //   127: sipush 128
    //   130: irem
    //   131: putstatic 123	o/ᓾ:yQ	I
    //   134: iload_3
    //   135: iconst_2
    //   136: irem
    //   137: ifeq +117 -> 254
    //   140: goto -73 -> 67
    //   143: goto +430 -> 573
    //   146: ldc_w 332
    //   149: astore_1
    //   150: goto +473 -> 623
    //   153: iconst_0
    //   154: istore_3
    //   155: goto +631 -> 786
    //   158: goto +156 -> 314
    //   161: aload 6
    //   163: astore_1
    //   164: iload_3
    //   165: tableswitch	default:+19->184, 0:+742->907
    //   184: aload 6
    //   186: astore_1
    //   187: goto +958 -> 1145
    //   190: iconst_1
    //   191: istore 4
    //   193: aload_1
    //   194: astore 6
    //   196: goto +27 -> 223
    //   199: iconst_2
    //   200: istore_3
    //   201: goto +950 -> 1151
    //   204: iconst_0
    //   205: istore_3
    //   206: goto +977 -> 1183
    //   209: iconst_1
    //   210: istore 4
    //   212: aload_1
    //   213: astore 6
    //   215: goto +8 -> 223
    //   218: iconst_0
    //   219: istore_3
    //   220: goto +893 -> 1113
    //   223: aload_0
    //   224: iload 4
    //   226: putfield 150	o/ᓾ:yH	Z
    //   229: aload_0
    //   230: aload 6
    //   232: iconst_4
    //   233: invokevirtual 338	android/content/res/Configuration:isLayoutSizeAtLeast	(I)Z
    //   236: putfield 144	o/ᓾ:yE	Z
    //   239: aload_0
    //   240: getfield 144	o/ᓾ:yE	Z
    //   243: ifne +896 -> 1139
    //   246: goto -47 -> 199
    //   249: iconst_1
    //   250: istore_3
    //   251: goto +862 -> 1113
    //   254: goto -187 -> 67
    //   257: iconst_0
    //   258: istore_3
    //   259: goto -98 -> 161
    //   262: iload_3
    //   263: lookupswitch	default:+25->288, 45:+-144->119, 67:+-117->146
    //   288: goto +20 -> 308
    //   291: bipush 10
    //   293: istore_3
    //   294: goto +241 -> 535
    //   297: iconst_1
    //   298: istore_3
    //   299: goto -138 -> 161
    //   302: iconst_0
    //   303: istore 5
    //   305: goto +452 -> 757
    //   308: bipush 45
    //   310: istore_3
    //   311: goto -49 -> 262
    //   314: aload 6
    //   316: getfield 344	o/aks:aRZ	Lo/aho;
    //   319: getfield 350	o/aho:aWi	Lcom/google/android/gms/measurement/AppMeasurement;
    //   322: ldc_w 352
    //   325: aload_1
    //   326: invokevirtual 358	com/google/android/gms/measurement/AppMeasurement:ᵎ	(Ljava/lang/String;Ljava/lang/String;)V
    //   329: aload_0
    //   330: getfield 360	o/ᓾ:yy	Lo/aks;
    //   333: getfield 344	o/aks:aRZ	Lo/aho;
    //   336: getfield 350	o/aho:aWi	Lcom/google/android/gms/measurement/AppMeasurement;
    //   339: ldc_w 362
    //   342: ldc_w 364
    //   345: invokevirtual 358	com/google/android/gms/measurement/AppMeasurement:ᵎ	(Ljava/lang/String;Ljava/lang/String;)V
    //   348: return
    //   349: aload_0
    //   350: invokevirtual 368	o/ᓾ:getResources	()Landroid/content/res/Resources;
    //   353: invokevirtual 374	android/content/res/Resources:getConfiguration	()Landroid/content/res/Configuration;
    //   356: astore 6
    //   358: aload 6
    //   360: getfield 377	android/content/res/Configuration:orientation	I
    //   363: iconst_2
    //   364: if_icmpeq +735 -> 1099
    //   367: goto +59 -> 426
    //   370: aload_0
    //   371: iload 4
    //   373: putfield 146	o/ᓾ:yF	Z
    //   376: aload_1
    //   377: astore 6
    //   379: fload_2
    //   380: f2d
    //   381: ldc2_w 378
    //   384: dcmpg
    //   385: iflt +103 -> 488
    //   388: goto +142 -> 530
    //   391: bipush 67
    //   393: istore_3
    //   394: goto -132 -> 262
    //   397: aload 6
    //   399: astore_1
    //   400: iload_3
    //   401: lookupswitch	default:+19->420, 32:+506->907
    //   420: aload 6
    //   422: astore_1
    //   423: goto +722 -> 1145
    //   426: bipush 32
    //   428: istore_3
    //   429: goto -32 -> 397
    //   432: goto +481 -> 913
    //   435: aload_0
    //   436: aload_1
    //   437: invokespecial 381	o/Ꮀ:onCreate	(Landroid/os/Bundle;)V
    //   440: goto +9 -> 449
    //   443: astore_1
    //   444: aload_1
    //   445: invokevirtual 285	java/lang/Throwable:getCause	()Ljava/lang/Throwable;
    //   448: athrow
    //   449: iconst_0
    //   450: iconst_0
    //   451: iconst_0
    //   452: invokestatic 287	o/ᓾ:$5	(ISI)Ljava/lang/String;
    //   455: invokestatic 293	o/ʢ:ˎ	(Ljava/lang/String;)Ljava/lang/Class;
    //   458: ldc_w 383
    //   461: aconst_null
    //   462: invokevirtual 309	java/lang/Class:getMethod	(Ljava/lang/String;[Ljava/lang/Class;)Ljava/lang/reflect/Method;
    //   465: aconst_null
    //   466: aconst_null
    //   467: invokevirtual 321	java/lang/reflect/Method:invoke	(Ljava/lang/Object;[Ljava/lang/Object;)Ljava/lang/Object;
    //   470: pop
    //   471: aload_0
    //   472: invokestatic 387	o/ﾚ:ՙ	(Landroid/content/Context;)V
    //   475: aload_0
    //   476: invokestatic 390	o/ʄ:ՙ	(Landroid/content/Context;)V
    //   479: invokestatic 392	o/ᓾ:ךּ	()Z
    //   482: ifeq -278 -> 204
    //   485: goto +296 -> 781
    //   488: iconst_0
    //   489: istore_3
    //   490: aload 6
    //   492: astore_1
    //   493: goto -490 -> 3
    //   496: getstatic 123	o/ᓾ:yQ	I
    //   499: bipush 85
    //   501: iadd
    //   502: istore_3
    //   503: iload_3
    //   504: sipush 128
    //   507: irem
    //   508: putstatic 121	o/ᓾ:yP	I
    //   511: iload_3
    //   512: iconst_2
    //   513: irem
    //   514: ifne -296 -> 218
    //   517: goto -268 -> 249
    //   520: iconst_0
    //   521: istore_3
    //   522: goto -488 -> 34
    //   525: iconst_0
    //   526: istore_3
    //   527: goto +280 -> 807
    //   530: iconst_1
    //   531: istore_3
    //   532: goto -529 -> 3
    //   535: iload_3
    //   536: lookupswitch	default:+28->564, 10:+31->567, 17:+132->668
    //   564: goto -273 -> 291
    //   567: iconst_0
    //   568: istore 4
    //   570: goto -200 -> 370
    //   573: goto +9 -> 582
    //   576: astore_1
    //   577: aload_1
    //   578: invokevirtual 285	java/lang/Throwable:getCause	()Ljava/lang/Throwable;
    //   581: athrow
    //   582: iconst_0
    //   583: iconst_0
    //   584: iconst_0
    //   585: invokestatic 287	o/ᓾ:$5	(ISI)Ljava/lang/String;
    //   588: invokestatic 293	o/ʢ:ˎ	(Ljava/lang/String;)Ljava/lang/Class;
    //   591: ldc_w 394
    //   594: iconst_1
    //   595: anewarray 297	java/lang/Class
    //   598: dup
    //   599: iconst_0
    //   600: ldc_w 396
    //   603: aastore
    //   604: invokevirtual 309	java/lang/Class:getMethod	(Ljava/lang/String;[Ljava/lang/Class;)Ljava/lang/reflect/Method;
    //   607: aconst_null
    //   608: iconst_1
    //   609: anewarray 311	java/lang/Object
    //   612: dup
    //   613: iconst_0
    //   614: aload_0
    //   615: aastore
    //   616: invokevirtual 321	java/lang/reflect/Method:invoke	(Ljava/lang/Object;[Ljava/lang/Object;)Ljava/lang/Object;
    //   619: pop
    //   620: goto +89 -> 709
    //   623: getstatic 123	o/ᓾ:yQ	I
    //   626: bipush 41
    //   628: iadd
    //   629: istore_3
    //   630: iload_3
    //   631: sipush 128
    //   634: irem
    //   635: putstatic 121	o/ᓾ:yP	I
    //   638: iload_3
    //   639: iconst_2
    //   640: irem
    //   641: ifne -483 -> 158
    //   644: goto -330 -> 314
    //   647: aload_0
    //   648: invokevirtual 368	o/ᓾ:getResources	()Landroid/content/res/Resources;
    //   651: invokevirtual 374	android/content/res/Resources:getConfiguration	()Landroid/content/res/Configuration;
    //   654: astore 6
    //   656: aload 6
    //   658: getfield 377	android/content/res/Configuration:orientation	I
    //   661: iconst_2
    //   662: if_icmpeq -365 -> 297
    //   665: goto -408 -> 257
    //   668: iconst_1
    //   669: istore 4
    //   671: goto -576 -> 95
    //   674: iconst_1
    //   675: istore_3
    //   676: goto +131 -> 807
    //   679: getstatic 121	o/ᓾ:yP	I
    //   682: bipush 61
    //   684: iadd
    //   685: istore_3
    //   686: iload_3
    //   687: sipush 128
    //   690: irem
    //   691: putstatic 123	o/ᓾ:yQ	I
    //   694: iload_3
    //   695: iconst_2
    //   696: irem
    //   697: ifeq -265 -> 432
    //   700: goto +213 -> 913
    //   703: bipush 17
    //   705: istore_3
    //   706: goto -171 -> 535
    //   709: getstatic 123	o/ᓾ:yQ	I
    //   712: bipush 85
    //   714: iadd
    //   715: istore_3
    //   716: iload_3
    //   717: sipush 128
    //   720: irem
    //   721: putstatic 121	o/ᓾ:yP	I
    //   724: iload_3
    //   725: iconst_2
    //   726: irem
    //   727: ifne -574 -> 153
    //   730: goto +375 -> 1105
    //   733: getstatic 123	o/ᓾ:yQ	I
    //   736: bipush 109
    //   738: iadd
    //   739: istore_3
    //   740: iload_3
    //   741: sipush 128
    //   744: irem
    //   745: putstatic 121	o/ᓾ:yP	I
    //   748: iload_3
    //   749: iconst_2
    //   750: irem
    //   751: ifne -608 -> 143
    //   754: goto -181 -> 573
    //   757: getstatic 123	o/ᓾ:yQ	I
    //   760: bipush 107
    //   762: iadd
    //   763: istore_3
    //   764: iload_3
    //   765: sipush 128
    //   768: irem
    //   769: putstatic 121	o/ᓾ:yP	I
    //   772: iload_3
    //   773: iconst_2
    //   774: irem
    //   775: ifne -255 -> 520
    //   778: goto +146 -> 924
    //   781: iconst_1
    //   782: istore_3
    //   783: goto +400 -> 1183
    //   786: iload_3
    //   787: tableswitch	default:+17->804, 1:+-438->349
    //   804: goto -157 -> 647
    //   807: iload_3
    //   808: tableswitch	default:+24->832, 0:+145->953, 1:+105->913
    //   832: goto -307 -> 525
    //   835: aload_0
    //   836: iload 4
    //   838: putfield 148	o/ᓾ:yG	Z
    //   841: aload_0
    //   842: invokevirtual 400	o/ᓾ:getWindowManager	()Landroid/view/WindowManager;
    //   845: invokeinterface 406 1 0
    //   850: aload_0
    //   851: getfield 155	o/ᓾ:yI	Landroid/graphics/Point;
    //   854: invokevirtual 412	android/view/Display:getSize	(Landroid/graphics/Point;)V
    //   857: aload_0
    //   858: getfield 155	o/ᓾ:yI	Landroid/graphics/Point;
    //   861: getfield 414	android/graphics/Point:y	I
    //   864: i2f
    //   865: aload_0
    //   866: getfield 155	o/ᓾ:yI	Landroid/graphics/Point;
    //   869: getfield 416	android/graphics/Point:x	I
    //   872: i2f
    //   873: fdiv
    //   874: aload_0
    //   875: getfield 155	o/ᓾ:yI	Landroid/graphics/Point;
    //   878: getfield 416	android/graphics/Point:x	I
    //   881: i2f
    //   882: aload_0
    //   883: getfield 155	o/ᓾ:yI	Landroid/graphics/Point;
    //   886: getfield 414	android/graphics/Point:y	I
    //   889: i2f
    //   890: fdiv
    //   891: invokestatic 422	java/lang/Math:max	(FF)F
    //   894: fstore_2
    //   895: fload_2
    //   896: f2d
    //   897: ldc2_w 423
    //   900: dcmpl
    //   901: ifgt -198 -> 703
    //   904: goto -613 -> 291
    //   907: iconst_0
    //   908: istore 4
    //   910: goto -75 -> 835
    //   913: aload_0
    //   914: iconst_0
    //   915: putfield 150	o/ᓾ:yH	Z
    //   918: goto +35 -> 953
    //   921: goto -551 -> 370
    //   924: iconst_1
    //   925: istore_3
    //   926: goto -892 -> 34
    //   929: aload_0
    //   930: iconst_0
    //   931: putfield 150	o/ᓾ:yH	Z
    //   934: aload_0
    //   935: aload_1
    //   936: iconst_4
    //   937: invokevirtual 338	android/content/res/Configuration:isLayoutSizeAtLeast	(I)Z
    //   940: putfield 144	o/ᓾ:yE	Z
    //   943: aload_0
    //   944: getfield 144	o/ᓾ:yE	Z
    //   947: ifne -273 -> 674
    //   950: goto -425 -> 525
    //   953: aload_0
    //   954: invokestatic 428	o/aho:ˢ	(Landroid/content/Context;)Lo/aho;
    //   957: getfield 431	o/aho:aWt	Lo/aks;
    //   960: astore_1
    //   961: aload_0
    //   962: aload_1
    //   963: putfield 360	o/ᓾ:yy	Lo/aks;
    //   966: aload_0
    //   967: getfield 360	o/ᓾ:yy	Lo/aks;
    //   970: astore_1
    //   971: invokestatic 437	java/util/Locale:getDefault	()Ljava/util/Locale;
    //   974: astore 6
    //   976: aload 6
    //   978: invokevirtual 440	java/util/Locale:getLanguage	()Ljava/lang/String;
    //   981: astore 6
    //   983: aload_1
    //   984: getfield 344	o/aks:aRZ	Lo/aho;
    //   987: getfield 350	o/aho:aWi	Lcom/google/android/gms/measurement/AppMeasurement;
    //   990: ldc_w 442
    //   993: aload 6
    //   995: invokevirtual 358	com/google/android/gms/measurement/AppMeasurement:ᵎ	(Ljava/lang/String;Ljava/lang/String;)V
    //   998: aload_0
    //   999: getfield 360	o/ᓾ:yy	Lo/aks;
    //   1002: astore_1
    //   1003: new 198	java/lang/StringBuilder
    //   1006: dup
    //   1007: invokespecial 443	java/lang/StringBuilder:<init>	()V
    //   1010: astore 6
    //   1012: aload_0
    //   1013: getfield 155	o/ᓾ:yI	Landroid/graphics/Point;
    //   1016: astore 7
    //   1018: aload 7
    //   1020: getfield 416	android/graphics/Point:x	I
    //   1023: istore_3
    //   1024: aload 6
    //   1026: iload_3
    //   1027: invokevirtual 446	java/lang/StringBuilder:append	(I)Ljava/lang/StringBuilder;
    //   1030: astore 6
    //   1032: aload 6
    //   1034: ldc_w 447
    //   1037: invokevirtual 207	java/lang/StringBuilder:append	(Ljava/lang/String;)Ljava/lang/StringBuilder;
    //   1040: astore 6
    //   1042: aload_0
    //   1043: getfield 155	o/ᓾ:yI	Landroid/graphics/Point;
    //   1046: astore 7
    //   1048: aload 7
    //   1050: getfield 414	android/graphics/Point:y	I
    //   1053: istore_3
    //   1054: aload 6
    //   1056: iload_3
    //   1057: invokevirtual 446	java/lang/StringBuilder:append	(I)Ljava/lang/StringBuilder;
    //   1060: invokevirtual 210	java/lang/StringBuilder:toString	()Ljava/lang/String;
    //   1063: astore 6
    //   1065: aload_1
    //   1066: getfield 344	o/aks:aRZ	Lo/aho;
    //   1069: getfield 350	o/aho:aWi	Lcom/google/android/gms/measurement/AppMeasurement;
    //   1072: ldc_w 449
    //   1075: aload 6
    //   1077: invokevirtual 358	com/google/android/gms/measurement/AppMeasurement:ᵎ	(Ljava/lang/String;Ljava/lang/String;)V
    //   1080: aload_0
    //   1081: getfield 360	o/ᓾ:yy	Lo/aks;
    //   1084: astore 6
    //   1086: invokestatic 392	o/ᓾ:ךּ	()Z
    //   1089: istore 4
    //   1091: iload 4
    //   1093: ifne -785 -> 308
    //   1096: goto -705 -> 391
    //   1099: bipush 10
    //   1101: istore_3
    //   1102: goto -705 -> 397
    //   1105: iconst_1
    //   1106: istore_3
    //   1107: goto -321 -> 786
    //   1110: astore_1
    //   1111: aload_1
    //   1112: athrow
    //   1113: iload_3
    //   1114: tableswitch	default:+22->1136, 0:+-924->190, 1:+-905->209
    //   1136: goto -887 -> 249
    //   1139: bipush 72
    //   1141: istore_3
    //   1142: goto +9 -> 1151
    //   1145: iconst_1
    //   1146: istore 4
    //   1148: goto -313 -> 835
    //   1151: iload_3
    //   1152: lookupswitch	default:+28->1180, 2:+-199->953, 72:+-473->679
    //   1180: goto -41 -> 1139
    //   1183: iload_3
    //   1184: tableswitch	default:+20->1204, 1:+-835->349
    //   1204: goto -471 -> 733
    //   1207: astore_1
    //   1208: aload_1
    //   1209: athrow
    // Local variable table:
    //   start	length	slot	name	signature
    //   0	1210	0	this	ᓾ
    //   0	1210	1	paramBundle	android.os.Bundle
    //   379	1	2	localObject1	Object
    //   894	2	2	f	float
    //   3	1181	3	i	int
    //   36	1111	4	bool1	boolean
    //   34	270	5	bool2	boolean
    //   29	1056	6	localObject2	Object
    //   1016	33	7	localPoint	Point
    // Exception table:
    //   from	to	target	type
    //   449	471	443	finally
    //   582	620	576	finally
    //   370	376	1110	java/lang/Exception
    //   961	966	1110	java/lang/Exception
    //   966	971	1110	java/lang/Exception
    //   971	976	1110	java/lang/Exception
    //   976	983	1110	java/lang/Exception
    //   983	998	1110	java/lang/Exception
    //   998	1003	1110	java/lang/Exception
    //   1003	1012	1110	java/lang/Exception
    //   1012	1018	1110	java/lang/Exception
    //   1018	1024	1110	java/lang/Exception
    //   1024	1032	1110	java/lang/Exception
    //   1032	1042	1110	java/lang/Exception
    //   1042	1048	1110	java/lang/Exception
    //   1048	1054	1110	java/lang/Exception
    //   1054	1091	1110	java/lang/Exception
    //   913	918	1207	java/lang/Exception
    //   953	961	1207	java/lang/Exception
  }
  
  /* Error */
  protected void onDestroy()
  {
    // Byte code:
    //   0: aload_0
    //   1: getfield 452	o/ᓾ:yA	Lo/ท;
    //   4: ifnull +10 -> 14
    //   7: aload_0
    //   8: getfield 452	o/ᓾ:yA	Lo/ท;
    //   11: invokevirtual 457	o/ท:destroy	()V
    //   14: goto +9 -> 23
    //   17: astore_1
    //   18: aload_1
    //   19: invokevirtual 285	java/lang/Throwable:getCause	()Ljava/lang/Throwable;
    //   22: athrow
    //   23: iconst_0
    //   24: iconst_0
    //   25: iconst_0
    //   26: invokestatic 287	o/ᓾ:$5	(ISI)Ljava/lang/String;
    //   29: invokestatic 293	o/ʢ:ˎ	(Ljava/lang/String;)Ljava/lang/Class;
    //   32: ldc_w 459
    //   35: aconst_null
    //   36: invokevirtual 309	java/lang/Class:getMethod	(Ljava/lang/String;[Ljava/lang/Class;)Ljava/lang/reflect/Method;
    //   39: aconst_null
    //   40: aconst_null
    //   41: invokevirtual 321	java/lang/reflect/Method:invoke	(Ljava/lang/Object;[Ljava/lang/Object;)Ljava/lang/Object;
    //   44: pop
    //   45: aload_0
    //   46: invokespecial 461	o/Ꮀ:onDestroy	()V
    //   49: return
    // Local variable table:
    //   start	length	slot	name	signature
    //   0	50	0	this	ᓾ
    //   17	2	1	localObject	Object
    // Exception table:
    //   from	to	target	type
    //   23	45	17	finally
  }
  
  protected void onPause()
  {
    if (yA != null) {
      yA.pause();
    }
    super.onPause();
  }
  
  protected void onResume()
  {
    super.onResume();
    if (yA != null) {
      yA.resume();
    }
  }
  
  /* Error */
  public void onStart()
  {
    // Byte code:
    //   0: goto +2963 -> 2963
    //   3: getstatic 133	o/ᓾ:w	J
    //   6: ldc2_w 227
    //   9: ladd
    //   10: getstatic 233	o/ﾚ:z	J
    //   13: ladd
    //   14: lconst_0
    //   15: lcmp
    //   16: ifne +8 -> 24
    //   19: iconst_1
    //   20: istore_1
    //   21: goto +5 -> 26
    //   24: iconst_0
    //   25: istore_1
    //   26: iload_1
    //   27: ifne +2490 -> 2517
    //   30: goto +1666 -> 1696
    //   33: iconst_0
    //   34: istore_1
    //   35: goto +1300 -> 1335
    //   38: iload_1
    //   39: lookupswitch	default:+17->56, 10:+2234->2273
    //   56: goto +1510 -> 1566
    //   59: bipush 36
    //   61: istore_1
    //   62: goto +1703 -> 1765
    //   65: iconst_0
    //   66: istore_1
    //   67: goto +2024 -> 2091
    //   70: getstatic 117	o/ᓾ:yR	[B
    //   73: bipush 86
    //   75: baload
    //   76: iconst_1
    //   77: isub
    //   78: i2s
    //   79: getstatic 117	o/ᓾ:yR	[B
    //   82: bipush 11
    //   84: baload
    //   85: i2b
    //   86: getstatic 119	o/ᓾ:yS	I
    //   89: iconst_1
    //   90: ishl
    //   91: i2b
    //   92: invokestatic 167	o/ᓾ:ˊ	(IBS)Ljava/lang/String;
    //   95: astore 24
    //   97: goto +2106 -> 2203
    //   100: getstatic 121	o/ᓾ:yP	I
    //   103: bipush 89
    //   105: iadd
    //   106: istore_1
    //   107: iload_1
    //   108: sipush 128
    //   111: irem
    //   112: putstatic 123	o/ᓾ:yQ	I
    //   115: iload_1
    //   116: iconst_2
    //   117: irem
    //   118: ifeq +1519 -> 1637
    //   121: goto +385 -> 506
    //   124: aload 25
    //   126: astore 23
    //   128: aload 24
    //   130: astore 26
    //   132: getstatic 133	o/ᓾ:w	J
    //   135: ldc2_w 475
    //   138: ladd
    //   139: lconst_0
    //   140: lcmp
    //   141: ifne +1338 -> 1479
    //   144: goto +162 -> 306
    //   147: goto +11 -> 158
    //   150: astore 23
    //   152: aload 23
    //   154: invokevirtual 285	java/lang/Throwable:getCause	()Ljava/lang/Throwable;
    //   157: athrow
    //   158: iconst_0
    //   159: iconst_0
    //   160: iconst_0
    //   161: invokestatic 287	o/ᓾ:$5	(ISI)Ljava/lang/String;
    //   164: invokestatic 293	o/ʢ:ˎ	(Ljava/lang/String;)Ljava/lang/Class;
    //   167: ldc_w 478
    //   170: iconst_1
    //   171: anewarray 297	java/lang/Class
    //   174: dup
    //   175: iconst_0
    //   176: ldc 51
    //   178: aastore
    //   179: invokevirtual 309	java/lang/Class:getMethod	(Ljava/lang/String;[Ljava/lang/Class;)Ljava/lang/reflect/Method;
    //   182: aconst_null
    //   183: iconst_1
    //   184: anewarray 311	java/lang/Object
    //   187: dup
    //   188: iconst_0
    //   189: ldc_w 480
    //   192: aastore
    //   193: invokevirtual 321	java/lang/reflect/Method:invoke	(Ljava/lang/Object;[Ljava/lang/Object;)Ljava/lang/Object;
    //   196: checkcast 323	java/lang/Boolean
    //   199: invokevirtual 326	java/lang/Boolean:booleanValue	()Z
    //   202: istore_3
    //   203: iload_3
    //   204: ifne +2399 -> 2603
    //   207: goto +2436 -> 2643
    //   210: iload_1
    //   211: tableswitch	default:+17->228, 0:+2193->2404
    //   228: goto +1733 -> 1961
    //   231: getstatic 121	o/ᓾ:yP	I
    //   234: bipush 91
    //   236: iadd
    //   237: istore_1
    //   238: iload_1
    //   239: sipush 128
    //   242: irem
    //   243: putstatic 123	o/ᓾ:yQ	I
    //   246: iload_1
    //   247: iconst_2
    //   248: irem
    //   249: ifeq +153 -> 402
    //   252: goto +741 -> 993
    //   255: getstatic 121	o/ᓾ:yP	I
    //   258: bipush 19
    //   260: iadd
    //   261: istore_2
    //   262: iload_2
    //   263: sipush 128
    //   266: irem
    //   267: putstatic 123	o/ᓾ:yQ	I
    //   270: iload_2
    //   271: iconst_2
    //   272: irem
    //   273: ifeq +610 -> 883
    //   276: goto +1233 -> 1509
    //   279: goto +1258 -> 1537
    //   282: getstatic 121	o/ᓾ:yP	I
    //   285: bipush 109
    //   287: iadd
    //   288: istore_1
    //   289: iload_1
    //   290: sipush 128
    //   293: irem
    //   294: putstatic 123	o/ᓾ:yQ	I
    //   297: iload_1
    //   298: iconst_2
    //   299: irem
    //   300: ifeq +1553 -> 1853
    //   303: goto +991 -> 1294
    //   306: iconst_0
    //   307: istore_1
    //   308: aload 24
    //   310: astore 26
    //   312: goto +1546 -> 1858
    //   315: getstatic 121	o/ᓾ:yP	I
    //   318: bipush 43
    //   320: iadd
    //   321: istore_1
    //   322: iload_1
    //   323: sipush 128
    //   326: irem
    //   327: putstatic 123	o/ᓾ:yQ	I
    //   330: iload_1
    //   331: iconst_2
    //   332: irem
    //   333: ifeq +1113 -> 1446
    //   336: goto +1867 -> 2203
    //   339: aload 23
    //   341: astore 25
    //   343: iload_1
    //   344: tableswitch	default:+20->364, 1:+-220->124
    //   364: goto +2004 -> 2368
    //   367: getstatic 123	o/ᓾ:yQ	I
    //   370: bipush 41
    //   372: iadd
    //   373: istore_2
    //   374: iload_2
    //   375: sipush 128
    //   378: irem
    //   379: putstatic 121	o/ᓾ:yP	I
    //   382: iload_2
    //   383: iconst_2
    //   384: irem
    //   385: ifne +879 -> 1264
    //   388: goto +1144 -> 1532
    //   391: iconst_2
    //   392: istore_1
    //   393: goto -138 -> 255
    //   396: bipush 93
    //   398: istore_1
    //   399: goto +2221 -> 2620
    //   402: goto +591 -> 993
    //   405: bipush 62
    //   407: istore_1
    //   408: aload 24
    //   410: astore 23
    //   412: goto +887 -> 1299
    //   415: aload 26
    //   417: astore 23
    //   419: iload_1
    //   420: lookupswitch	default:+20->440, 91:+3100->3520
    //   440: goto +945 -> 1385
    //   443: goto +11 -> 454
    //   446: astore 23
    //   448: aload 23
    //   450: invokevirtual 285	java/lang/Throwable:getCause	()Ljava/lang/Throwable;
    //   453: athrow
    //   454: iconst_0
    //   455: iconst_0
    //   456: iconst_0
    //   457: invokestatic 287	o/ᓾ:$5	(ISI)Ljava/lang/String;
    //   460: invokestatic 293	o/ʢ:ˎ	(Ljava/lang/String;)Ljava/lang/Class;
    //   463: ldc_w 478
    //   466: iconst_1
    //   467: anewarray 297	java/lang/Class
    //   470: dup
    //   471: iconst_0
    //   472: ldc 51
    //   474: aastore
    //   475: invokevirtual 309	java/lang/Class:getMethod	(Ljava/lang/String;[Ljava/lang/Class;)Ljava/lang/reflect/Method;
    //   478: aconst_null
    //   479: iconst_1
    //   480: anewarray 311	java/lang/Object
    //   483: dup
    //   484: iconst_0
    //   485: ldc_w 480
    //   488: aastore
    //   489: invokevirtual 321	java/lang/reflect/Method:invoke	(Ljava/lang/Object;[Ljava/lang/Object;)Ljava/lang/Object;
    //   492: checkcast 323	java/lang/Boolean
    //   495: invokevirtual 326	java/lang/Boolean:booleanValue	()Z
    //   498: istore_3
    //   499: iload_3
    //   500: ifne +415 -> 915
    //   503: goto -444 -> 59
    //   506: bipush 22
    //   508: istore_1
    //   509: goto +902 -> 1411
    //   512: bipush 52
    //   514: istore_1
    //   515: aload 26
    //   517: astore 25
    //   519: goto +2880 -> 3399
    //   522: iload_1
    //   523: tableswitch	default:+17->540, 1:+1004->1527
    //   540: goto -440 -> 100
    //   543: getstatic 117	o/ᓾ:yR	[B
    //   546: bipush 17
    //   548: baload
    //   549: i2s
    //   550: getstatic 117	o/ᓾ:yR	[B
    //   553: bipush 57
    //   555: baload
    //   556: i2b
    //   557: getstatic 117	o/ᓾ:yR	[B
    //   560: bipush 114
    //   562: baload
    //   563: i2b
    //   564: invokestatic 167	o/ᓾ:ˊ	(IBS)Ljava/lang/String;
    //   567: astore 26
    //   569: goto +2778 -> 3347
    //   572: ldc_w 482
    //   575: bipush 6
    //   577: invokestatic 487	o/if:ˊ	(Ljava/lang/String;I)Ljava/lang/String;
    //   580: astore 25
    //   582: aload 25
    //   584: ifnull +21 -> 605
    //   587: aload 26
    //   589: getfield 493	o/aw$ˎ:VX	Ljava/util/HashMap;
    //   592: aload 25
    //   594: aload 23
    //   596: invokeinterface 499 3 0
    //   601: pop
    //   602: goto +9 -> 611
    //   605: ldc_w 501
    //   608: invokestatic 506	o/bi:ǃ	(Ljava/lang/String;)V
    //   611: aload 26
    //   613: checkcast 508	o/aw$if
    //   616: astore 23
    //   618: sipush 128
    //   621: getstatic 117	o/ᓾ:yR	[B
    //   624: bipush 116
    //   626: baload
    //   627: i2b
    //   628: getstatic 117	o/ᓾ:yR	[B
    //   631: bipush 114
    //   633: baload
    //   634: i2b
    //   635: invokestatic 167	o/ᓾ:ˊ	(IBS)Ljava/lang/String;
    //   638: astore 25
    //   640: goto +11 -> 651
    //   643: astore 23
    //   645: aload 23
    //   647: invokevirtual 285	java/lang/Throwable:getCause	()Ljava/lang/Throwable;
    //   650: athrow
    //   651: iconst_0
    //   652: iconst_0
    //   653: iconst_0
    //   654: invokestatic 287	o/ᓾ:$5	(ISI)Ljava/lang/String;
    //   657: invokestatic 293	o/ʢ:ˎ	(Ljava/lang/String;)Ljava/lang/Class;
    //   660: ldc_w 510
    //   663: iconst_1
    //   664: anewarray 297	java/lang/Class
    //   667: dup
    //   668: iconst_0
    //   669: ldc 51
    //   671: aastore
    //   672: invokevirtual 309	java/lang/Class:getMethod	(Ljava/lang/String;[Ljava/lang/Class;)Ljava/lang/reflect/Method;
    //   675: aconst_null
    //   676: iconst_1
    //   677: anewarray 311	java/lang/Object
    //   680: dup
    //   681: iconst_0
    //   682: aload 25
    //   684: aastore
    //   685: invokevirtual 321	java/lang/reflect/Method:invoke	(Ljava/lang/Object;[Ljava/lang/Object;)Ljava/lang/Object;
    //   688: astore 25
    //   690: ldc_w 482
    //   693: iconst_3
    //   694: invokestatic 487	o/if:ˊ	(Ljava/lang/String;I)Ljava/lang/String;
    //   697: astore 26
    //   699: aload 26
    //   701: ifnull +21 -> 722
    //   704: aload 23
    //   706: getfield 493	o/aw$ˎ:VX	Ljava/util/HashMap;
    //   709: aload 26
    //   711: aload 25
    //   713: invokeinterface 499 3 0
    //   718: pop
    //   719: goto +9 -> 728
    //   722: ldc_w 501
    //   725: invokestatic 506	o/bi:ǃ	(Ljava/lang/String;)V
    //   728: aload 23
    //   730: checkcast 508	o/aw$if
    //   733: astore 23
    //   735: aload_0
    //   736: invokevirtual 513	o/ᓾ:getPackageName	()Ljava/lang/String;
    //   739: astore 25
    //   741: goto +11 -> 752
    //   744: astore 23
    //   746: aload 23
    //   748: invokevirtual 285	java/lang/Throwable:getCause	()Ljava/lang/Throwable;
    //   751: athrow
    //   752: iconst_0
    //   753: iconst_0
    //   754: iconst_0
    //   755: invokestatic 287	o/ᓾ:$5	(ISI)Ljava/lang/String;
    //   758: invokestatic 293	o/ʢ:ˎ	(Ljava/lang/String;)Ljava/lang/Class;
    //   761: ldc_w 515
    //   764: iconst_1
    //   765: anewarray 297	java/lang/Class
    //   768: dup
    //   769: iconst_0
    //   770: ldc 51
    //   772: aastore
    //   773: invokevirtual 309	java/lang/Class:getMethod	(Ljava/lang/String;[Ljava/lang/Class;)Ljava/lang/reflect/Method;
    //   776: aconst_null
    //   777: iconst_1
    //   778: anewarray 311	java/lang/Object
    //   781: dup
    //   782: iconst_0
    //   783: aload 25
    //   785: aastore
    //   786: invokevirtual 321	java/lang/reflect/Method:invoke	(Ljava/lang/Object;[Ljava/lang/Object;)Ljava/lang/Object;
    //   789: astore 25
    //   791: ldc_w 482
    //   794: iconst_4
    //   795: invokestatic 487	o/if:ˊ	(Ljava/lang/String;I)Ljava/lang/String;
    //   798: astore 26
    //   800: aload 26
    //   802: ifnull +21 -> 823
    //   805: aload 23
    //   807: getfield 493	o/aw$ˎ:VX	Ljava/util/HashMap;
    //   810: aload 26
    //   812: aload 25
    //   814: invokeinterface 499 3 0
    //   819: pop
    //   820: goto +9 -> 829
    //   823: ldc_w 501
    //   826: invokestatic 506	o/bi:ǃ	(Ljava/lang/String;)V
    //   829: aload 24
    //   831: aload 23
    //   833: checkcast 508	o/aw$if
    //   836: invokevirtual 519	o/aw$if:γ	()Ljava/util/Map;
    //   839: invokevirtual 524	o/az:ˊ	(Ljava/util/Map;)V
    //   842: return
    //   843: iconst_0
    //   844: istore_1
    //   845: goto +1899 -> 2744
    //   848: iload_1
    //   849: lookupswitch	default:+27->876, 26:+603->1452, 31:+1760->2609
    //   876: aload 23
    //   878: astore 24
    //   880: goto +1854 -> 2734
    //   883: goto +626 -> 1509
    //   886: iconst_1
    //   887: istore_1
    //   888: goto +899 -> 1787
    //   891: invokestatic 530	o/הּ:ﾍ	()Lo/az;
    //   894: astore 23
    //   896: aload 23
    //   898: astore 24
    //   900: aload 25
    //   902: astore 26
    //   904: aload_0
    //   905: getfield 137	o/ᓾ:mode	I
    //   908: iconst_2
    //   909: if_icmpeq -397 -> 512
    //   912: goto +768 -> 1680
    //   915: iconst_2
    //   916: istore_1
    //   917: goto +848 -> 1765
    //   920: getstatic 123	o/ᓾ:yQ	I
    //   923: bipush 79
    //   925: iadd
    //   926: istore_1
    //   927: iload_1
    //   928: sipush 128
    //   931: irem
    //   932: putstatic 121	o/ᓾ:yP	I
    //   935: aload 25
    //   937: astore 23
    //   939: iload_1
    //   940: iconst_2
    //   941: irem
    //   942: ifne +675 -> 1617
    //   945: goto +666 -> 1611
    //   948: iconst_0
    //   949: istore_1
    //   950: goto +278 -> 1228
    //   953: aload 23
    //   955: astore 25
    //   957: goto -833 -> 124
    //   960: getstatic 123	o/ᓾ:yQ	I
    //   963: bipush 91
    //   965: iadd
    //   966: istore_1
    //   967: iload_1
    //   968: sipush 128
    //   971: irem
    //   972: putstatic 121	o/ᓾ:yP	I
    //   975: aload 23
    //   977: astore 24
    //   979: iload_1
    //   980: iconst_2
    //   981: irem
    //   982: ifne -577 -> 405
    //   985: goto +1377 -> 2362
    //   988: iconst_1
    //   989: istore_1
    //   990: goto -651 -> 339
    //   993: aload_0
    //   994: iload_3
    //   995: putfield 532	o/ᓾ:yJ	Z
    //   998: goto +11 -> 1009
    //   1001: astore 23
    //   1003: aload 23
    //   1005: invokevirtual 285	java/lang/Throwable:getCause	()Ljava/lang/Throwable;
    //   1008: athrow
    //   1009: iconst_0
    //   1010: iconst_0
    //   1011: iconst_0
    //   1012: invokestatic 287	o/ᓾ:$5	(ISI)Ljava/lang/String;
    //   1015: invokestatic 293	o/ʢ:ˎ	(Ljava/lang/String;)Ljava/lang/Class;
    //   1018: ldc_w 478
    //   1021: iconst_1
    //   1022: anewarray 297	java/lang/Class
    //   1025: dup
    //   1026: iconst_0
    //   1027: ldc 51
    //   1029: aastore
    //   1030: invokevirtual 309	java/lang/Class:getMethod	(Ljava/lang/String;[Ljava/lang/Class;)Ljava/lang/reflect/Method;
    //   1033: aconst_null
    //   1034: iconst_1
    //   1035: anewarray 311	java/lang/Object
    //   1038: dup
    //   1039: iconst_0
    //   1040: ldc_w 534
    //   1043: aastore
    //   1044: invokevirtual 321	java/lang/reflect/Method:invoke	(Ljava/lang/Object;[Ljava/lang/Object;)Ljava/lang/Object;
    //   1047: checkcast 323	java/lang/Boolean
    //   1050: invokevirtual 326	java/lang/Boolean:booleanValue	()Z
    //   1053: istore_3
    //   1054: aload_0
    //   1055: iload_3
    //   1056: putfield 536	o/ᓾ:yK	Z
    //   1059: goto +11 -> 1070
    //   1062: astore 23
    //   1064: aload 23
    //   1066: invokevirtual 285	java/lang/Throwable:getCause	()Ljava/lang/Throwable;
    //   1069: athrow
    //   1070: iconst_0
    //   1071: iconst_0
    //   1072: iconst_0
    //   1073: invokestatic 287	o/ᓾ:$5	(ISI)Ljava/lang/String;
    //   1076: invokestatic 293	o/ʢ:ˎ	(Ljava/lang/String;)Ljava/lang/Class;
    //   1079: ldc_w 478
    //   1082: iconst_1
    //   1083: anewarray 297	java/lang/Class
    //   1086: dup
    //   1087: iconst_0
    //   1088: ldc 51
    //   1090: aastore
    //   1091: invokevirtual 309	java/lang/Class:getMethod	(Ljava/lang/String;[Ljava/lang/Class;)Ljava/lang/reflect/Method;
    //   1094: aconst_null
    //   1095: iconst_1
    //   1096: anewarray 311	java/lang/Object
    //   1099: dup
    //   1100: iconst_0
    //   1101: ldc_w 538
    //   1104: aastore
    //   1105: invokevirtual 321	java/lang/reflect/Method:invoke	(Ljava/lang/Object;[Ljava/lang/Object;)Ljava/lang/Object;
    //   1108: checkcast 323	java/lang/Boolean
    //   1111: invokevirtual 326	java/lang/Boolean:booleanValue	()Z
    //   1114: istore_3
    //   1115: aload_0
    //   1116: iload_3
    //   1117: putfield 540	o/ᓾ:yL	Z
    //   1120: getstatic 133	o/ᓾ:w	J
    //   1123: lstore 5
    //   1125: getstatic 129	o/ᓾ:y	J
    //   1128: lstore 7
    //   1130: getstatic 233	o/ﾚ:z	J
    //   1133: lstore 9
    //   1135: getstatic 131	o/ᓾ:yD	J
    //   1138: lstore 11
    //   1140: getstatic 127	o/ᓾ:x	J
    //   1143: lstore 13
    //   1145: getstatic 129	o/ᓾ:y	J
    //   1148: lstore 15
    //   1150: getstatic 129	o/ᓾ:y	J
    //   1153: lstore 17
    //   1155: getstatic 233	o/ﾚ:z	J
    //   1158: lstore 19
    //   1160: getstatic 233	o/ﾚ:z	J
    //   1163: lstore 21
    //   1165: lload 5
    //   1167: ldc2_w 269
    //   1170: lload 7
    //   1172: lload 9
    //   1174: ldc2_w 263
    //   1177: lmul
    //   1178: ldc2_w 271
    //   1181: ladd
    //   1182: lmul
    //   1183: lsub
    //   1184: lload 11
    //   1186: lload 13
    //   1188: ladd
    //   1189: lload 15
    //   1191: lload 17
    //   1193: lmul
    //   1194: ladd
    //   1195: lload 19
    //   1197: ldc2_w 273
    //   1200: ladd
    //   1201: lmul
    //   1202: lsub
    //   1203: lload 21
    //   1205: ldc2_w 275
    //   1208: lmul
    //   1209: ladd
    //   1210: lcmp
    //   1211: ifeq +277 -> 1488
    //   1214: goto -328 -> 886
    //   1217: astore 23
    //   1219: aload 23
    //   1221: athrow
    //   1222: bipush 31
    //   1224: istore_1
    //   1225: goto -377 -> 848
    //   1228: iload_1
    //   1229: tableswitch	default:+19->1248, 1:+922->2151
    //   1248: goto +740 -> 1988
    //   1251: ldc_w 542
    //   1254: astore 30
    //   1256: goto -336 -> 920
    //   1259: iconst_1
    //   1260: istore_1
    //   1261: goto +830 -> 2091
    //   1264: iconst_0
    //   1265: istore_2
    //   1266: goto +324 -> 1590
    //   1269: iconst_1
    //   1270: istore_1
    //   1271: goto -904 -> 367
    //   1274: invokestatic 530	o/הּ:ﾍ	()Lo/az;
    //   1277: astore 25
    //   1279: aload 25
    //   1281: astore 30
    //   1283: aload_0
    //   1284: getfield 137	o/ᓾ:mode	I
    //   1287: iconst_2
    //   1288: if_icmpeq -1223 -> 65
    //   1291: goto -32 -> 1259
    //   1294: iconst_0
    //   1295: istore_1
    //   1296: goto +1187 -> 2483
    //   1299: iload_1
    //   1300: lookupswitch	default:+28->1328, 13:+653->1953, 62:+1167->2467
    //   1328: aload 23
    //   1330: astore 24
    //   1332: goto -927 -> 405
    //   1335: iload_1
    //   1336: lookupswitch	default:+28->1364, 0:+921->2257, 43:+-376->960
    //   1364: goto -1331 -> 33
    //   1367: aload_0
    //   1368: iconst_1
    //   1369: putfield 137	o/ᓾ:mode	I
    //   1372: aload_0
    //   1373: invokespecial 544	o/ᓾ:Ⅼ	()V
    //   1376: invokestatic 262	o/ᓾ:ⅴ	()Z
    //   1379: ifne +352 -> 1731
    //   1382: goto +699 -> 2081
    //   1385: ldc_w 546
    //   1388: astore 24
    //   1390: ldc2_w 547
    //   1393: getstatic 129	o/ᓾ:y	J
    //   1396: ldc2_w 263
    //   1399: ladd
    //   1400: getstatic 129	o/ᓾ:y	J
    //   1403: lmul
    //   1404: lcmp
    //   1405: ifne +443 -> 1848
    //   1408: goto +32 -> 1440
    //   1411: iload_1
    //   1412: lookupswitch	default:+20->1432, 22:+-969->443
    //   1432: goto -1285 -> 147
    //   1435: iconst_3
    //   1436: istore_1
    //   1437: goto +72 -> 1509
    //   1440: bipush 47
    //   1442: istore_1
    //   1443: goto +259 -> 1702
    //   1446: goto +757 -> 2203
    //   1449: goto +955 -> 2404
    //   1452: sipush 129
    //   1455: getstatic 117	o/ᓾ:yR	[B
    //   1458: bipush 75
    //   1460: baload
    //   1461: iconst_1
    //   1462: isub
    //   1463: i2b
    //   1464: getstatic 117	o/ᓾ:yR	[B
    //   1467: bipush 68
    //   1469: baload
    //   1470: i2b
    //   1471: invokestatic 167	o/ᓾ:ˊ	(IBS)Ljava/lang/String;
    //   1474: astore 24
    //   1476: goto +727 -> 2203
    //   1479: iconst_1
    //   1480: istore_1
    //   1481: aload 23
    //   1483: astore 25
    //   1485: goto +373 -> 1858
    //   1488: iconst_0
    //   1489: istore_1
    //   1490: goto +297 -> 1787
    //   1493: ldc_w 546
    //   1496: astore 24
    //   1498: getstatic 131	o/ᓾ:yD	J
    //   1501: lconst_0
    //   1502: lcmp
    //   1503: iflt +583 -> 2086
    //   1506: goto -518 -> 988
    //   1509: aload_0
    //   1510: iload_1
    //   1511: putfield 137	o/ᓾ:mode	I
    //   1514: aload_0
    //   1515: invokespecial 544	o/ᓾ:Ⅼ	()V
    //   1518: invokestatic 262	o/ᓾ:ⅴ	()Z
    //   1521: ifne +860 -> 2381
    //   1524: goto +1864 -> 3388
    //   1527: iconst_1
    //   1528: istore_3
    //   1529: goto -1298 -> 231
    //   1532: iconst_1
    //   1533: istore_2
    //   1534: goto +56 -> 1590
    //   1537: getstatic 117	o/ᓾ:yR	[B
    //   1540: bipush 38
    //   1542: baload
    //   1543: i2s
    //   1544: getstatic 117	o/ᓾ:yR	[B
    //   1547: bipush 57
    //   1549: baload
    //   1550: i2b
    //   1551: getstatic 117	o/ᓾ:yR	[B
    //   1554: bipush 68
    //   1556: baload
    //   1557: i2b
    //   1558: invokestatic 167	o/ᓾ:ˊ	(IBS)Ljava/lang/String;
    //   1561: astore 23
    //   1563: goto +1957 -> 3520
    //   1566: getstatic 121	o/ᓾ:yP	I
    //   1569: bipush 97
    //   1571: iadd
    //   1572: istore_1
    //   1573: iload_1
    //   1574: sipush 128
    //   1577: irem
    //   1578: putstatic 123	o/ᓾ:yQ	I
    //   1581: iload_1
    //   1582: iconst_2
    //   1583: irem
    //   1584: ifeq -1305 -> 279
    //   1587: goto -50 -> 1537
    //   1590: iload_2
    //   1591: tableswitch	default:+17->1608, 1:+-82->1509
    //   1608: goto -241 -> 1367
    //   1611: bipush 43
    //   1613: istore_1
    //   1614: goto +1668 -> 3282
    //   1617: bipush 17
    //   1619: istore_1
    //   1620: aload 23
    //   1622: astore 25
    //   1624: goto +1658 -> 3282
    //   1627: aload_0
    //   1628: invokestatic 550	o/ᓾ:ʼ	(Landroid/app/Activity;)Z
    //   1631: ifne -1235 -> 396
    //   1634: goto +941 -> 2575
    //   1637: bipush 58
    //   1639: istore_1
    //   1640: goto -229 -> 1411
    //   1643: iconst_1
    //   1644: istore_1
    //   1645: goto -1123 -> 522
    //   1648: iload_1
    //   1649: tableswitch	default:+23->1672, 0:+654->2303, 1:+-1579->70
    //   1672: goto +1699 -> 3371
    //   1675: iconst_1
    //   1676: istore_1
    //   1677: goto -449 -> 1228
    //   1680: bipush 11
    //   1682: istore_1
    //   1683: goto +1716 -> 3399
    //   1686: aload_0
    //   1687: invokestatic 550	o/ᓾ:ʼ	(Landroid/app/Activity;)Z
    //   1690: ifne +1692 -> 3382
    //   1693: goto +634 -> 2327
    //   1696: bipush 18
    //   1698: istore_1
    //   1699: goto +882 -> 2581
    //   1702: aload 26
    //   1704: astore 25
    //   1706: iload_1
    //   1707: lookupswitch	default:+17->1724, 47:+-1583->124
    //   1724: aload 26
    //   1726: astore 23
    //   1728: goto -235 -> 1493
    //   1731: iconst_0
    //   1732: istore_1
    //   1733: goto +818 -> 2551
    //   1736: getstatic 117	o/ᓾ:yR	[B
    //   1739: bipush 33
    //   1741: baload
    //   1742: i2s
    //   1743: getstatic 117	o/ᓾ:yR	[B
    //   1746: bipush 75
    //   1748: baload
    //   1749: i2b
    //   1750: getstatic 117	o/ᓾ:yR	[B
    //   1753: bipush 87
    //   1755: baload
    //   1756: i2b
    //   1757: invokestatic 167	o/ᓾ:ˊ	(IBS)Ljava/lang/String;
    //   1760: astore 24
    //   1762: goto -1447 -> 315
    //   1765: iload_1
    //   1766: lookupswitch	default:+18->1784, 36:+129->1895
    //   1784: goto -257 -> 1527
    //   1787: iload_1
    //   1788: tableswitch	default:+20->1808, 1:+-161->1627
    //   1808: goto -1417 -> 391
    //   1811: iconst_5
    //   1812: istore_1
    //   1813: goto +710 -> 2523
    //   1816: getstatic 121	o/ᓾ:yP	I
    //   1819: bipush 55
    //   1821: iadd
    //   1822: istore_1
    //   1823: iload_1
    //   1824: sipush 128
    //   1827: irem
    //   1828: putstatic 123	o/ᓾ:yQ	I
    //   1831: iload_1
    //   1832: iconst_2
    //   1833: irem
    //   1834: ifeq +559 -> 2393
    //   1837: aload 23
    //   1839: astore 24
    //   1841: aload 25
    //   1843: astore 23
    //   1845: goto -1273 -> 572
    //   1848: iconst_4
    //   1849: istore_1
    //   1850: goto -148 -> 1702
    //   1853: iconst_1
    //   1854: istore_1
    //   1855: goto +628 -> 2483
    //   1858: aload 25
    //   1860: astore 23
    //   1862: aload 26
    //   1864: astore 24
    //   1866: iload_1
    //   1867: tableswitch	default:+21->1888, 0:+-593->1274, 1:+-616->1251
    //   1888: aload 25
    //   1890: astore 23
    //   1892: goto -413 -> 1479
    //   1895: iconst_0
    //   1896: istore_3
    //   1897: goto -904 -> 993
    //   1900: getstatic 117	o/ᓾ:yR	[B
    //   1903: bipush 17
    //   1905: baload
    //   1906: i2s
    //   1907: getstatic 117	o/ᓾ:yR	[B
    //   1910: bipush 57
    //   1912: baload
    //   1913: i2b
    //   1914: getstatic 117	o/ᓾ:yR	[B
    //   1917: bipush 114
    //   1919: baload
    //   1920: i2b
    //   1921: invokestatic 167	o/ᓾ:ˊ	(IBS)Ljava/lang/String;
    //   1924: astore 23
    //   1926: goto +1594 -> 3520
    //   1929: getstatic 123	o/ᓾ:yQ	I
    //   1932: bipush 119
    //   1934: iadd
    //   1935: istore_1
    //   1936: iload_1
    //   1937: sipush 128
    //   1940: irem
    //   1941: putstatic 121	o/ᓾ:yP	I
    //   1944: iload_1
    //   1945: iconst_2
    //   1946: irem
    //   1947: ifne -498 -> 1449
    //   1950: goto +454 -> 2404
    //   1953: ldc_w 552
    //   1956: astore 25
    //   1958: goto -142 -> 1816
    //   1961: getstatic 121	o/ᓾ:yP	I
    //   1964: bipush 77
    //   1966: iadd
    //   1967: istore_1
    //   1968: iload_1
    //   1969: sipush 128
    //   1972: irem
    //   1973: putstatic 123	o/ᓾ:yQ	I
    //   1976: iload_1
    //   1977: iconst_2
    //   1978: irem
    //   1979: ifeq -1031 -> 948
    //   1982: goto -307 -> 1675
    //   1985: goto -249 -> 1736
    //   1988: goto +11 -> 1999
    //   1991: astore 23
    //   1993: aload 23
    //   1995: invokevirtual 285	java/lang/Throwable:getCause	()Ljava/lang/Throwable;
    //   1998: athrow
    //   1999: iconst_0
    //   2000: iconst_0
    //   2001: iconst_0
    //   2002: invokestatic 287	o/ᓾ:$5	(ISI)Ljava/lang/String;
    //   2005: invokestatic 293	o/ʢ:ˎ	(Ljava/lang/String;)Ljava/lang/Class;
    //   2008: ldc_w 554
    //   2011: iconst_1
    //   2012: anewarray 297	java/lang/Class
    //   2015: dup
    //   2016: iconst_0
    //   2017: ldc_w 396
    //   2020: aastore
    //   2021: invokevirtual 309	java/lang/Class:getMethod	(Ljava/lang/String;[Ljava/lang/Class;)Ljava/lang/reflect/Method;
    //   2024: aconst_null
    //   2025: iconst_1
    //   2026: anewarray 311	java/lang/Object
    //   2029: dup
    //   2030: iconst_0
    //   2031: aload_0
    //   2032: aastore
    //   2033: invokevirtual 321	java/lang/reflect/Method:invoke	(Ljava/lang/Object;[Ljava/lang/Object;)Ljava/lang/Object;
    //   2036: pop
    //   2037: goto +367 -> 2404
    //   2040: bipush 37
    //   2042: getstatic 117	o/ᓾ:yR	[B
    //   2045: bipush 22
    //   2047: baload
    //   2048: i2b
    //   2049: getstatic 117	o/ᓾ:yR	[B
    //   2052: bipush 75
    //   2054: baload
    //   2055: iconst_1
    //   2056: isub
    //   2057: i2b
    //   2058: invokestatic 167	o/ᓾ:ˊ	(IBS)Ljava/lang/String;
    //   2061: astore 24
    //   2063: aload 26
    //   2065: astore 23
    //   2067: goto +700 -> 2767
    //   2070: bipush 56
    //   2072: istore_1
    //   2073: goto +450 -> 2523
    //   2076: astore 23
    //   2078: aload 23
    //   2080: athrow
    //   2081: iconst_1
    //   2082: istore_1
    //   2083: goto +468 -> 2551
    //   2086: iconst_0
    //   2087: istore_1
    //   2088: goto -1749 -> 339
    //   2091: aload 25
    //   2093: astore 33
    //   2095: aload 23
    //   2097: astore 31
    //   2099: aload 24
    //   2101: astore 28
    //   2103: aload 30
    //   2105: astore 26
    //   2107: aload 25
    //   2109: astore 34
    //   2111: aload 23
    //   2113: astore 32
    //   2115: aload 24
    //   2117: astore 29
    //   2119: aload 30
    //   2121: astore 27
    //   2123: iload_1
    //   2124: tableswitch	default:+24->2148, 0:+1348->3472, 1:+-84->2040
    //   2148: goto -889 -> 1259
    //   2151: goto +11 -> 2162
    //   2154: astore 23
    //   2156: aload 23
    //   2158: invokevirtual 285	java/lang/Throwable:getCause	()Ljava/lang/Throwable;
    //   2161: athrow
    //   2162: iconst_0
    //   2163: iconst_0
    //   2164: iconst_0
    //   2165: invokestatic 287	o/ᓾ:$5	(ISI)Ljava/lang/String;
    //   2168: invokestatic 293	o/ʢ:ˎ	(Ljava/lang/String;)Ljava/lang/Class;
    //   2171: ldc_w 554
    //   2174: iconst_1
    //   2175: anewarray 297	java/lang/Class
    //   2178: dup
    //   2179: iconst_0
    //   2180: ldc_w 396
    //   2183: aastore
    //   2184: invokevirtual 309	java/lang/Class:getMethod	(Ljava/lang/String;[Ljava/lang/Class;)Ljava/lang/reflect/Method;
    //   2187: aconst_null
    //   2188: iconst_1
    //   2189: anewarray 311	java/lang/Object
    //   2192: dup
    //   2193: iconst_0
    //   2194: aload_0
    //   2195: aastore
    //   2196: invokevirtual 321	java/lang/reflect/Method:invoke	(Ljava/lang/Object;[Ljava/lang/Object;)Ljava/lang/Object;
    //   2199: pop
    //   2200: goto -271 -> 1929
    //   2203: ldc_w 482
    //   2206: iconst_1
    //   2207: invokestatic 487	o/if:ˊ	(Ljava/lang/String;I)Ljava/lang/String;
    //   2210: astore 26
    //   2212: aload 26
    //   2214: ifnull +21 -> 2235
    //   2217: aload 25
    //   2219: getfield 493	o/aw$ˎ:VX	Ljava/util/HashMap;
    //   2222: aload 26
    //   2224: aload 24
    //   2226: invokeinterface 499 3 0
    //   2231: pop
    //   2232: goto +9 -> 2241
    //   2235: ldc_w 501
    //   2238: invokestatic 506	o/bi:ǃ	(Ljava/lang/String;)V
    //   2241: aload 25
    //   2243: checkcast 508	o/aw$if
    //   2246: astore 26
    //   2248: getstatic 557	o/ﾚ:Bj	I
    //   2251: ifeq +136 -> 2387
    //   2254: goto -2221 -> 33
    //   2257: ldc_w 559
    //   2260: astore 25
    //   2262: aload 23
    //   2264: astore 24
    //   2266: aload 25
    //   2268: astore 23
    //   2270: goto -1698 -> 572
    //   2273: getstatic 117	o/ᓾ:yR	[B
    //   2276: iconst_2
    //   2277: baload
    //   2278: iconst_1
    //   2279: iadd
    //   2280: i2s
    //   2281: getstatic 117	o/ᓾ:yR	[B
    //   2284: bipush 75
    //   2286: baload
    //   2287: i2b
    //   2288: getstatic 117	o/ᓾ:yR	[B
    //   2291: bipush 68
    //   2293: baload
    //   2294: i2b
    //   2295: invokestatic 167	o/ᓾ:ˊ	(IBS)Ljava/lang/String;
    //   2298: astore 23
    //   2300: goto +1220 -> 3520
    //   2303: getstatic 121	o/ᓾ:yP	I
    //   2306: bipush 55
    //   2308: iadd
    //   2309: istore_1
    //   2310: iload_1
    //   2311: sipush 128
    //   2314: irem
    //   2315: putstatic 123	o/ᓾ:yQ	I
    //   2318: iload_1
    //   2319: iconst_2
    //   2320: irem
    //   2321: ifeq -336 -> 1985
    //   2324: goto -588 -> 1736
    //   2327: bipush 10
    //   2329: istore_1
    //   2330: goto -2292 -> 38
    //   2333: getstatic 117	o/ᓾ:yR	[B
    //   2336: bipush 22
    //   2338: baload
    //   2339: i2s
    //   2340: getstatic 117	o/ᓾ:yR	[B
    //   2343: bipush 49
    //   2345: baload
    //   2346: i2b
    //   2347: getstatic 117	o/ᓾ:yR	[B
    //   2350: bipush 87
    //   2352: baload
    //   2353: i2b
    //   2354: invokestatic 167	o/ᓾ:ˊ	(IBS)Ljava/lang/String;
    //   2357: astore 23
    //   2359: goto +1161 -> 3520
    //   2362: bipush 13
    //   2364: istore_1
    //   2365: goto -1066 -> 1299
    //   2368: ldc_w 561
    //   2371: astore 24
    //   2373: goto +276 -> 2649
    //   2376: iconst_1
    //   2377: istore_1
    //   2378: goto -2168 -> 210
    //   2381: bipush 45
    //   2383: istore_1
    //   2384: goto +315 -> 2699
    //   2387: bipush 43
    //   2389: istore_1
    //   2390: goto -1055 -> 1335
    //   2393: aload 23
    //   2395: astore 24
    //   2397: aload 25
    //   2399: astore 23
    //   2401: goto -1829 -> 572
    //   2404: goto +11 -> 2415
    //   2407: astore 23
    //   2409: aload 23
    //   2411: invokevirtual 285	java/lang/Throwable:getCause	()Ljava/lang/Throwable;
    //   2414: athrow
    //   2415: iconst_0
    //   2416: iconst_0
    //   2417: iconst_0
    //   2418: invokestatic 287	o/ᓾ:$5	(ISI)Ljava/lang/String;
    //   2421: invokestatic 293	o/ʢ:ˎ	(Ljava/lang/String;)Ljava/lang/Class;
    //   2424: ldc_w 478
    //   2427: iconst_1
    //   2428: anewarray 297	java/lang/Class
    //   2431: dup
    //   2432: iconst_0
    //   2433: ldc 51
    //   2435: aastore
    //   2436: invokevirtual 309	java/lang/Class:getMethod	(Ljava/lang/String;[Ljava/lang/Class;)Ljava/lang/reflect/Method;
    //   2439: aconst_null
    //   2440: iconst_1
    //   2441: anewarray 311	java/lang/Object
    //   2444: dup
    //   2445: iconst_0
    //   2446: ldc_w 563
    //   2449: aastore
    //   2450: invokevirtual 321	java/lang/reflect/Method:invoke	(Ljava/lang/Object;[Ljava/lang/Object;)Ljava/lang/Object;
    //   2453: checkcast 323	java/lang/Boolean
    //   2456: invokevirtual 326	java/lang/Boolean:booleanValue	()Z
    //   2459: istore_3
    //   2460: iload_3
    //   2461: ifeq +1006 -> 3467
    //   2464: goto -821 -> 1643
    //   2467: ldc_w 552
    //   2470: astore 25
    //   2472: aload 23
    //   2474: astore 24
    //   2476: aload 25
    //   2478: astore 23
    //   2480: goto -1908 -> 572
    //   2483: iload_1
    //   2484: tableswitch	default:+20->2504, 0:+28->2512
    //   2504: goto -1069 -> 1435
    //   2507: iconst_0
    //   2508: istore_1
    //   2509: goto -2299 -> 210
    //   2512: iconst_3
    //   2513: istore_1
    //   2514: goto -1005 -> 1509
    //   2517: bipush 23
    //   2519: istore_1
    //   2520: goto +61 -> 2581
    //   2523: aload 23
    //   2525: astore 25
    //   2527: iload_1
    //   2528: lookupswitch	default:+20->2548, 5:+-2404->124
    //   2548: goto -1055 -> 1493
    //   2551: iload_1
    //   2552: tableswitch	default:+20->2572, 1:+-2549->3
    //   2572: goto -239 -> 2333
    //   2575: bipush 15
    //   2577: istore_1
    //   2578: goto +42 -> 2620
    //   2581: iload_1
    //   2582: lookupswitch	default:+18->2600, 18:+-896->1686
    //   2600: goto +723 -> 3323
    //   2603: bipush 52
    //   2605: istore_1
    //   2606: goto +70 -> 2676
    //   2609: aload_0
    //   2610: getfield 137	o/ᓾ:mode	I
    //   2613: iconst_2
    //   2614: if_icmpeq +780 -> 3394
    //   2617: goto +754 -> 3371
    //   2620: iload_1
    //   2621: lookupswitch	default:+19->2640, 15:+-1352->1269
    //   2640: goto -2358 -> 282
    //   2643: bipush 19
    //   2645: istore_1
    //   2646: goto +30 -> 2676
    //   2649: getstatic 121	o/ᓾ:yP	I
    //   2652: iconst_3
    //   2653: iadd
    //   2654: istore_1
    //   2655: iload_1
    //   2656: sipush 128
    //   2659: irem
    //   2660: putstatic 123	o/ᓾ:yQ	I
    //   2663: iload_1
    //   2664: iconst_2
    //   2665: irem
    //   2666: ifeq -1713 -> 953
    //   2669: aload 23
    //   2671: astore 25
    //   2673: goto -2549 -> 124
    //   2676: iload_1
    //   2677: lookupswitch	default:+19->2696, 19:+-782->1895
    //   2696: goto -1169 -> 1527
    //   2699: iload_1
    //   2700: lookupswitch	default:+20->2720, 56:+-2697->3
    //   2720: goto -387 -> 2333
    //   2723: iconst_1
    //   2724: istore_1
    //   2725: goto +19 -> 2744
    //   2728: bipush 91
    //   2730: istore_1
    //   2731: goto -2316 -> 415
    //   2734: bipush 26
    //   2736: istore_1
    //   2737: aload 24
    //   2739: astore 23
    //   2741: goto -1893 -> 848
    //   2744: iload_1
    //   2745: tableswitch	default:+19->2764, 1:+-2202->543
    //   2764: goto -864 -> 1900
    //   2767: ldc_w 565
    //   2770: invokestatic 571	android/text/TextUtils:isEmpty	(Ljava/lang/CharSequence;)Z
    //   2773: ifne +19 -> 2792
    //   2776: aload 33
    //   2778: getfield 574	o/az:Wc	Ljava/util/HashMap;
    //   2781: ldc_w 565
    //   2784: aload 24
    //   2786: invokeinterface 499 3 0
    //   2791: pop
    //   2792: iconst_1
    //   2793: invokestatic 580	o/bp:ᵗ	(Z)Ljava/lang/String;
    //   2796: astore 24
    //   2798: ldc_w 582
    //   2801: invokestatic 571	android/text/TextUtils:isEmpty	(Ljava/lang/CharSequence;)Z
    //   2804: ifne +19 -> 2823
    //   2807: aload 23
    //   2809: getfield 574	o/az:Wc	Ljava/util/HashMap;
    //   2812: ldc_w 582
    //   2815: aload 24
    //   2817: invokeinterface 499 3 0
    //   2822: pop
    //   2823: ldc_w 482
    //   2826: invokestatic 571	android/text/TextUtils:isEmpty	(Ljava/lang/CharSequence;)Z
    //   2829: ifne +20 -> 2849
    //   2832: aload 23
    //   2834: getfield 574	o/az:Wc	Ljava/util/HashMap;
    //   2837: ldc_w 482
    //   2840: ldc_w 584
    //   2843: invokeinterface 499 3 0
    //   2848: pop
    //   2849: new 508	o/aw$if
    //   2852: dup
    //   2853: invokespecial 585	o/aw$if:<init>	()V
    //   2856: astore 24
    //   2858: ldc_w 482
    //   2861: iconst_2
    //   2862: invokestatic 487	o/if:ˊ	(Ljava/lang/String;I)Ljava/lang/String;
    //   2865: astore 25
    //   2867: aload 25
    //   2869: ifnull +21 -> 2890
    //   2872: aload 24
    //   2874: getfield 493	o/aw$ˎ:VX	Ljava/util/HashMap;
    //   2877: aload 25
    //   2879: aload 31
    //   2881: invokeinterface 499 3 0
    //   2886: pop
    //   2887: goto +9 -> 2896
    //   2890: ldc_w 501
    //   2893: invokestatic 506	o/bi:ǃ	(Ljava/lang/String;)V
    //   2896: aload 24
    //   2898: checkcast 508	o/aw$if
    //   2901: astore 24
    //   2903: ldc_w 482
    //   2906: iconst_5
    //   2907: invokestatic 487	o/if:ˊ	(Ljava/lang/String;I)Ljava/lang/String;
    //   2910: astore 25
    //   2912: aload 25
    //   2914: ifnull +21 -> 2935
    //   2917: aload 24
    //   2919: getfield 493	o/aw$ˎ:VX	Ljava/util/HashMap;
    //   2922: aload 25
    //   2924: aload 28
    //   2926: invokeinterface 499 3 0
    //   2931: pop
    //   2932: goto +9 -> 2941
    //   2935: ldc_w 501
    //   2938: invokestatic 506	o/bi:ǃ	(Ljava/lang/String;)V
    //   2941: aload 24
    //   2943: checkcast 508	o/aw$if
    //   2946: astore 25
    //   2948: aload 23
    //   2950: astore 24
    //   2952: aload_0
    //   2953: getfield 137	o/ᓾ:mode	I
    //   2956: iconst_1
    //   2957: if_icmpeq -223 -> 2734
    //   2960: goto -1738 -> 1222
    //   2963: aload_0
    //   2964: invokespecial 587	o/Ꮀ:onStart	()V
    //   2967: goto +39 -> 3006
    //   2970: bipush 38
    //   2972: istore_1
    //   2973: goto +6 -> 2979
    //   2976: bipush 69
    //   2978: istore_1
    //   2979: iload_1
    //   2980: lookupswitch	default:+20->3000, 38:+246->3226
    //   3000: lconst_0
    //   3001: lstore 5
    //   3003: goto +223 -> 3226
    //   3006: invokestatic 196	o/aln:bd	()Lo/aln;
    //   3009: putstatic 190	o/ᓾ:yz	Lo/aln;
    //   3012: new 589	o/alt$if
    //   3015: dup
    //   3016: invokespecial 590	o/alt$if:<init>	()V
    //   3019: astore 23
    //   3021: aload 23
    //   3023: iconst_0
    //   3024: putfield 593	o/alt$if:aFX	Z
    //   3027: new 595	o/alt
    //   3030: dup
    //   3031: aload 23
    //   3033: iconst_0
    //   3034: invokespecial 598	o/alt:<init>	(Lo/alt$if;B)V
    //   3037: astore 24
    //   3039: getstatic 190	o/ᓾ:yz	Lo/aln;
    //   3042: astore 23
    //   3044: aload 23
    //   3046: getfield 602	o/aln:bav	Ljava/util/concurrent/locks/ReentrantReadWriteLock;
    //   3049: invokeinterface 608 1 0
    //   3054: invokeinterface 613 1 0
    //   3059: aload 23
    //   3061: getfield 617	o/aln:arb	Lo/wl$if;
    //   3064: getfield 620	o/wl$if:aFX	Z
    //   3067: istore_3
    //   3068: aload 24
    //   3070: getfield 621	o/alt:aFX	Z
    //   3073: istore 4
    //   3075: aload 23
    //   3077: getfield 617	o/aln:arb	Lo/wl$if;
    //   3080: iload 4
    //   3082: putfield 620	o/wl$if:aFX	Z
    //   3085: iload_3
    //   3086: iload 4
    //   3088: if_icmpeq +8 -> 3096
    //   3091: aload 23
    //   3093: invokevirtual 624	o/aln:bg	()V
    //   3096: aload 23
    //   3098: getfield 602	o/aln:bav	Ljava/util/concurrent/locks/ReentrantReadWriteLock;
    //   3101: invokeinterface 608 1 0
    //   3106: invokeinterface 627 1 0
    //   3111: goto +23 -> 3134
    //   3114: astore 24
    //   3116: aload 23
    //   3118: getfield 602	o/aln:bav	Ljava/util/concurrent/locks/ReentrantReadWriteLock;
    //   3121: invokeinterface 608 1 0
    //   3126: invokeinterface 627 1 0
    //   3131: aload 24
    //   3133: athrow
    //   3134: new 629	java/util/HashMap
    //   3137: dup
    //   3138: invokespecial 630	java/util/HashMap:<init>	()V
    //   3141: astore 23
    //   3143: aload 23
    //   3145: ldc_w 632
    //   3148: bipush 102
    //   3150: bipush 36
    //   3152: getstatic 117	o/ᓾ:yR	[B
    //   3155: bipush 114
    //   3157: baload
    //   3158: i2b
    //   3159: invokestatic 167	o/ᓾ:ˊ	(IBS)Ljava/lang/String;
    //   3162: invokeinterface 499 3 0
    //   3167: pop
    //   3168: aload 23
    //   3170: ldc_w 634
    //   3173: bipush 102
    //   3175: bipush 36
    //   3177: getstatic 117	o/ᓾ:yR	[B
    //   3180: bipush 114
    //   3182: baload
    //   3183: i2b
    //   3184: invokestatic 167	o/ᓾ:ˊ	(IBS)Ljava/lang/String;
    //   3187: invokeinterface 499 3 0
    //   3192: pop
    //   3193: getstatic 190	o/ᓾ:yz	Lo/aln;
    //   3196: aload 23
    //   3198: ldc -44
    //   3200: invokevirtual 637	o/aln:ˋ	(Ljava/util/HashMap;Ljava/lang/String;)V
    //   3203: ldc2_w 638
    //   3206: lstore 5
    //   3208: getstatic 190	o/ᓾ:yz	Lo/aln;
    //   3211: invokevirtual 643	o/aln:bf	()Lo/als;
    //   3214: getfield 649	o/als:baz	Lo/alt;
    //   3217: getfield 621	o/alt:aFX	Z
    //   3220: ifne -244 -> 2976
    //   3223: goto -253 -> 2970
    //   3226: getstatic 190	o/ᓾ:yz	Lo/aln;
    //   3229: lload 5
    //   3231: invokevirtual 653	o/aln:ﹺ	(J)Lo/akp;
    //   3234: new 655	o/ᓿ
    //   3237: dup
    //   3238: aload_0
    //   3239: invokespecial 658	o/ᓿ:<init>	(Lo/ᓾ;)V
    //   3242: invokevirtual 663	o/aki:ˊ	(Lo/ᓿ;)Lo/akp;
    //   3245: pop
    //   3246: aload_0
    //   3247: getfield 360	o/ᓾ:yy	Lo/aks;
    //   3250: astore 23
    //   3252: aload 23
    //   3254: getfield 344	o/aks:aRZ	Lo/aho;
    //   3257: getfield 350	o/aho:aWi	Lcom/google/android/gms/measurement/AppMeasurement;
    //   3260: ldc_w 665
    //   3263: aconst_null
    //   3264: invokevirtual 668	com/google/android/gms/measurement/AppMeasurement:ˊ	(Ljava/lang/String;Landroid/os/Bundle;)V
    //   3267: aload_0
    //   3268: invokestatic 387	o/ﾚ:ՙ	(Landroid/content/Context;)V
    //   3271: invokestatic 392	o/ᓾ:ךּ	()Z
    //   3274: istore_3
    //   3275: iload_3
    //   3276: ifeq -900 -> 2376
    //   3279: goto -772 -> 2507
    //   3282: aload 25
    //   3284: astore 23
    //   3286: aload 30
    //   3288: astore 24
    //   3290: iload_1
    //   3291: lookupswitch	default:+25->3316, 17:+-2400->891, 43:+-2017->1274
    //   3316: aload 25
    //   3318: astore 23
    //   3320: goto -1703 -> 1617
    //   3323: getstatic 123	o/ᓾ:yQ	I
    //   3326: bipush 93
    //   3328: iadd
    //   3329: istore_1
    //   3330: iload_1
    //   3331: sipush 128
    //   3334: irem
    //   3335: putstatic 121	o/ᓾ:yP	I
    //   3338: iload_1
    //   3339: iconst_2
    //   3340: irem
    //   3341: ifne -2498 -> 843
    //   3344: goto -621 -> 2723
    //   3347: getstatic 123	o/ᓾ:yQ	I
    //   3350: bipush 97
    //   3352: iadd
    //   3353: istore_1
    //   3354: iload_1
    //   3355: sipush 128
    //   3358: irem
    //   3359: putstatic 121	o/ᓾ:yP	I
    //   3362: iload_1
    //   3363: iconst_2
    //   3364: irem
    //   3365: ifne +11 -> 3376
    //   3368: goto -640 -> 2728
    //   3371: iconst_1
    //   3372: istore_1
    //   3373: goto -1725 -> 1648
    //   3376: bipush 42
    //   3378: istore_1
    //   3379: goto -2964 -> 415
    //   3382: bipush 46
    //   3384: istore_1
    //   3385: goto -3347 -> 38
    //   3388: bipush 56
    //   3390: istore_1
    //   3391: goto -692 -> 2699
    //   3394: iconst_0
    //   3395: istore_1
    //   3396: goto -1748 -> 1648
    //   3399: aload 23
    //   3401: astore 33
    //   3403: aload 25
    //   3405: astore 31
    //   3407: aload 30
    //   3409: astore 28
    //   3411: aload 24
    //   3413: astore 26
    //   3415: aload 23
    //   3417: astore 34
    //   3419: aload 25
    //   3421: astore 32
    //   3423: aload 30
    //   3425: astore 29
    //   3427: aload 24
    //   3429: astore 27
    //   3431: iload_1
    //   3432: lookupswitch	default:+28->3460, 11:+-1392->2040, 52:+40->3472
    //   3460: aload 25
    //   3462: astore 26
    //   3464: goto -2952 -> 512
    //   3467: iconst_0
    //   3468: istore_1
    //   3469: goto -2947 -> 522
    //   3472: getstatic 117	o/ᓾ:yR	[B
    //   3475: iconst_2
    //   3476: baload
    //   3477: iconst_1
    //   3478: isub
    //   3479: i2s
    //   3480: getstatic 117	o/ᓾ:yR	[B
    //   3483: bipush 15
    //   3485: baload
    //   3486: i2b
    //   3487: getstatic 117	o/ᓾ:yR	[B
    //   3490: bipush 75
    //   3492: baload
    //   3493: iconst_1
    //   3494: isub
    //   3495: i2b
    //   3496: invokestatic 167	o/ᓾ:ˊ	(IBS)Ljava/lang/String;
    //   3499: astore 24
    //   3501: aload 34
    //   3503: astore 33
    //   3505: aload 32
    //   3507: astore 31
    //   3509: aload 29
    //   3511: astore 28
    //   3513: aload 27
    //   3515: astore 23
    //   3517: goto -750 -> 2767
    //   3520: ldc_w 546
    //   3523: astore 24
    //   3525: ldc2_w 547
    //   3528: getstatic 129	o/ᓾ:y	J
    //   3531: ldc2_w 263
    //   3534: ladd
    //   3535: getstatic 129	o/ᓾ:y	J
    //   3538: lmul
    //   3539: lcmp
    //   3540: ifne -1470 -> 2070
    //   3543: goto -1732 -> 1811
    // Local variable table:
    //   start	length	slot	name	signature
    //   0	3546	0	this	ᓾ
    //   20	3449	1	i	int
    //   261	1330	2	j	int
    //   202	3074	3	bool1	boolean
    //   3073	16	4	bool2	boolean
    //   1123	2107	5	l1	long
    //   1128	43	7	l2	long
    //   1133	40	9	l3	long
    //   1138	47	11	l4	long
    //   1143	44	13	l5	long
    //   1148	42	15	l6	long
    //   1153	39	17	l7	long
    //   1158	38	19	l8	long
    //   1163	41	21	l9	long
    //   126	1	23	localObject1	Object
    //   150	190	23	localObject2	Object
    //   410	8	23	localObject3	Object
    //   446	149	23	localObject4	Object
    //   616	1	23	localif1	aw.if
    //   643	86	23	localObject5	Object
    //   733	1	23	localif2	aw.if
    //   744	133	23	localObject6	Object
    //   894	82	23	localObject7	Object
    //   1001	3	23	localObject8	Object
    //   1062	3	23	localObject9	Object
    //   1217	265	23	localException1	Exception
    //   1561	364	23	localObject10	Object
    //   1991	3	23	localObject11	Object
    //   2065	1	23	localObject12	Object
    //   2076	36	23	localException2	Exception
    //   2154	109	23	localObject13	Object
    //   2268	132	23	localObject14	Object
    //   2407	66	23	localObject15	Object
    //   2478	1038	23	localObject16	Object
    //   95	2974	24	localObject17	Object
    //   3114	18	24	localObject18	Object
    //   3288	236	24	localObject19	Object
    //   124	3337	25	localObject20	Object
    //   130	3333	26	localObject21	Object
    //   2121	1393	27	localObject22	Object
    //   2101	1411	28	localObject23	Object
    //   2117	1393	29	localObject24	Object
    //   1254	2170	30	localObject25	Object
    //   2097	1411	31	localObject26	Object
    //   2113	1393	32	localObject27	Object
    //   2093	1411	33	localObject28	Object
    //   2109	1393	34	localObject29	Object
    // Exception table:
    //   from	to	target	type
    //   158	203	150	finally
    //   454	499	446	finally
    //   651	690	643	finally
    //   752	791	744	finally
    //   1009	1054	1001	finally
    //   1070	1115	1062	finally
    //   448	454	1217	java/lang/Exception
    //   993	998	1217	java/lang/Exception
    //   1999	2037	1991	finally
    //   448	454	2076	java/lang/Exception
    //   1003	1009	2076	java/lang/Exception
    //   1054	1059	2076	java/lang/Exception
    //   1064	1070	2076	java/lang/Exception
    //   1115	1120	2076	java/lang/Exception
    //   1120	1125	2076	java/lang/Exception
    //   1125	1130	2076	java/lang/Exception
    //   1130	1165	2076	java/lang/Exception
    //   2963	2967	2076	java/lang/Exception
    //   3006	3059	2076	java/lang/Exception
    //   3096	3111	2076	java/lang/Exception
    //   3116	3134	2076	java/lang/Exception
    //   3134	3203	2076	java/lang/Exception
    //   3208	3223	2076	java/lang/Exception
    //   3226	3246	2076	java/lang/Exception
    //   3246	3252	2076	java/lang/Exception
    //   3252	3267	2076	java/lang/Exception
    //   3267	3271	2076	java/lang/Exception
    //   3271	3275	2076	java/lang/Exception
    //   2162	2200	2154	finally
    //   2415	2460	2407	finally
    //   3059	3085	3114	finally
    //   3091	3096	3114	finally
  }
  
  protected void onStop()
  {
    ﾚ.י(this);
    super.onStop();
  }
  
  protected final void כּ()
  {
    try
    {
      if (yA == null)
      {
        if (yA == null)
        {
          yA = new ท(this);
          yA.setAdSize(ถ.IC);
          yA.setAdUnitId(י("banner"));
          yA.setAdListener$3b914f14(yC);
          ((FrameLayout)findViewById(2131689589)).addView(yA, 0);
        }
        yB = new ฅ(new ฅ.if(), (byte)0);
        yA.ˊ(yB);
        yA.setVisibility(0);
        if ((mode != 2) && (mode != 3) && (yM != null)) {
          yM.setVisibility(0);
        }
      }
      return;
    }
    catch (Exception localException)
    {
      yA = null;
      az localaz = הּ.ﾍ();
      aw.ˋ localˋ = new aw.ˋ();
      String str = localException.getMessage();
      VX.put("&exd", str);
      str = bp.ᵗ(false);
      VX.put("&exf", str);
      localaz.ˊ(localˋ.γ());
    }
  }
  
  protected final void ﭨ()
  {
    if (yA != null)
    {
      yA.setVisibility(8);
      if ((!yN) && (yM != null) && (yO)) {
        yM.setVisibility(8);
      }
    }
  }
  
  public final void ﮢ()
  {
    if ((mode != 2) && (mode != 3) && (yM != null)) {
      yM.setVisibility(0);
    }
  }
  
  public final void ﺌ()
  {
    if ((!yN) && (yM != null) && (yO)) {
      yM.setVisibility(8);
    }
  }
  
  final class if
    extends hx
  {
    private static int yP = 0;
    private static int yQ = 1;
    private static final byte[] yR = { 39, 63, 75, 82, 0 };
    
    private if() {}
    
    private static String ˊ(short paramShort, int paramInt, byte paramByte)
    {
      break label45;
      paramInt += 1;
      byte[] arrayOfByte1;
      short s = arrayOfByte1[paramInt];
      for (;;)
      {
        s = yQ + 51;
        yP = s % 128;
        if (s % 2 == 0) {
          break label80;
        }
        break label80;
        label45:
        s = 3 - paramShort * 2;
        int i = paramInt * 4 + 2;
        paramShort = paramByte * 4 + 97;
        paramByte = -1;
        arrayOfByte1 = yR;
        byte[] arrayOfByte2 = new byte[i];
        paramInt = s;
        label80:
        paramByte += 1;
        arrayOfByte2[paramByte] = ((byte)paramShort);
        if (paramByte != i - 1) {
          break;
        }
        return new String(arrayOfByte2, 0);
        paramShort = s + paramShort + 3;
      }
    }
    
    /* Error */
    public final void Ӏ(int paramInt)
    {
      // Byte code:
      //   0: goto +43 -> 43
      //   3: iload_3
      //   4: tableswitch	default:+20->24, 1:+28->32
      //   24: goto +43 -> 67
      //   27: astore 4
      //   29: aload 4
      //   31: athrow
      //   32: return
      //   33: iconst_1
      //   34: istore_3
      //   35: goto -32 -> 3
      //   38: iconst_0
      //   39: istore_3
      //   40: goto -37 -> 3
      //   43: aload_0
      //   44: getfield 32	o/ᓾ$if:yT	Lo/ᓾ;
      //   47: astore 4
      //   49: aload 4
      //   51: getfield 52	o/ᓾ:yA	Lo/ท;
      //   54: astore 4
      //   56: aload 4
      //   58: ifnull +6 -> 64
      //   61: goto -23 -> 38
      //   64: goto -31 -> 33
      //   67: getstatic 23	o/ᓾ$if:yR	[B
      //   70: iconst_4
      //   71: baload
      //   72: i2b
      //   73: istore_2
      //   74: iload_2
      //   75: i2b
      //   76: istore_3
      //   77: iload_2
      //   78: iload_3
      //   79: iload_3
      //   80: i2b
      //   81: invokestatic 54	o/ᓾ$if:ˊ	(SIB)Ljava/lang/String;
      //   84: invokevirtual 58	java/lang/String:intern	()Ljava/lang/String;
      //   87: ldc 60
      //   89: ldc 62
      //   91: iload_1
      //   92: invokestatic 67	o/л:ˊ	(Ljava/lang/String;Ljava/lang/String;Ljava/lang/String;I)V
      //   95: return
      // Local variable table:
      //   start	length	slot	name	signature
      //   0	96	0	this	if
      //   0	96	1	paramInt	int
      //   73	5	2	s	short
      //   3	77	3	i	int
      //   27	3	4	localException	Exception
      //   47	10	4	localObject	Object
      // Exception table:
      //   from	to	target	type
      //   43	49	27	java/lang/Exception
      //   49	56	27	java/lang/Exception
    }
    
    public final void ﺯ()
    {
      break label116;
      int i = yP + 69;
      yQ = i % 128;
      if (i % 2 != 0) {
        break label56;
      }
      for (;;)
      {
        switch (i)
        {
        default: 
          break;
        case 0: 
          return;
          label56:
          yO = true;
          yA.setVisibility(0);
          ﺌ();
          short s = (byte)yR[4];
          i = (byte)s;
          л.ˊ(ˊ(s, i, (byte)i).intern(), "admob", "loaded", 0);
          return;
          label111:
          i = 1;
          continue;
          try
          {
            label116:
            Object localObject = ᓾ.this;
            localObject = yA;
            if (localObject != null) {
              break label111;
            }
            i = 0;
          }
          catch (Exception localException)
          {
            throw localException;
          }
        }
      }
    }
    
    public final void ﻣ()
    {
      short s = (byte)yR[4];
      int i = (byte)s;
      л.ˊ(ˊ(s, i, (byte)i).intern(), "admob", "click", 0);
    }
  }
}

/* Location:
 * Qualified Name:     o.ᓾ
 * Java Class Version: 6 (50.0)
 * JD-Core Version:    0.7.1
 */