package o;

import android.content.ComponentName;
import android.content.Context;
import android.content.pm.ResolveInfo;
import android.database.DataSetObservable;
import android.os.AsyncTask;
import android.text.TextUtils;
import java.math.BigDecimal;
import java.util.HashMap;
import java.util.List;

class ノ
  extends DataSetObservable
{
  private static final String lT = ノ.class.getSimpleName();
  final Object lU;
  final List<if> lV;
  final List<ˊ> lW;
  final String lX;
  private boolean lY;
  boolean lZ;
  private final Context mContext;
  boolean ma;
  
  static
  {
    new Object();
    new HashMap();
  }
  
  /* Error */
  private void ῑ()
  {
    // Byte code:
    //   0: aload_0
    //   1: getfield 51	o/ノ:mContext	Landroid/content/Context;
    //   4: aload_0
    //   5: getfield 54	o/ノ:lX	Ljava/lang/String;
    //   8: invokevirtual 71	android/content/Context:openFileInput	(Ljava/lang/String;)Ljava/io/FileInputStream;
    //   11: astore_2
    //   12: goto +3 -> 15
    //   15: invokestatic 77	android/util/Xml:newPullParser	()Lorg/xmlpull/v1/XmlPullParser;
    //   18: astore_3
    //   19: aload_3
    //   20: aload_2
    //   21: ldc 79
    //   23: invokeinterface 85 3 0
    //   28: iconst_0
    //   29: istore_1
    //   30: iload_1
    //   31: iconst_1
    //   32: if_icmpeq +18 -> 50
    //   35: iload_1
    //   36: iconst_2
    //   37: if_icmpeq +13 -> 50
    //   40: aload_3
    //   41: invokeinterface 89 1 0
    //   46: istore_1
    //   47: goto -17 -> 30
    //   50: ldc 91
    //   52: aload_3
    //   53: invokeinterface 94 1 0
    //   58: invokevirtual 100	java/lang/String:equals	(Ljava/lang/Object;)Z
    //   61: ifne +13 -> 74
    //   64: new 63	org/xmlpull/v1/XmlPullParserException
    //   67: dup
    //   68: ldc 102
    //   70: invokespecial 105	org/xmlpull/v1/XmlPullParserException:<init>	(Ljava/lang/String;)V
    //   73: athrow
    //   74: aload_0
    //   75: getfield 107	o/ノ:lW	Ljava/util/List;
    //   78: astore 4
    //   80: aload 4
    //   82: invokeinterface 112 1 0
    //   87: aload_3
    //   88: invokeinterface 89 1 0
    //   93: istore_1
    //   94: iload_1
    //   95: iconst_1
    //   96: if_icmpeq +88 -> 184
    //   99: iload_1
    //   100: iconst_3
    //   101: if_icmpeq -14 -> 87
    //   104: iload_1
    //   105: iconst_4
    //   106: if_icmpeq -19 -> 87
    //   109: ldc 114
    //   111: aload_3
    //   112: invokeinterface 94 1 0
    //   117: invokevirtual 100	java/lang/String:equals	(Ljava/lang/Object;)Z
    //   120: ifne +13 -> 133
    //   123: new 63	org/xmlpull/v1/XmlPullParserException
    //   126: dup
    //   127: ldc 116
    //   129: invokespecial 105	org/xmlpull/v1/XmlPullParserException:<init>	(Ljava/lang/String;)V
    //   132: athrow
    //   133: aload 4
    //   135: new 9	o/ノ$ˊ
    //   138: dup
    //   139: aload_3
    //   140: aconst_null
    //   141: ldc 118
    //   143: invokeinterface 122 3 0
    //   148: aload_3
    //   149: aconst_null
    //   150: ldc 124
    //   152: invokeinterface 122 3 0
    //   157: invokestatic 130	java/lang/Long:parseLong	(Ljava/lang/String;)J
    //   160: aload_3
    //   161: aconst_null
    //   162: ldc -124
    //   164: invokeinterface 122 3 0
    //   169: invokestatic 138	java/lang/Float:parseFloat	(Ljava/lang/String;)F
    //   172: invokespecial 141	o/ノ$ˊ:<init>	(Ljava/lang/String;JF)V
    //   175: invokeinterface 144 2 0
    //   180: pop
    //   181: goto -94 -> 87
    //   184: aload_2
    //   185: ifnull +93 -> 278
    //   188: aload_2
    //   189: invokevirtual 149	java/io/FileInputStream:close	()V
    //   192: return
    //   193: astore_3
    //   194: getstatic 39	o/ノ:lT	Ljava/lang/String;
    //   197: new 151	java/lang/StringBuilder
    //   200: dup
    //   201: ldc -103
    //   203: invokespecial 154	java/lang/StringBuilder:<init>	(Ljava/lang/String;)V
    //   206: aload_0
    //   207: getfield 54	o/ノ:lX	Ljava/lang/String;
    //   210: invokevirtual 158	java/lang/StringBuilder:append	(Ljava/lang/String;)Ljava/lang/StringBuilder;
    //   213: invokevirtual 161	java/lang/StringBuilder:toString	()Ljava/lang/String;
    //   216: aload_3
    //   217: invokestatic 167	android/util/Log:e	(Ljava/lang/String;Ljava/lang/String;Ljava/lang/Throwable;)I
    //   220: pop
    //   221: aload_2
    //   222: ifnull +56 -> 278
    //   225: aload_2
    //   226: invokevirtual 149	java/io/FileInputStream:close	()V
    //   229: return
    //   230: astore_3
    //   231: getstatic 39	o/ノ:lT	Ljava/lang/String;
    //   234: new 151	java/lang/StringBuilder
    //   237: dup
    //   238: ldc -103
    //   240: invokespecial 154	java/lang/StringBuilder:<init>	(Ljava/lang/String;)V
    //   243: aload_0
    //   244: getfield 54	o/ノ:lX	Ljava/lang/String;
    //   247: invokevirtual 158	java/lang/StringBuilder:append	(Ljava/lang/String;)Ljava/lang/StringBuilder;
    //   250: invokevirtual 161	java/lang/StringBuilder:toString	()Ljava/lang/String;
    //   253: aload_3
    //   254: invokestatic 167	android/util/Log:e	(Ljava/lang/String;Ljava/lang/String;Ljava/lang/Throwable;)I
    //   257: pop
    //   258: aload_2
    //   259: ifnull +19 -> 278
    //   262: aload_2
    //   263: invokevirtual 149	java/io/FileInputStream:close	()V
    //   266: return
    //   267: astore_3
    //   268: aload_2
    //   269: ifnull +7 -> 276
    //   272: aload_2
    //   273: invokevirtual 149	java/io/FileInputStream:close	()V
    //   276: aload_3
    //   277: athrow
    //   278: return
    //   279: astore_2
    //   280: return
    //   281: astore_2
    //   282: return
    //   283: astore_2
    //   284: return
    //   285: astore_2
    //   286: return
    //   287: astore_2
    //   288: goto -12 -> 276
    // Local variable table:
    //   start	length	slot	name	signature
    //   0	291	0	this	ノ
    //   29	78	1	i	int
    //   11	262	2	localFileInputStream	java.io.FileInputStream
    //   279	1	2	localFileNotFoundException	java.io.FileNotFoundException
    //   281	1	2	localIOException1	java.io.IOException
    //   283	1	2	localIOException2	java.io.IOException
    //   285	1	2	localIOException3	java.io.IOException
    //   287	1	2	localIOException4	java.io.IOException
    //   18	143	3	localXmlPullParser	org.xmlpull.v1.XmlPullParser
    //   193	24	3	localXmlPullParserException	org.xmlpull.v1.XmlPullParserException
    //   230	24	3	localIOException5	java.io.IOException
    //   267	10	3	localObject	Object
    //   78	56	4	localList	List
    // Exception table:
    //   from	to	target	type
    //   15	28	193	org/xmlpull/v1/XmlPullParserException
    //   40	47	193	org/xmlpull/v1/XmlPullParserException
    //   50	74	193	org/xmlpull/v1/XmlPullParserException
    //   74	87	193	org/xmlpull/v1/XmlPullParserException
    //   87	94	193	org/xmlpull/v1/XmlPullParserException
    //   109	133	193	org/xmlpull/v1/XmlPullParserException
    //   133	181	193	org/xmlpull/v1/XmlPullParserException
    //   15	28	230	java/io/IOException
    //   40	47	230	java/io/IOException
    //   50	74	230	java/io/IOException
    //   74	87	230	java/io/IOException
    //   87	94	230	java/io/IOException
    //   109	133	230	java/io/IOException
    //   133	181	230	java/io/IOException
    //   15	28	267	finally
    //   40	47	267	finally
    //   50	74	267	finally
    //   74	87	267	finally
    //   87	94	267	finally
    //   109	133	267	finally
    //   133	181	267	finally
    //   194	221	267	finally
    //   231	258	267	finally
    //   0	12	279	java/io/FileNotFoundException
    //   188	192	281	java/io/IOException
    //   225	229	283	java/io/IOException
    //   262	266	285	java/io/IOException
    //   272	276	287	java/io/IOException
  }
  
  public final int getHistorySize()
  {
    synchronized (lU)
    {
      boolean bool = ί();
      ῐ();
      if ((bool | false)) {
        notifyChanged();
      }
      int i = lW.size();
      return i;
    }
  }
  
  public final int ˊ(ResolveInfo paramResolveInfo)
  {
    synchronized (lU)
    {
      boolean bool = ί();
      ῐ();
      if ((bool | false)) {
        notifyChanged();
      }
      List localList = lV;
      int j = localList.size();
      int i = 0;
      while (i < j)
      {
        ResolveInfo localResolveInfo = getresolveInfo;
        if (localResolveInfo == paramResolveInfo) {
          return i;
        }
        i += 1;
      }
      return -1;
    }
  }
  
  public final ResolveInfo ۦ(int paramInt)
  {
    synchronized (lU)
    {
      boolean bool = ί();
      ῐ();
      if ((bool | false)) {
        notifyChanged();
      }
      ResolveInfo localResolveInfo = lV.get(paramInt)).resolveInfo;
      return localResolveInfo;
    }
  }
  
  public final int ἱ()
  {
    synchronized (lU)
    {
      boolean bool = ί();
      ῐ();
      if ((bool | false)) {
        notifyChanged();
      }
      int i = lV.size();
      return i;
    }
  }
  
  public final ResolveInfo ὶ()
  {
    synchronized (lU)
    {
      boolean bool = ί();
      ῐ();
      if ((bool | false)) {
        notifyChanged();
      }
      if (!lV.isEmpty())
      {
        ResolveInfo localResolveInfo = lV.get(0)).resolveInfo;
        return localResolveInfo;
      }
    }
    return null;
  }
  
  final boolean ί()
  {
    if ((lY) && (ma) && (!TextUtils.isEmpty(lX)))
    {
      lY = false;
      lZ = true;
      ῑ();
      return true;
    }
    return false;
  }
  
  final void ῐ()
  {
    int j = lW.size();
    if (j <= 0) {
      return;
    }
    ma = true;
    int i = 0;
    while (i < j)
    {
      lW.remove(0);
      i += 1;
    }
  }
  
  public final class if
    implements Comparable<if>
  {
    public final ResolveInfo resolveInfo;
    
    public final boolean equals(Object paramObject)
    {
      if (this == paramObject) {
        return true;
      }
      if (paramObject == null) {
        return false;
      }
      if (getClass() != paramObject.getClass()) {
        return false;
      }
      return Float.floatToIntBits(0.0F) == Float.floatToIntBits(0.0F);
    }
    
    public final int hashCode()
    {
      return Float.floatToIntBits(0.0F) + 31;
    }
    
    public final String toString()
    {
      StringBuilder localStringBuilder = new StringBuilder();
      localStringBuilder.append("[");
      localStringBuilder.append("resolveInfo:").append(resolveInfo.toString());
      localStringBuilder.append("; weight:").append(new BigDecimal(0.0D));
      localStringBuilder.append("]");
      return localStringBuilder.toString();
    }
  }
  
  public static final class ˊ
  {
    public final ComponentName mb;
    public final long time;
    public final float weight;
    
    public ˊ(ComponentName paramComponentName, long paramLong, float paramFloat)
    {
      mb = paramComponentName;
      time = paramLong;
      weight = paramFloat;
    }
    
    public ˊ(String paramString, long paramLong, float paramFloat)
    {
      this(ComponentName.unflattenFromString(paramString), paramLong, paramFloat);
    }
    
    public final boolean equals(Object paramObject)
    {
      if (this == paramObject) {
        return true;
      }
      if (paramObject == null) {
        return false;
      }
      if (getClass() != paramObject.getClass()) {
        return false;
      }
      paramObject = (ˊ)paramObject;
      if (mb == null)
      {
        if (mb != null) {
          return false;
        }
      }
      else if (!mb.equals(mb)) {
        return false;
      }
      if (time != time) {
        return false;
      }
      return Float.floatToIntBits(weight) == Float.floatToIntBits(weight);
    }
    
    public final int hashCode()
    {
      int i;
      if (mb == null) {
        i = 0;
      } else {
        i = mb.hashCode();
      }
      return ((i + 31) * 31 + (int)(time ^ time >>> 32)) * 31 + Float.floatToIntBits(weight);
    }
    
    public final String toString()
    {
      StringBuilder localStringBuilder = new StringBuilder();
      localStringBuilder.append("[");
      localStringBuilder.append("; activity:").append(mb);
      localStringBuilder.append("; time:").append(time);
      localStringBuilder.append("; weight:").append(new BigDecimal(weight));
      localStringBuilder.append("]");
      return localStringBuilder.toString();
    }
  }
  
  final class ˋ
    extends AsyncTask<Object, Void, Void>
  {
    private ˋ() {}
    
    /* Error */
    private Void ˊ(Object... paramVarArgs)
    {
      // Byte code:
      //   0: aload_1
      //   1: iconst_0
      //   2: aaload
      //   3: checkcast 33	java/util/List
      //   6: astore 4
      //   8: aload_1
      //   9: iconst_1
      //   10: aaload
      //   11: checkcast 35	java/lang/String
      //   14: astore 5
      //   16: aload_0
      //   17: getfield 14	o/ノ$ˋ:mc	Lo/ノ;
      //   20: invokestatic 38	o/ノ:ˊ	(Lo/ノ;)Landroid/content/Context;
      //   23: aload 5
      //   25: iconst_0
      //   26: invokevirtual 44	android/content/Context:openFileOutput	(Ljava/lang/String;I)Ljava/io/FileOutputStream;
      //   29: astore_1
      //   30: goto +31 -> 61
      //   33: astore_1
      //   34: invokestatic 48	o/ノ:‿	()Ljava/lang/String;
      //   37: new 50	java/lang/StringBuilder
      //   40: dup
      //   41: ldc 52
      //   43: invokespecial 55	java/lang/StringBuilder:<init>	(Ljava/lang/String;)V
      //   46: aload 5
      //   48: invokevirtual 59	java/lang/StringBuilder:append	(Ljava/lang/String;)Ljava/lang/StringBuilder;
      //   51: invokevirtual 62	java/lang/StringBuilder:toString	()Ljava/lang/String;
      //   54: aload_1
      //   55: invokestatic 68	android/util/Log:e	(Ljava/lang/String;Ljava/lang/String;Ljava/lang/Throwable;)I
      //   58: pop
      //   59: aconst_null
      //   60: areturn
      //   61: invokestatic 74	android/util/Xml:newSerializer	()Lorg/xmlpull/v1/XmlSerializer;
      //   64: astore 5
      //   66: aload 5
      //   68: aload_1
      //   69: aconst_null
      //   70: invokeinterface 80 3 0
      //   75: aload 5
      //   77: ldc 82
      //   79: iconst_1
      //   80: invokestatic 88	java/lang/Boolean:valueOf	(Z)Ljava/lang/Boolean;
      //   83: invokeinterface 92 3 0
      //   88: aload 5
      //   90: aconst_null
      //   91: ldc 94
      //   93: invokeinterface 98 3 0
      //   98: pop
      //   99: aload 4
      //   101: invokeinterface 102 1 0
      //   106: istore_3
      //   107: iconst_0
      //   108: istore_2
      //   109: iload_2
      //   110: iload_3
      //   111: if_icmpge +102 -> 213
      //   114: aload 4
      //   116: iconst_0
      //   117: invokeinterface 106 2 0
      //   122: checkcast 108	o/ノ$ˊ
      //   125: astore 6
      //   127: aload 5
      //   129: aconst_null
      //   130: ldc 110
      //   132: invokeinterface 98 3 0
      //   137: pop
      //   138: aload 5
      //   140: aconst_null
      //   141: ldc 112
      //   143: aload 6
      //   145: getfield 116	o/ノ$ˊ:mb	Landroid/content/ComponentName;
      //   148: invokevirtual 121	android/content/ComponentName:flattenToString	()Ljava/lang/String;
      //   151: invokeinterface 125 4 0
      //   156: pop
      //   157: aload 5
      //   159: aconst_null
      //   160: ldc 127
      //   162: aload 6
      //   164: getfield 130	o/ノ$ˊ:time	J
      //   167: invokestatic 133	java/lang/String:valueOf	(J)Ljava/lang/String;
      //   170: invokeinterface 125 4 0
      //   175: pop
      //   176: aload 5
      //   178: aconst_null
      //   179: ldc -121
      //   181: aload 6
      //   183: getfield 138	o/ノ$ˊ:weight	F
      //   186: invokestatic 141	java/lang/String:valueOf	(F)Ljava/lang/String;
      //   189: invokeinterface 125 4 0
      //   194: pop
      //   195: aload 5
      //   197: aconst_null
      //   198: ldc 110
      //   200: invokeinterface 144 3 0
      //   205: pop
      //   206: iload_2
      //   207: iconst_1
      //   208: iadd
      //   209: istore_2
      //   210: goto -101 -> 109
      //   213: aload 5
      //   215: aconst_null
      //   216: ldc 94
      //   218: invokeinterface 144 3 0
      //   223: pop
      //   224: aload 5
      //   226: invokeinterface 147 1 0
      //   231: aload_0
      //   232: getfield 14	o/ノ$ˋ:mc	Lo/ノ;
      //   235: invokestatic 151	o/ノ:ˎ	(Lo/ノ;)Z
      //   238: pop
      //   239: aload_1
      //   240: ifnull +199 -> 439
      //   243: aload_1
      //   244: invokevirtual 156	java/io/FileOutputStream:close	()V
      //   247: goto +192 -> 439
      //   250: goto +189 -> 439
      //   253: astore 4
      //   255: invokestatic 48	o/ノ:‿	()Ljava/lang/String;
      //   258: new 50	java/lang/StringBuilder
      //   261: dup
      //   262: ldc 52
      //   264: invokespecial 55	java/lang/StringBuilder:<init>	(Ljava/lang/String;)V
      //   267: aload_0
      //   268: getfield 14	o/ノ$ˋ:mc	Lo/ノ;
      //   271: invokestatic 159	o/ノ:ˋ	(Lo/ノ;)Ljava/lang/String;
      //   274: invokevirtual 59	java/lang/StringBuilder:append	(Ljava/lang/String;)Ljava/lang/StringBuilder;
      //   277: invokevirtual 62	java/lang/StringBuilder:toString	()Ljava/lang/String;
      //   280: aload 4
      //   282: invokestatic 68	android/util/Log:e	(Ljava/lang/String;Ljava/lang/String;Ljava/lang/Throwable;)I
      //   285: pop
      //   286: aload_0
      //   287: getfield 14	o/ノ$ˋ:mc	Lo/ノ;
      //   290: invokestatic 151	o/ノ:ˎ	(Lo/ノ;)Z
      //   293: pop
      //   294: aload_1
      //   295: ifnull +144 -> 439
      //   298: aload_1
      //   299: invokevirtual 156	java/io/FileOutputStream:close	()V
      //   302: goto +137 -> 439
      //   305: goto +134 -> 439
      //   308: astore 4
      //   310: invokestatic 48	o/ノ:‿	()Ljava/lang/String;
      //   313: new 50	java/lang/StringBuilder
      //   316: dup
      //   317: ldc 52
      //   319: invokespecial 55	java/lang/StringBuilder:<init>	(Ljava/lang/String;)V
      //   322: aload_0
      //   323: getfield 14	o/ノ$ˋ:mc	Lo/ノ;
      //   326: invokestatic 159	o/ノ:ˋ	(Lo/ノ;)Ljava/lang/String;
      //   329: invokevirtual 59	java/lang/StringBuilder:append	(Ljava/lang/String;)Ljava/lang/StringBuilder;
      //   332: invokevirtual 62	java/lang/StringBuilder:toString	()Ljava/lang/String;
      //   335: aload 4
      //   337: invokestatic 68	android/util/Log:e	(Ljava/lang/String;Ljava/lang/String;Ljava/lang/Throwable;)I
      //   340: pop
      //   341: aload_0
      //   342: getfield 14	o/ノ$ˋ:mc	Lo/ノ;
      //   345: invokestatic 151	o/ノ:ˎ	(Lo/ノ;)Z
      //   348: pop
      //   349: aload_1
      //   350: ifnull +89 -> 439
      //   353: aload_1
      //   354: invokevirtual 156	java/io/FileOutputStream:close	()V
      //   357: goto +82 -> 439
      //   360: goto +79 -> 439
      //   363: astore 4
      //   365: invokestatic 48	o/ノ:‿	()Ljava/lang/String;
      //   368: new 50	java/lang/StringBuilder
      //   371: dup
      //   372: ldc 52
      //   374: invokespecial 55	java/lang/StringBuilder:<init>	(Ljava/lang/String;)V
      //   377: aload_0
      //   378: getfield 14	o/ノ$ˋ:mc	Lo/ノ;
      //   381: invokestatic 159	o/ノ:ˋ	(Lo/ノ;)Ljava/lang/String;
      //   384: invokevirtual 59	java/lang/StringBuilder:append	(Ljava/lang/String;)Ljava/lang/StringBuilder;
      //   387: invokevirtual 62	java/lang/StringBuilder:toString	()Ljava/lang/String;
      //   390: aload 4
      //   392: invokestatic 68	android/util/Log:e	(Ljava/lang/String;Ljava/lang/String;Ljava/lang/Throwable;)I
      //   395: pop
      //   396: aload_0
      //   397: getfield 14	o/ノ$ˋ:mc	Lo/ノ;
      //   400: invokestatic 151	o/ノ:ˎ	(Lo/ノ;)Z
      //   403: pop
      //   404: aload_1
      //   405: ifnull +34 -> 439
      //   408: aload_1
      //   409: invokevirtual 156	java/io/FileOutputStream:close	()V
      //   412: goto +27 -> 439
      //   415: goto +24 -> 439
      //   418: astore 4
      //   420: aload_0
      //   421: getfield 14	o/ノ$ˋ:mc	Lo/ノ;
      //   424: invokestatic 151	o/ノ:ˎ	(Lo/ノ;)Z
      //   427: pop
      //   428: aload_1
      //   429: ifnull +7 -> 436
      //   432: aload_1
      //   433: invokevirtual 156	java/io/FileOutputStream:close	()V
      //   436: aload 4
      //   438: athrow
      //   439: aconst_null
      //   440: areturn
      //   441: astore_1
      //   442: goto -192 -> 250
      //   445: astore_1
      //   446: goto -141 -> 305
      //   449: astore_1
      //   450: goto -90 -> 360
      //   453: astore_1
      //   454: goto -39 -> 415
      //   457: astore_1
      //   458: goto -22 -> 436
      // Local variable table:
      //   start	length	slot	name	signature
      //   0	461	0	this	ˋ
      //   0	461	1	paramVarArgs	Object[]
      //   108	102	2	i	int
      //   106	6	3	j	int
      //   6	109	4	localList	List
      //   253	28	4	localIllegalArgumentException	IllegalArgumentException
      //   308	28	4	localIllegalStateException	IllegalStateException
      //   363	28	4	localIOException	java.io.IOException
      //   418	19	4	localObject1	Object
      //   14	211	5	localObject2	Object
      //   125	57	6	localˊ	ノ.ˊ
      // Exception table:
      //   from	to	target	type
      //   16	30	33	java/io/FileNotFoundException
      //   66	107	253	java/lang/IllegalArgumentException
      //   114	206	253	java/lang/IllegalArgumentException
      //   213	231	253	java/lang/IllegalArgumentException
      //   66	107	308	java/lang/IllegalStateException
      //   114	206	308	java/lang/IllegalStateException
      //   213	231	308	java/lang/IllegalStateException
      //   66	107	363	java/io/IOException
      //   114	206	363	java/io/IOException
      //   213	231	363	java/io/IOException
      //   66	107	418	finally
      //   114	206	418	finally
      //   213	231	418	finally
      //   255	286	418	finally
      //   310	341	418	finally
      //   365	396	418	finally
      //   243	247	441	java/io/IOException
      //   298	302	445	java/io/IOException
      //   353	357	449	java/io/IOException
      //   408	412	453	java/io/IOException
      //   432	436	457	java/io/IOException
    }
  }
}

/* Location:
 * Qualified Name:     o.ノ
 * Java Class Version: 6 (50.0)
 * JD-Core Version:    0.7.1
 */