package o;

import com.google.android.gms.ads.internal.client.AdRequestParcel;

@vq
public final class ﹳ
  implements ᵔ.if
{
  public final AdRequestParcel ī;
  public final int ĭ;
  public final String ˆ;
  
  public ﹳ() {}
  
  private ﹳ(AdRequestParcel paramAdRequestParcel, String paramString, int paramInt)
  {
    ī = paramAdRequestParcel;
    ˆ = paramString;
    ĭ = paramInt;
  }
  
  /* Error */
  public ﹳ(String paramString)
  {
    // Byte code:
    //   0: aload_0
    //   1: invokespecial 17	java/lang/Object:<init>	()V
    //   4: aload_1
    //   5: ldc 30
    //   7: invokevirtual 36	java/lang/String:split	(Ljava/lang/String;)[Ljava/lang/String;
    //   10: astore_2
    //   11: aload_2
    //   12: arraylength
    //   13: iconst_3
    //   14: if_icmpeq +13 -> 27
    //   17: new 38	java/io/IOException
    //   20: dup
    //   21: ldc 40
    //   23: invokespecial 42	java/io/IOException:<init>	(Ljava/lang/String;)V
    //   26: athrow
    //   27: invokestatic 48	android/os/Parcel:obtain	()Landroid/os/Parcel;
    //   30: astore_1
    //   31: aload_0
    //   32: new 32	java/lang/String
    //   35: dup
    //   36: aload_2
    //   37: iconst_0
    //   38: aaload
    //   39: iconst_0
    //   40: invokestatic 54	android/util/Base64:decode	(Ljava/lang/String;I)[B
    //   43: ldc 56
    //   45: invokespecial 59	java/lang/String:<init>	([BLjava/lang/String;)V
    //   48: putfield 23	o/ﹳ:ˆ	Ljava/lang/String;
    //   51: aload_0
    //   52: aload_2
    //   53: iconst_1
    //   54: aaload
    //   55: invokestatic 65	java/lang/Integer:parseInt	(Ljava/lang/String;)I
    //   58: putfield 25	o/ﹳ:ĭ	I
    //   61: aload_2
    //   62: iconst_2
    //   63: aaload
    //   64: iconst_0
    //   65: invokestatic 54	android/util/Base64:decode	(Ljava/lang/String;I)[B
    //   68: astore_2
    //   69: aload_1
    //   70: aload_2
    //   71: iconst_0
    //   72: aload_2
    //   73: arraylength
    //   74: invokevirtual 69	android/os/Parcel:unmarshall	([BII)V
    //   77: aload_1
    //   78: iconst_0
    //   79: invokevirtual 73	android/os/Parcel:setDataPosition	(I)V
    //   82: aload_0
    //   83: getstatic 79	com/google/android/gms/ads/internal/client/AdRequestParcel:CREATOR	Lo/ᘦ;
    //   86: aload_1
    //   87: invokevirtual 85	o/ᘦ:createFromParcel	(Landroid/os/Parcel;)Ljava/lang/Object;
    //   90: checkcast 75	com/google/android/gms/ads/internal/client/AdRequestParcel
    //   93: putfield 21	o/ﹳ:ī	Lcom/google/android/gms/ads/internal/client/AdRequestParcel;
    //   96: aload_1
    //   97: invokevirtual 88	android/os/Parcel:recycle	()V
    //   100: return
    //   101: new 38	java/io/IOException
    //   104: dup
    //   105: ldc 90
    //   107: invokespecial 42	java/io/IOException:<init>	(Ljava/lang/String;)V
    //   110: athrow
    //   111: astore_2
    //   112: aload_1
    //   113: invokevirtual 88	android/os/Parcel:recycle	()V
    //   116: aload_2
    //   117: athrow
    //   118: astore_2
    //   119: goto -18 -> 101
    // Local variable table:
    //   start	length	slot	name	signature
    //   0	122	0	this	ﹳ
    //   0	122	1	paramString	String
    //   10	63	2	localObject1	Object
    //   111	6	2	localObject2	Object
    //   118	1	2	localIllegalArgumentException	IllegalArgumentException
    // Exception table:
    //   from	to	target	type
    //   31	96	111	finally
    //   101	111	111	finally
    //   31	96	118	java/lang/IllegalArgumentException
  }
  
  public ﹳ(ql paramql)
  {
    this(azB, ˆ, ĭ);
  }
  
  public static void ˊ(Object paramObject, StringBuilder paramStringBuilder)
  {
    if (paramObject == null)
    {
      paramStringBuilder.append("null");
      return;
    }
    String str2 = paramObject.getClass().getSimpleName();
    String str1;
    if (str2 != null)
    {
      str1 = str2;
      if (str2.length() > 0) {}
    }
    else
    {
      str2 = paramObject.getClass().getName();
      int i = str2.lastIndexOf('.');
      str1 = str2;
      if (i > 0) {
        str1 = str2.substring(i + 1);
      }
    }
    paramStringBuilder.append(str1);
    paramStringBuilder.append('{');
    paramStringBuilder.append(Integer.toHexString(System.identityHashCode(paramObject)));
  }
  
  /* Error */
  public final String ﹺ()
  {
    // Byte code:
    //   0: invokestatic 48	android/os/Parcel:obtain	()Landroid/os/Parcel;
    //   3: astore_1
    //   4: aload_0
    //   5: getfield 23	o/ﹳ:ˆ	Ljava/lang/String;
    //   8: ldc 56
    //   10: invokevirtual 154	java/lang/String:getBytes	(Ljava/lang/String;)[B
    //   13: iconst_0
    //   14: invokestatic 158	android/util/Base64:encodeToString	([BI)Ljava/lang/String;
    //   17: astore_2
    //   18: aload_0
    //   19: getfield 25	o/ﹳ:ĭ	I
    //   22: invokestatic 161	java/lang/Integer:toString	(I)Ljava/lang/String;
    //   25: astore_3
    //   26: aload_0
    //   27: getfield 21	o/ﹳ:ī	Lcom/google/android/gms/ads/internal/client/AdRequestParcel;
    //   30: aload_1
    //   31: iconst_0
    //   32: invokevirtual 165	com/google/android/gms/ads/internal/client/AdRequestParcel:writeToParcel	(Landroid/os/Parcel;I)V
    //   35: aload_1
    //   36: invokevirtual 169	android/os/Parcel:marshall	()[B
    //   39: iconst_0
    //   40: invokestatic 158	android/util/Base64:encodeToString	([BI)Ljava/lang/String;
    //   43: astore 4
    //   45: new 106	java/lang/StringBuilder
    //   48: dup
    //   49: aload_2
    //   50: invokestatic 173	java/lang/String:valueOf	(Ljava/lang/Object;)Ljava/lang/String;
    //   53: invokevirtual 124	java/lang/String:length	()I
    //   56: iconst_2
    //   57: iadd
    //   58: aload_3
    //   59: invokestatic 173	java/lang/String:valueOf	(Ljava/lang/Object;)Ljava/lang/String;
    //   62: invokevirtual 124	java/lang/String:length	()I
    //   65: iadd
    //   66: aload 4
    //   68: invokestatic 173	java/lang/String:valueOf	(Ljava/lang/Object;)Ljava/lang/String;
    //   71: invokevirtual 124	java/lang/String:length	()I
    //   74: iadd
    //   75: invokespecial 175	java/lang/StringBuilder:<init>	(I)V
    //   78: aload_2
    //   79: invokevirtual 110	java/lang/StringBuilder:append	(Ljava/lang/String;)Ljava/lang/StringBuilder;
    //   82: ldc 30
    //   84: invokevirtual 110	java/lang/StringBuilder:append	(Ljava/lang/String;)Ljava/lang/StringBuilder;
    //   87: aload_3
    //   88: invokevirtual 110	java/lang/StringBuilder:append	(Ljava/lang/String;)Ljava/lang/StringBuilder;
    //   91: ldc 30
    //   93: invokevirtual 110	java/lang/StringBuilder:append	(Ljava/lang/String;)Ljava/lang/StringBuilder;
    //   96: aload 4
    //   98: invokevirtual 110	java/lang/StringBuilder:append	(Ljava/lang/String;)Ljava/lang/StringBuilder;
    //   101: invokevirtual 177	java/lang/StringBuilder:toString	()Ljava/lang/String;
    //   104: astore_2
    //   105: aload_1
    //   106: invokevirtual 88	android/os/Parcel:recycle	()V
    //   109: aload_2
    //   110: areturn
    //   111: ldc -77
    //   113: ldc -75
    //   115: invokestatic 187	android/util/Log:e	(Ljava/lang/String;Ljava/lang/String;)I
    //   118: pop
    //   119: aload_1
    //   120: invokevirtual 88	android/os/Parcel:recycle	()V
    //   123: goto +10 -> 133
    //   126: astore_2
    //   127: aload_1
    //   128: invokevirtual 88	android/os/Parcel:recycle	()V
    //   131: aload_2
    //   132: athrow
    //   133: ldc -67
    //   135: areturn
    //   136: astore_2
    //   137: goto -26 -> 111
    // Local variable table:
    //   start	length	slot	name	signature
    //   0	140	0	this	ﹳ
    //   3	125	1	localParcel	android.os.Parcel
    //   17	93	2	str1	String
    //   126	6	2	localObject	Object
    //   136	1	2	localUnsupportedEncodingException	java.io.UnsupportedEncodingException
    //   25	63	3	str2	String
    //   43	54	4	str3	String
    // Exception table:
    //   from	to	target	type
    //   4	105	126	finally
    //   111	119	126	finally
    //   4	105	136	java/io/UnsupportedEncodingException
  }
}

/* Location:
 * Qualified Name:     o.ﹳ
 * Java Class Version: 6 (50.0)
 * JD-Core Version:    0.7.1
 */