package o;

import android.content.ComponentName;
import android.content.Context;
import android.content.Intent;
import android.content.pm.PackageManager;
import com.eclipsim.gpstoolbox.monitor.GpsBroadcastReceiver;

public final class ﾚ
{
  public static float BA;
  public static float BB;
  public static float BC;
  public static String BD;
  public static int Ba = 1;
  public static int Bb = 0;
  public static int Bc = 0;
  public static int Bd = 0;
  public static int Be = 0;
  public static int Bf = 0;
  public static int Bg = 0;
  public static int Bh = 0;
  public static int Bi = 0;
  public static int Bj = 0;
  public static boolean Bk = false;
  public static boolean Bl;
  public static boolean Bm;
  public static boolean Bn;
  public static boolean Bo;
  public static boolean Bp;
  public static boolean Bq;
  public static boolean Br;
  public static boolean Bs;
  public static boolean Bt;
  public static float Bu;
  public static int Bv;
  public static int Bw;
  public static boolean Bx;
  public static boolean By;
  public static float Bz;
  private static int yP;
  private static int yQ;
  private static final byte[] yR = { 96, -39, 65, -48, 22, -22, -7, 8, -6 };
  public static long z = -1L;
  
  static
  {
    yP = 0;
    yQ = 1;
  }
  
  private static void ˊ(Context paramContext, boolean paramBoolean)
  {
    if (!paramBoolean) {
      paramContext.stopService(new Intent(paramContext, ף.class));
    }
    ComponentName localComponentName = new ComponentName(paramContext, GpsBroadcastReceiver.class);
    paramContext = paramContext.getPackageManager();
    int i;
    if (paramBoolean) {
      i = 1;
    } else {
      i = 2;
    }
    paramContext.setComponentEnabledSetting(localComponentName, i, 1);
  }
  
  private static String ч()
  {
    break label109;
    int n;
    int i1;
    int i2;
    int m;
    for (;;)
    {
      k = -n;
      n = j + 1;
      i1 = k + i - 5;
      do
      {
        i2 = 74;
        break;
        i = yQ + 15;
        yP = i % 128;
      } while (i % 2 != 0);
      break label215;
      arrayOfByte2[m] = ((byte)i1);
      if (m == 5) {
        break label184;
      }
      i = i1;
      j = n;
      k = m;
      break label171;
      label82:
      k = yQ + 35;
      yP = k % 128;
      if (k % 2 != 0) {
        break label195;
      }
    }
    label109:
    int i = 122;
    int j = 0 + 4;
    byte[] arrayOfByte1 = yR;
    int k = 0;
    byte[] arrayOfByte2 = new byte[6];
    for (;;)
    {
      i = i1;
      j = n;
      k = m;
      switch (i2)
      {
      case 74: 
      default: 
        break;
      case 72: 
        for (;;)
        {
          label171:
          n = arrayOfByte1[j];
          m = k + 1;
          break label82;
          label184:
          label195:
          do
          {
            return new String(arrayOfByte2, 0);
            break;
            arrayOfByte2[k] = ((byte)i);
          } while (k == 5);
        }
      }
      label215:
      i2 = 72;
    }
  }
  
  /* Error */
  public static void ՙ(Context paramContext)
  {
    // Byte code:
    //   0: goto +369 -> 369
    //   3: aload_2
    //   4: ldc -122
    //   6: iconst_1
    //   7: invokestatic 140	java/lang/Integer:toString	(I)Ljava/lang/String;
    //   10: invokeinterface 146 3 0
    //   15: invokestatic 150	java/lang/Integer:parseInt	(Ljava/lang/String;)I
    //   18: putstatic 63	o/ﾚ:Ba	I
    //   21: goto +633 -> 654
    //   24: aload_2
    //   25: ldc -104
    //   27: ldc -102
    //   29: invokeinterface 146 3 0
    //   34: invokestatic 160	java/lang/Float:parseFloat	(Ljava/lang/String;)F
    //   37: putstatic 162	o/ﾚ:BA	F
    //   40: goto +929 -> 969
    //   43: aload_2
    //   44: ldc -122
    //   46: iconst_1
    //   47: invokestatic 140	java/lang/Integer:toString	(I)Ljava/lang/String;
    //   50: invokeinterface 146 3 0
    //   55: invokestatic 150	java/lang/Integer:parseInt	(Ljava/lang/String;)I
    //   58: putstatic 63	o/ﾚ:Ba	I
    //   61: goto +593 -> 654
    //   64: iconst_3
    //   65: istore_1
    //   66: goto +158 -> 224
    //   69: fconst_0
    //   70: putstatic 162	o/ﾚ:BA	F
    //   73: goto +896 -> 969
    //   76: aload_2
    //   77: ldc -92
    //   79: iconst_0
    //   80: invokestatic 140	java/lang/Integer:toString	(I)Ljava/lang/String;
    //   83: invokeinterface 146 3 0
    //   88: invokestatic 150	java/lang/Integer:parseInt	(Ljava/lang/String;)I
    //   91: putstatic 75	o/ﾚ:Bg	I
    //   94: goto +82 -> 176
    //   97: getstatic 61	o/ﾚ:yQ	I
    //   100: bipush 119
    //   102: iadd
    //   103: istore_1
    //   104: iload_1
    //   105: sipush 128
    //   108: irem
    //   109: putstatic 59	o/ﾚ:yP	I
    //   112: iload_1
    //   113: iconst_2
    //   114: irem
    //   115: ifeq +6 -> 121
    //   118: goto +563 -> 681
    //   121: goto +719 -> 840
    //   124: aload_2
    //   125: ldc -104
    //   127: ldc -102
    //   129: invokeinterface 146 3 0
    //   134: invokestatic 160	java/lang/Float:parseFloat	(Ljava/lang/String;)F
    //   137: putstatic 162	o/ﾚ:BA	F
    //   140: goto +829 -> 969
    //   143: bipush 75
    //   145: istore_1
    //   146: goto +742 -> 888
    //   149: getstatic 59	o/ﾚ:yP	I
    //   152: bipush 73
    //   154: iadd
    //   155: istore_1
    //   156: iload_1
    //   157: sipush 128
    //   160: irem
    //   161: putstatic 61	o/ﾚ:yQ	I
    //   164: iload_1
    //   165: iconst_2
    //   166: irem
    //   167: ifne +6 -> 173
    //   170: goto +538 -> 708
    //   173: goto +675 -> 848
    //   176: aload_2
    //   177: ldc -90
    //   179: iconst_0
    //   180: invokestatic 140	java/lang/Integer:toString	(I)Ljava/lang/String;
    //   183: invokeinterface 146 3 0
    //   188: invokestatic 150	java/lang/Integer:parseInt	(Ljava/lang/String;)I
    //   191: putstatic 77	o/ﾚ:Bh	I
    //   194: goto -45 -> 149
    //   197: getstatic 61	o/ﾚ:yQ	I
    //   200: bipush 71
    //   202: iadd
    //   203: istore_1
    //   204: iload_1
    //   205: sipush 128
    //   208: irem
    //   209: putstatic 59	o/ﾚ:yP	I
    //   212: iload_1
    //   213: iconst_2
    //   214: irem
    //   215: ifeq +6 -> 221
    //   218: goto -154 -> 64
    //   221: goto +454 -> 675
    //   224: iload_1
    //   225: lookupswitch	default:+19->244, 33:+123->348
    //   244: goto +795 -> 1039
    //   247: ldc -89
    //   249: putstatic 169	o/ﾚ:Bu	F
    //   252: goto +434 -> 686
    //   255: iconst_0
    //   256: putstatic 73	o/ﾚ:Bf	I
    //   259: goto -216 -> 43
    //   262: iconst_1
    //   263: putstatic 83	o/ﾚ:Bk	Z
    //   266: return
    //   267: bipush 97
    //   269: istore_1
    //   270: goto +648 -> 918
    //   273: iconst_1
    //   274: putstatic 83	o/ﾚ:Bk	Z
    //   277: return
    //   278: iconst_0
    //   279: putstatic 75	o/ﾚ:Bg	I
    //   282: goto -106 -> 176
    //   285: ldc -86
    //   287: putstatic 172	o/ﾚ:Bv	I
    //   290: goto -17 -> 273
    //   293: iconst_0
    //   294: putstatic 67	o/ﾚ:Bc	I
    //   297: goto -221 -> 76
    //   300: aload_2
    //   301: ldc -82
    //   303: iconst_0
    //   304: invokestatic 140	java/lang/Integer:toString	(I)Ljava/lang/String;
    //   307: invokeinterface 146 3 0
    //   312: invokestatic 150	java/lang/Integer:parseInt	(Ljava/lang/String;)I
    //   315: putstatic 79	o/ﾚ:Bi	I
    //   318: goto +493 -> 811
    //   321: aload_2
    //   322: ldc -80
    //   324: iconst_0
    //   325: invokestatic 140	java/lang/Integer:toString	(I)Ljava/lang/String;
    //   328: invokeinterface 146 3 0
    //   333: invokestatic 150	java/lang/Integer:parseInt	(Ljava/lang/String;)I
    //   336: putstatic 73	o/ﾚ:Bf	I
    //   339: goto +651 -> 990
    //   342: bipush 28
    //   344: istore_1
    //   345: goto +573 -> 918
    //   348: aload_2
    //   349: ldc -78
    //   351: iconst_0
    //   352: invokestatic 140	java/lang/Integer:toString	(I)Ljava/lang/String;
    //   355: invokeinterface 146 3 0
    //   360: invokestatic 150	java/lang/Integer:parseInt	(Ljava/lang/String;)I
    //   363: putstatic 71	o/ﾚ:Be	I
    //   366: goto -45 -> 321
    //   369: aload_0
    //   370: ldc -77
    //   372: iconst_0
    //   373: invokestatic 185	android/preference/PreferenceManager:setDefaultValues	(Landroid/content/Context;IZ)V
    //   376: aload_0
    //   377: ldc -70
    //   379: iconst_0
    //   380: invokestatic 185	android/preference/PreferenceManager:setDefaultValues	(Landroid/content/Context;IZ)V
    //   383: aload_0
    //   384: ldc -69
    //   386: iconst_0
    //   387: invokestatic 185	android/preference/PreferenceManager:setDefaultValues	(Landroid/content/Context;IZ)V
    //   390: aload_0
    //   391: ldc -68
    //   393: iconst_0
    //   394: invokestatic 185	android/preference/PreferenceManager:setDefaultValues	(Landroid/content/Context;IZ)V
    //   397: aload_0
    //   398: ldc -67
    //   400: iconst_0
    //   401: invokestatic 185	android/preference/PreferenceManager:setDefaultValues	(Landroid/content/Context;IZ)V
    //   404: aload_0
    //   405: invokestatic 193	android/preference/PreferenceManager:getDefaultSharedPreferences	(Landroid/content/Context;)Landroid/content/SharedPreferences;
    //   408: astore_2
    //   409: aload_2
    //   410: ldc -61
    //   412: iconst_1
    //   413: invokeinterface 199 3 0
    //   418: putstatic 201	o/ﾚ:Bl	Z
    //   421: aload_2
    //   422: ldc -53
    //   424: iconst_1
    //   425: invokeinterface 199 3 0
    //   430: putstatic 205	o/ﾚ:Bo	Z
    //   433: aload_2
    //   434: ldc -49
    //   436: iconst_1
    //   437: invokeinterface 199 3 0
    //   442: putstatic 209	o/ﾚ:Bp	Z
    //   445: aload_2
    //   446: ldc -45
    //   448: iconst_0
    //   449: invokeinterface 199 3 0
    //   454: putstatic 213	o/ﾚ:Bq	Z
    //   457: aload_2
    //   458: ldc -41
    //   460: iconst_0
    //   461: invokeinterface 199 3 0
    //   466: putstatic 217	o/ﾚ:Br	Z
    //   469: aload_2
    //   470: ldc -37
    //   472: iconst_0
    //   473: invokeinterface 199 3 0
    //   478: putstatic 221	o/ﾚ:Bs	Z
    //   481: aload_2
    //   482: ldc -33
    //   484: iconst_1
    //   485: invokeinterface 199 3 0
    //   490: putstatic 225	o/ﾚ:Bt	Z
    //   493: aload_2
    //   494: ldc -29
    //   496: iconst_0
    //   497: invokeinterface 199 3 0
    //   502: putstatic 229	o/ﾚ:Bm	Z
    //   505: aload_2
    //   506: ldc -25
    //   508: iconst_0
    //   509: invokeinterface 199 3 0
    //   514: putstatic 233	o/ﾚ:Bn	Z
    //   517: aload_2
    //   518: ldc -21
    //   520: iconst_0
    //   521: invokeinterface 199 3 0
    //   526: putstatic 237	o/ﾚ:Bx	Z
    //   529: aload_2
    //   530: ldc -17
    //   532: iconst_1
    //   533: invokeinterface 199 3 0
    //   538: putstatic 241	o/ﾚ:By	Z
    //   541: aload_2
    //   542: ldc -13
    //   544: fconst_0
    //   545: invokeinterface 247 3 0
    //   550: putstatic 249	o/ﾚ:BB	F
    //   553: aload_2
    //   554: ldc -5
    //   556: fconst_0
    //   557: invokeinterface 247 3 0
    //   562: putstatic 253	o/ﾚ:BC	F
    //   565: aload_2
    //   566: ldc -1
    //   568: iconst_0
    //   569: invokeinterface 259 3 0
    //   574: putstatic 261	o/ﾚ:Bw	I
    //   577: aload_2
    //   578: invokestatic 263	o/ﾚ:ч	()Ljava/lang/String;
    //   581: invokevirtual 266	java/lang/String:intern	()Ljava/lang/String;
    //   584: lconst_0
    //   585: invokeinterface 270 4 0
    //   590: putstatic 87	o/ﾚ:z	J
    //   593: aload_2
    //   594: ldc_w 272
    //   597: aload_0
    //   598: ldc_w 273
    //   601: invokevirtual 275	android/content/Context:getString	(I)Ljava/lang/String;
    //   604: invokeinterface 146 3 0
    //   609: putstatic 277	o/ﾚ:BD	Ljava/lang/String;
    //   612: aload_2
    //   613: ldc_w 279
    //   616: fconst_0
    //   617: invokeinterface 247 3 0
    //   622: putstatic 281	o/ﾚ:Bz	F
    //   625: aload_2
    //   626: ldc_w 283
    //   629: iconst_0
    //   630: invokestatic 140	java/lang/Integer:toString	(I)Ljava/lang/String;
    //   633: invokeinterface 146 3 0
    //   638: invokestatic 150	java/lang/Integer:parseInt	(Ljava/lang/String;)I
    //   641: putstatic 81	o/ﾚ:Bj	I
    //   644: goto +111 -> 755
    //   647: iconst_0
    //   648: putstatic 65	o/ﾚ:Bb	I
    //   651: goto +82 -> 733
    //   654: aload_2
    //   655: ldc_w 285
    //   658: ldc_w 287
    //   661: invokeinterface 146 3 0
    //   666: invokestatic 150	java/lang/Integer:parseInt	(Ljava/lang/String;)I
    //   669: putstatic 172	o/ﾚ:Bv	I
    //   672: goto -575 -> 97
    //   675: bipush 33
    //   677: istore_1
    //   678: goto -454 -> 224
    //   681: iconst_0
    //   682: istore_1
    //   683: goto +256 -> 939
    //   686: aload_2
    //   687: ldc_w 289
    //   690: iconst_0
    //   691: invokestatic 140	java/lang/Integer:toString	(I)Ljava/lang/String;
    //   694: invokeinterface 146 3 0
    //   699: invokestatic 150	java/lang/Integer:parseInt	(Ljava/lang/String;)I
    //   702: putstatic 65	o/ﾚ:Bb	I
    //   705: goto +28 -> 733
    //   708: iconst_0
    //   709: istore_1
    //   710: goto +307 -> 1017
    //   713: iconst_0
    //   714: putstatic 81	o/ﾚ:Bj	I
    //   717: goto -593 -> 124
    //   720: goto -644 -> 76
    //   723: iconst_0
    //   724: putstatic 79	o/ﾚ:Bi	I
    //   727: goto +84 -> 811
    //   730: astore_0
    //   731: aload_0
    //   732: athrow
    //   733: aload_2
    //   734: ldc_w 291
    //   737: iconst_0
    //   738: invokestatic 140	java/lang/Integer:toString	(I)Ljava/lang/String;
    //   741: invokeinterface 146 3 0
    //   746: invokestatic 150	java/lang/Integer:parseInt	(Ljava/lang/String;)I
    //   749: putstatic 67	o/ﾚ:Bc	I
    //   752: goto +32 -> 784
    //   755: getstatic 59	o/ﾚ:yP	I
    //   758: istore_1
    //   759: iload_1
    //   760: bipush 19
    //   762: iadd
    //   763: istore_1
    //   764: iload_1
    //   765: sipush 128
    //   768: irem
    //   769: putstatic 61	o/ﾚ:yQ	I
    //   772: iload_1
    //   773: iconst_2
    //   774: irem
    //   775: ifne +6 -> 781
    //   778: goto -635 -> 143
    //   781: goto +182 -> 963
    //   784: getstatic 61	o/ﾚ:yQ	I
    //   787: bipush 43
    //   789: iadd
    //   790: istore_1
    //   791: iload_1
    //   792: sipush 128
    //   795: irem
    //   796: putstatic 59	o/ﾚ:yP	I
    //   799: iload_1
    //   800: iconst_2
    //   801: irem
    //   802: ifeq +6 -> 808
    //   805: goto -85 -> 720
    //   808: goto -732 -> 76
    //   811: aload_2
    //   812: ldc_w 293
    //   815: iconst_0
    //   816: invokestatic 140	java/lang/Integer:toString	(I)Ljava/lang/String;
    //   819: invokeinterface 146 3 0
    //   824: invokestatic 150	java/lang/Integer:parseInt	(Ljava/lang/String;)I
    //   827: putstatic 69	o/ﾚ:Bd	I
    //   830: goto -633 -> 197
    //   833: iconst_0
    //   834: putstatic 71	o/ﾚ:Be	I
    //   837: goto -516 -> 321
    //   840: iconst_1
    //   841: istore_1
    //   842: goto +97 -> 939
    //   845: astore_0
    //   846: aload_0
    //   847: athrow
    //   848: iconst_1
    //   849: istore_1
    //   850: goto +167 -> 1017
    //   853: aload_2
    //   854: ldc -82
    //   856: iconst_0
    //   857: invokestatic 140	java/lang/Integer:toString	(I)Ljava/lang/String;
    //   860: invokeinterface 146 3 0
    //   865: invokestatic 150	java/lang/Integer:parseInt	(Ljava/lang/String;)I
    //   868: putstatic 79	o/ﾚ:Bi	I
    //   871: goto -60 -> 811
    //   874: iconst_1
    //   875: putstatic 63	o/ﾚ:Ba	I
    //   878: goto -224 -> 654
    //   881: iconst_0
    //   882: putstatic 69	o/ﾚ:Bd	I
    //   885: goto -537 -> 348
    //   888: iload_1
    //   889: lookupswitch	default:+19->908, 50:+-765->124
    //   908: goto -884 -> 24
    //   911: iconst_0
    //   912: putstatic 77	o/ﾚ:Bh	I
    //   915: goto -615 -> 300
    //   918: iload_1
    //   919: lookupswitch	default:+17->936, 28:+-876->43
    //   936: goto -933 -> 3
    //   939: iload_1
    //   940: tableswitch	default:+20->960, 1:+-667->273
    //   960: goto -698 -> 262
    //   963: bipush 50
    //   965: istore_1
    //   966: goto -78 -> 888
    //   969: aload_2
    //   970: ldc_w 295
    //   973: ldc_w 297
    //   976: invokeinterface 146 3 0
    //   981: invokestatic 160	java/lang/Float:parseFloat	(Ljava/lang/String;)F
    //   984: putstatic 169	o/ﾚ:Bu	F
    //   987: goto -301 -> 686
    //   990: getstatic 59	o/ﾚ:yP	I
    //   993: bipush 85
    //   995: iadd
    //   996: istore_1
    //   997: iload_1
    //   998: sipush 128
    //   1001: irem
    //   1002: putstatic 61	o/ﾚ:yQ	I
    //   1005: iload_1
    //   1006: iconst_2
    //   1007: irem
    //   1008: ifne +6 -> 1014
    //   1011: goto -744 -> 267
    //   1014: goto -672 -> 342
    //   1017: iload_1
    //   1018: tableswitch	default:+18->1036, 1:+-718->300
    //   1036: goto -183 -> 853
    //   1039: aload_2
    //   1040: ldc -78
    //   1042: iconst_0
    //   1043: invokestatic 140	java/lang/Integer:toString	(I)Ljava/lang/String;
    //   1046: invokeinterface 146 3 0
    //   1051: invokestatic 150	java/lang/Integer:parseInt	(Ljava/lang/String;)I
    //   1054: putstatic 71	o/ﾚ:Be	I
    //   1057: goto -736 -> 321
    //   1060: astore_0
    //   1061: goto -187 -> 874
    //   1064: astore_0
    //   1065: goto -996 -> 69
    //   1068: astore_0
    //   1069: goto -791 -> 278
    //   1072: astore_0
    //   1073: goto -162 -> 911
    //   1076: astore_0
    //   1077: goto -354 -> 723
    //   1080: astore_0
    //   1081: goto -826 -> 255
    //   1084: astore_0
    //   1085: goto -252 -> 833
    //   1088: astore_0
    //   1089: goto -376 -> 713
    //   1092: astore_0
    //   1093: goto -808 -> 285
    //   1096: astore_0
    //   1097: goto -450 -> 647
    //   1100: astore_0
    //   1101: goto -808 -> 293
    //   1104: astore_0
    //   1105: goto -224 -> 881
    //   1108: astore_0
    //   1109: goto -862 -> 247
    // Local variable table:
    //   start	length	slot	name	signature
    //   0	1112	0	paramContext	Context
    //   65	953	1	i	int
    //   3	1037	2	localSharedPreferences	android.content.SharedPreferences
    // Exception table:
    //   from	to	target	type
    //   755	759	730	java/lang/Exception
    //   764	772	730	java/lang/Exception
    //   262	266	845	java/lang/Exception
    //   3	21	1060	java/lang/Exception
    //   43	61	1060	java/lang/Exception
    //   24	40	1064	java/lang/Exception
    //   124	140	1064	java/lang/Exception
    //   76	94	1068	java/lang/Exception
    //   176	194	1072	java/lang/Exception
    //   300	318	1076	java/lang/Exception
    //   853	871	1076	java/lang/Exception
    //   321	339	1080	java/lang/Exception
    //   348	366	1084	java/lang/Exception
    //   1039	1057	1084	java/lang/Exception
    //   625	644	1088	java/lang/Exception
    //   654	672	1092	java/lang/Exception
    //   686	705	1096	java/lang/Exception
    //   733	752	1100	java/lang/Exception
    //   811	830	1104	java/lang/Exception
    //   969	987	1108	java/lang/Exception
  }
  
  /* Error */
  public static void י(Context paramContext)
  {
    // Byte code:
    //   0: goto +30 -> 30
    //   3: getstatic 61	o/ﾚ:yQ	I
    //   6: bipush 81
    //   8: iadd
    //   9: istore_1
    //   10: iload_1
    //   11: sipush 128
    //   14: irem
    //   15: putstatic 59	o/ﾚ:yP	I
    //   18: iload_1
    //   19: iconst_2
    //   20: irem
    //   21: ifeq +6 -> 27
    //   24: goto +193 -> 217
    //   27: goto +185 -> 212
    //   30: aload_0
    //   31: invokestatic 193	android/preference/PreferenceManager:getDefaultSharedPreferences	(Landroid/content/Context;)Landroid/content/SharedPreferences;
    //   34: astore_3
    //   35: aload_3
    //   36: invokeinterface 302 1 0
    //   41: ldc -13
    //   43: getstatic 249	o/ﾚ:BB	F
    //   46: invokeinterface 308 3 0
    //   51: ldc -5
    //   53: getstatic 253	o/ﾚ:BC	F
    //   56: invokeinterface 308 3 0
    //   61: ldc_w 279
    //   64: getstatic 281	o/ﾚ:Bz	F
    //   67: invokeinterface 308 3 0
    //   72: ldc -1
    //   74: getstatic 261	o/ﾚ:Bw	I
    //   77: invokeinterface 312 3 0
    //   82: invokestatic 263	o/ﾚ:ч	()Ljava/lang/String;
    //   85: invokevirtual 266	java/lang/String:intern	()Ljava/lang/String;
    //   88: getstatic 87	o/ﾚ:z	J
    //   91: invokeinterface 316 4 0
    //   96: invokeinterface 319 1 0
    //   101: aload_3
    //   102: ldc_w 283
    //   105: iconst_0
    //   106: invokestatic 140	java/lang/Integer:toString	(I)Ljava/lang/String;
    //   109: invokeinterface 146 3 0
    //   114: invokestatic 150	java/lang/Integer:parseInt	(Ljava/lang/String;)I
    //   117: putstatic 81	o/ﾚ:Bj	I
    //   120: goto +11 -> 131
    //   123: astore_0
    //   124: aload_0
    //   125: athrow
    //   126: iconst_0
    //   127: istore_1
    //   128: goto +21 -> 149
    //   131: iconst_2
    //   132: getstatic 81	o/ﾚ:Bj	I
    //   135: if_icmpeq +6 -> 141
    //   138: goto +6 -> 144
    //   141: goto +153 -> 294
    //   144: iconst_1
    //   145: istore_1
    //   146: goto +105 -> 251
    //   149: iload_1
    //   150: tableswitch	default:+18->168, 1:+72->222
    //   168: goto +120 -> 288
    //   171: iconst_0
    //   172: putstatic 81	o/ﾚ:Bj	I
    //   175: goto -44 -> 131
    //   178: iconst_0
    //   179: istore_2
    //   180: goto +42 -> 222
    //   183: getstatic 59	o/ﾚ:yP	I
    //   186: istore_1
    //   187: iload_1
    //   188: bipush 81
    //   190: iadd
    //   191: istore_1
    //   192: iload_1
    //   193: sipush 128
    //   196: irem
    //   197: putstatic 61	o/ﾚ:yQ	I
    //   200: iload_1
    //   201: iconst_2
    //   202: irem
    //   203: ifne +6 -> 209
    //   206: goto -80 -> 126
    //   209: goto +90 -> 299
    //   212: iconst_0
    //   213: istore_1
    //   214: goto +14 -> 228
    //   217: iconst_1
    //   218: istore_1
    //   219: goto +9 -> 228
    //   222: aload_0
    //   223: iload_2
    //   224: invokestatic 321	o/ﾚ:ˊ	(Landroid/content/Context;Z)V
    //   227: return
    //   228: iload_1
    //   229: tableswitch	default:+19->248, 0:+46->275
    //   248: goto +35 -> 283
    //   251: iload_1
    //   252: tableswitch	default:+20->272, 0:+-74->178
    //   272: goto -269 -> 3
    //   275: iconst_1
    //   276: istore_2
    //   277: goto -94 -> 183
    //   280: astore_0
    //   281: aload_0
    //   282: athrow
    //   283: iconst_1
    //   284: istore_2
    //   285: goto -63 -> 222
    //   288: aload_0
    //   289: iconst_1
    //   290: invokestatic 321	o/ﾚ:ˊ	(Landroid/content/Context;Z)V
    //   293: return
    //   294: iconst_0
    //   295: istore_1
    //   296: goto -45 -> 251
    //   299: iconst_1
    //   300: istore_1
    //   301: goto -152 -> 149
    //   304: astore_3
    //   305: goto -134 -> 171
    // Local variable table:
    //   start	length	slot	name	signature
    //   0	308	0	paramContext	Context
    //   9	292	1	i	int
    //   179	106	2	bool	boolean
    //   34	68	3	localSharedPreferences	android.content.SharedPreferences
    //   304	1	3	localException	Exception
    // Exception table:
    //   from	to	target	type
    //   183	187	123	java/lang/Exception
    //   192	200	280	java/lang/Exception
    //   101	120	304	java/lang/Exception
  }
}

/* Location:
 * Qualified Name:     o.ﾚ
 * Java Class Version: 6 (50.0)
 * JD-Core Version:    0.7.1
 */